Workbook
Name FOOT_BRAND: Rules!$I$49:$I$51
Name NO_NAME_CN: Rules!$I$54:$I$56
Name SITE_GLASS: Rules!$I$54:$I$56

Sheet External Prices
A2: Price in EUR, EXW workshop | B2: Country | AG2: Factors | AH2: Pump + LC | AI2: Tank
A3: Overruling agreements | B3: Walk away | AG3: Overruling | AH3: =IF($B$3<>"None",VLOOKUP($B$3,Rules!$P$6:$X$57,9,FALSE),0) -> 0.001 | AI3: =IF($B$3<>"None",VLOOKUP($B$3,Rules!$Z$6:$AH$57,9,FALSE),0) -> 0.001
A4: Country | B4: United Kingdom | AG4: Country | AH4: =IF($AH$3<>0%,0,VLOOKUP($B$4, Rules!$A$6:$D$201, 4, FALSE)) -> 0 | AI4: =IF($AH$3<>0%,0,VLOOKUP($B$4, Rules!$A$6:$D$201, 4, FALSE)) -> 0
A5: Agent fee | B5: No | C5: =AH5 -> 0 | AG5: Agent | AH5: =IF($AH$3<>0%,0,IF($B$5 <> "Yes",0, VLOOKUP($B$4, Rules!$A$6:$D$201, 3,FALSE))) -> 0 | AI5: =IF($AH$3<>0%,0,IF($B$5 <> "Yes",0, VLOOKUP($B$4, Rules!$A$6:$D$201, 3,FALSE))) -> 0
A6: Negotiation fee | B6: Yes | C6: =AH6 -> 0 | AG6: Negotiation | AH6: =IF($AH$3<>0%,0,IF($B$6 <> "Yes",0, VLOOKUP($B$4, Rules!$A$6:$D$201, 2,FALSE))) -> 0 | AI6: =IF($AH$3<>0%,0,IF($B$6 <> "Yes",0, VLOOKUP($B$4, Rules!$A$6:$D$201, 2,FALSE))) -> 0
A7: Order "when" | B7: 2025 | AG7: Order "when" | AH7: =IF($AH$3<>0%,0,VLOOKUP($B$7, Rules!$F$6:$G$7, 2, FALSE)) -> 0 | AI7: =IF($AH$3<>0%,0,VLOOKUP($B$7, Rules!$F$6:$G$7, 2, FALSE)) -> 0
A8: Competetion | B8: Standard | AG8: Competetion | AH8: =IF($AH$3<>0%,0,VLOOKUP($B$8, Rules!$M$6:$N$7, 2,FALSE)) -> 0 | AI8: =IF($AH$3<>0%,0,VLOOKUP($B$8, Rules!$M$6:$N$7, 2,FALSE)) -> 0
A9: Client | B9: Any w. Agent | AG9: Client | AH9: =IF($AH$3<>0%,0,VLOOKUP($B$9, Rules!$I$6:$J$10, 2,FALSE)) -> 0 | AI9: =IF($AH$3<>0%,0,VLOOKUP($B$9, Rules!$I$6:$J$10, 2,FALSE)) -> 0
A10: Design level | B10: Standard | AG10: Design level | AH10: =IF($AH$3<>0%,0,VLOOKUP($B$10, Rules!$K$6:$L$7, 2,FALSE)) -> 0 | AI10: =IF($AH$3<>0%,0,VLOOKUP($B$10, Rules!$K$6:$L$7, 2,FALSE)) -> 0
AG12: Total | AH12: =(1/(1-AH3)/(1-AH4)/(1-AH7)/(1-AH5)/(1-AH6)/(1-AH9)/(1-AH10)/(1-AH8)) -> 1.001001 | AI12: =(1/(1-AI3)/(1-AI4)/(1-AI7)/(1-AI5)/(1-AI6)/(1-AI9)/(1-AI10)/(1-AI8)) -> 1.001001
A14: Technical adjustment | B14: Power | E14: 22 kW | F14: 22 kW | G14: 22 kW | H14: 22 kW | I14: 11 kW | J14: 11 kW | K14: 22 kW | L14: 22 kW | N14: 22 kW | O14: 22 kW | P14: 22 kW | Q14: 22 kW | R14: 22 kW | S14: 22 kW | T14: 22 kW | U14: 22 kW | V14: 22 kW | W14: 22 kW | X14: 30 kW | Y14: 55 kW | Z14: 22 kW | AA14: 22 kW | AB14: 55 kW | AC14: =B14 -> Power
B15: Extra powder inlets | P15: 0 | W15: 0 | X15: 2 | Y15: 0 | Z15: 2 | AA15: 2 | AB15: 0 | AC15: =B15 -> Extra powder inlets
B16: V50 TinkTop | H16: No | N16: Yes | O16: No | P16: No | R16: No | S16: No | T16: No | U16: No | V16: No | W16: No | X16: Yes | Y16: No | Z16: No | AA16: Yes | AB16: No | AC16: =B16 -> V50 TinkTop
B17: Vacuum pump | P17: 5.5 MS | W17: 5.5 SS | X17: 5.5 SS | Y17: 5.5 SS | Z17: 4.0 SS | AA17: 5.5 SS | AB17: 5.5 SS | AC17: =B17 -> Vacuum pump
B18: Foot brand | I18: MARTIN | J18: MARTIN | K18: MARTIN | L18: NGI | M18: MARTIN | N18: NGI | O18: MARTIN | P18: NGI | R18: MARTIN | S18: MARTIN | T18: MARTIN | U18: NGI | V18: NGI | W18: NGI | X18: NGI | Y18: NGI | Z18: MARTIN | AA18: NGI | AB18: NGI | AC18: =B18 -> Foot brand
B19: Site glass brand | P19: EBORA EU | R19: NONE | S19: NONE | T19: NONE | U19: EBORA EU | V19: EBORA EU | W19: EBORA EU | X19: EBORA EU | Y19: EBORA EU | Z19: EBORA EU | AA19: EBORA EU | AB19: EBORA EU | AC19: =B19 -> Site glass brand
B20: CIP opiton | P20: Yes | R20: No | S20: No | T20: No | U20: Yes | V20: Yes | W20: Yes | X20: Yes | Y20: Yes | Z20: Yes | AA20: Yes | AB20: Yes | AC20: =B20 -> CIP opiton
B21: Non-foam | P21: Yes | R21: No | S21: No | T21: No | U21: Yes | V21: Yes | W21: Yes | X21: Yes | Y21: Yes | Z21: Yes | AA21: Yes | AB21: Yes | AC21: =B21 -> Non-foam
B22: Tangential inlet | P22: Yes | R22: No | S22: No | T22: No | U22: No | V22: No | W22: Yes | X22: Yes | Y22: Yes | Z22: No | AA22: Yes | AB22: Yes | AC22: =B22 -> Tangential inlet
B23: Minor ingredients tank connection (MBV) | P23: Yes | W23: Yes | X23: Yes | Y23: Yes | Z23: Yes | AA23: Yes | AB23: Yes | AC23: =B23 -> Minor ingredients tank connection (MBV)
B24: 300 mm impeller system | P24: No | T24: No | X24: No | Y24: No | AA24: No | AB24: No | AC24: =B24 -> 300 mm impeller system
B25: Insulation & Cladding | P25: No | R25: No | S25: No | T25: No | U25: No | V25: No | W25: No | X25: Yes | Y25: No | Z25: No | AA25: No | AB25: No | AC25: =B25 -> Insulation & Cladding
B26: Jacket, Insulation & Cladding | P26: No | R26: No | S26: No | T26: No | U26: No | V26: No | W26: No | X26: No | Y26: No | Z26: Yes | AA26: Yes | AB26: Yes | AC26: =B26 -> Jacket, Insulation & Cladding
B27: Coaxial system | Z27: No | AA27: No | AB27: No | AC27: =B27 -> Coaxial system
B28: Double high-shear unit | S28: No | T28: No | Y28: Yes | Z28: No | AA28: No | AB28: Yes | AC28: =B28 -> Double high-shear unit
B29: Steam Injection nozzles | Z29: No | AA29: No | AB29: No | AC29: =B29 -> Steam Injection nozzles
B30: Culinary steam unit, 5 µm | Z30: No | AA30: No | AB30: No | AC30: =B30 -> Culinary steam unit, 5 µm
B31: 22L tank CIP | P31: No | W31: No | X31: No | Y31: No | Z31: No | AA31: No | AB31: No | AC31: =B31 -> 22L tank CIP | AD31: AL Manway, CIP spray ball, Acutator, IFM safety
B32: EU Documentation | I32: No | J32: No | K32: No | L32: No | M32: No | N32: No | O32: No | P32: No | Q32: Yes | R32: No | S32: No | T32: No | U32: No | V32: No | W32: No | X32: Yes | Y32: No | Z32: No | AA32: Yes | AB32: No | AC32: =B32 -> EU Documentation
B33: Polish & Grind external welds | P33: No | R33: No | S33: No | T33: No | U33: No | V33: No | W33: No | X33: No | Y33: No | Z33: Yes | AA33: No | AB33: No | AC33: =B33 -> Polish & Grind external welds
B34: Tangential Inlet hose | P34: No | R34: No | S34: No | T34: No | U34: No | V34: No | W34: No | X34: No | Y34: No | Z34: No | AA34: No | AB34: No | AC34: =B34 -> Tangential Inlet hose
B35: Outlet hose | P35: No | R35: No | S35: No | T35: No | U35: No | V35: No | W35: No | X35: No | Y35: No | Z35: No | AA35: No | AB35: No | AC35: =B35 -> Outlet hose
B36: Ingredients inlet hoses | P36: No | W36: No | X36: Yes | Y36: No | Z36: No | AA36: Yes | AB36: No | AC36: =B36 -> Ingredients inlet hoses
B38: Workshop | E38: DK | F38: DK | G38: DK | H38: DK | I38: VN | J38: VN | K38: VN | L38: VN | M38: VN | N38: VN | O38: VN | P38: VN | R38: VN | S38: VN | T38: VN | U38: VN | V38: VN | W38: VN | X38: VN | Y38: VN | Z38: VN | AA38: VN | AB38: VN
B39: Equipment | D39: Options | E39: Shear | F39: Shear L | G39: Injector | H39: Vortex | I39: Injector site assemble | J39: Shear | K39: Loop | L39: Injector | M39: Vortex site assemble | N39: Vortex | O39: Vortex VN 800 | P39: Vortex Vacuum 2000 | Q39: Bottom Shear | R39: LC 500 | S39: LC 1000 | T39: LC3000 | U39: Standard 500 | V39: Standard 1000 | W39: Vacuum 500 | X39: Vacuum 1000 | Y39: Vacuum 3000 | Z39: Process 500 | AA39: Process 1000 | AB39: Process 3000
B40: Price w/o options below | E40: =ROUNDUP('Internal Sales price'!E218*'External Prices'!$AH$12,0) -> 15593 | F40: =ROUNDUP('Internal Sales price'!F218*'External Prices'!$AH$12,0) -> 17480 | G40: =ROUNDUP('Internal Sales price'!H218*'External Prices'!$AH$12,0) -> 21743 | H40: =ROUNDUP('Internal Sales price'!J218*'External Prices'!$AH$12,0) -> 30134 | I40: =ROUNDUP('Internal Sales price'!L218*'External Prices'!$AH$12,0) -> 12413 | J40: =ROUNDUP('Internal Sales price'!N218*'External Prices'!$AH$12,0) -> 20058 | K40: =ROUNDUP('Internal Sales price'!P218*'External Prices'!$AH$12,0) -> 21869 | L40: =ROUNDUP('Internal Sales price'!R218*'External Prices'!$AH$12,0) -> 25050 | N40: =ROUNDUP('Internal Sales price'!V218*'External Prices'!$AH$12,0) -> 29811 | O40: =ROUNDUP('Internal Sales price'!X218*'External Prices'!$AH$12,0) -> 52357 | P40: =ROUNDUP('Internal Sales price'!Z218*'External Prices'!$AI$12,0) -> 104435 | Q40: =ROUNDUP('Internal Sales price'!AB218*'External Prices'!$AI$12,0) -> 15447 | R40: =ROUNDUP('Internal Sales price'!AD218*'External Prices'!$AH$12,0) -> 36809 | S40: =ROUNDUP('Internal Sales price'!AE218*'External Prices'!$AH$12,0) -> 37818 | T40: =ROUNDUP('Internal Sales price'!AF218*'External Prices'!$AH$12,0) -> 49680 | U40: =ROUNDUP('Internal Sales price'!AH218*'External Prices'!$AI$12,0) -> 56083 | V40: =ROUNDUP('Internal Sales price'!AI218*'External Prices'!$AI$12,0) -> 57191 | W40: =ROUNDUP('Internal Sales price'!AK218*'External Prices'!$AI$12,0) -> 95206 | X40: =ROUNDUP('Internal Sales price'!AL218*'External Prices'!$AI$12,0) -> 117464 | Y40: =ROUNDUP('Internal Sales price'!AM218*'External Prices'!$AI$12,0) -> 130198 | Z40: =ROUNDUP('Internal Sales price'!AO218*'External Prices'!$AI$12,0) -> 120644 | AA40: =ROUNDUP('Internal Sales price'!AP218*'External Prices'!$AI$12,0) -> 148861 | AB40: =ROUNDUP('Internal Sales price'!AQ218*'External Prices'!$AI$12,0) -> 170773
B41: Control Panel & VSD, 11 kW | D41: ='Internal Sales price'!$AS$218*'External Prices'!$AH$12 -> 5606.6659 | E41: ='Internal Sales price'!$AS$218*'External Prices'!$AH$12 -> 5606.6659 | F41: ='Internal Sales price'!$AS$218*'External Prices'!$AH$12 -> 5606.6659 | G41: ='Internal Sales price'!$AS$218*'External Prices'!$AH$12 -> 5606.6659 | H41: ='Internal Sales price'!$AS$218*'External Prices'!$AH$12 -> 5606.6659 | I41: ='Internal Sales price'!$AS$218*'External Prices'!$AH$12 -> 5606.6659 | J41: ='Internal Sales price'!$AS$218*'External Prices'!$AH$12 -> 5606.6659 | K41: ='Internal Sales price'!$AS$218*'External Prices'!$AH$12 -> 5606.6659 | L41: ='Internal Sales price'!$AS$218*'External Prices'!$AH$12 -> 5606.6659 | N41: ='Internal Sales price'!$AS$218*'External Prices'!$AH$12 -> 5606.6659 | O41: ='Internal Sales price'!$AS$218*'External Prices'!$AH$12 -> 5606.6659
B42: Control Panel & VSD, 15 kW | D42: ='Internal Sales price'!$AT$218*'External Prices'!$AH$12 -> 5766.122 | E42: ='Internal Sales price'!$AT$218*'External Prices'!$AH$12 -> 5766.122 | F42: ='Internal Sales price'!$AT$218*'External Prices'!$AH$12 -> 5766.122 | G42: ='Internal Sales price'!$AT$218*'External Prices'!$AH$12 -> 5766.122 | H42: ='Internal Sales price'!$AT$218*'External Prices'!$AH$12 -> 5766.122 | I42: ='Internal Sales price'!$AT$218*'External Prices'!$AH$12 -> 5766.122 | J42: ='Internal Sales price'!$AT$218*'External Prices'!$AH$12 -> 5766.122 | K42: ='Internal Sales price'!$AT$218*'External Prices'!$AH$12 -> 5766.122 | L42: ='Internal Sales price'!$AT$218*'External Prices'!$AH$12 -> 5766.122 | N42: ='Internal Sales price'!$AT$218*'External Prices'!$AH$12 -> 5766.122 | O42: ='Internal Sales price'!$AT$218*'External Prices'!$AH$12 -> 5766.122
B43: Control Panel & VSD, 18.5 kW | D43: ='Internal Sales price'!$AU$218*'External Prices'!$AH$12 -> 5925.5781 | E43: ='Internal Sales price'!$AU$218*'External Prices'!$AH$12 -> 5925.5781 | F43: ='Internal Sales price'!$AU$218*'External Prices'!$AH$12 -> 5925.5781 | G43: ='Internal Sales price'!$AU$218*'External Prices'!$AH$12 -> 5925.5781 | H43: ='Internal Sales price'!$AU$218*'External Prices'!$AH$12 -> 5925.5781 | I43: ='Internal Sales price'!$AU$218*'External Prices'!$AH$12 -> 5925.5781 | J43: ='Internal Sales price'!$AU$218*'External Prices'!$AH$12 -> 5925.5781 | K43: ='Internal Sales price'!$AU$218*'External Prices'!$AH$12 -> 5925.5781 | L43: ='Internal Sales price'!$AU$218*'External Prices'!$AH$12 -> 5925.5781 | N43: ='Internal Sales price'!$AU$218*'External Prices'!$AH$12 -> 5925.5781 | O43: ='Internal Sales price'!$AU$218*'External Prices'!$AH$12 -> 5925.5781
B44: Control Panel & VSD, 22 kW | D44: ='Internal Sales price'!$AV$218*'External Prices'!$AH$12 -> 6786.5913 | E44: ='Internal Sales price'!$AV$218*'External Prices'!$AH$12 -> 6786.5913 | F44: ='Internal Sales price'!$AV$218*'External Prices'!$AH$12 -> 6786.5913 | G44: ='Internal Sales price'!$AV$218*'External Prices'!$AH$12 -> 6786.5913 | H44: ='Internal Sales price'!$AV$218*'External Prices'!$AH$12 -> 6786.5913 | I44: ='Internal Sales price'!$AV$218*'External Prices'!$AH$12 -> 6786.5913 | J44: ='Internal Sales price'!$AV$218*'External Prices'!$AH$12 -> 6786.5913 | K44: ='Internal Sales price'!$AV$218*'External Prices'!$AH$12 -> 6786.5913 | L44: ='Internal Sales price'!$AV$218*'External Prices'!$AH$12 -> 6786.5913 | N44: ='Internal Sales price'!$AV$218*'External Prices'!$AH$12 -> 6786.5913 | O44: ='Internal Sales price'!$AV$218*'External Prices'!$AH$12 -> 6786.5913
A45: ERROR? | B45: Control Panel & VSD, 30 kW | D45: ='Internal Sales price'!$AW$218*'External Prices'!$AH$12 -> 5430.3028 | E45: ='Internal Sales price'!$AW$218*'External Prices'!$AH$12 -> 5430.3028 | F45: ='Internal Sales price'!$AW$218*'External Prices'!$AH$12 -> 5430.3028 | G45: ='Internal Sales price'!$AW$218*'External Prices'!$AH$12 -> 5430.3028 | H45: ='Internal Sales price'!$AW$218*'External Prices'!$AH$12 -> 5430.3028 | I45: ='Internal Sales price'!$AW$218*'External Prices'!$AH$12 -> 5430.3028 | J45: ='Internal Sales price'!$AW$218*'External Prices'!$AH$12 -> 5430.3028 | K45: ='Internal Sales price'!$AW$218*'External Prices'!$AH$12 -> 5430.3028 | L45: ='Internal Sales price'!$AW$218*'External Prices'!$AH$12 -> 5430.3028 | N45: ='Internal Sales price'!$AW$218*'External Prices'!$AH$12 -> 5430.3028 | O45: ='Internal Sales price'!$AW$218*'External Prices'!$AH$12 -> 5430.3028
B46: Frequency Converter 11 kW | D46: ='Internal Sales price'!$AX$218*'External Prices'!$AH$12 -> 2957.4438 | E46: ='Internal Sales price'!$AX$218*'External Prices'!$AH$12 -> 2957.4438 | F46: ='Internal Sales price'!$AX$218*'External Prices'!$AH$12 -> 2957.4438 | G46: ='Internal Sales price'!$AX$218*'External Prices'!$AH$12 -> 2957.4438 | H46: ='Internal Sales price'!$AX$218*'External Prices'!$AH$12 -> 2957.4438 | I46: ='Internal Sales price'!$AX$218*'External Prices'!$AH$12 -> 2957.4438 | J46: ='Internal Sales price'!$AX$218*'External Prices'!$AH$12 -> 2957.4438 | K46: ='Internal Sales price'!$AX$218*'External Prices'!$AH$12 -> 2957.4438 | L46: ='Internal Sales price'!$AX$218*'External Prices'!$AH$12 -> 2957.4438 | N46: ='Internal Sales price'!$AX$218*'External Prices'!$AH$12 -> 2957.4438 | O46: ='Internal Sales price'!$AX$218*'External Prices'!$AH$12 -> 2957.4438
B47: Frequency Converter 15 kW | D47: ='Internal Sales price'!$AY$218*'External Prices'!$AH$12 -> 3328.1543 | E47: ='Internal Sales price'!$AY$218*'External Prices'!$AH$12 -> 3328.1543 | F47: ='Internal Sales price'!$AY$218*'External Prices'!$AH$12 -> 3328.1543 | G47: ='Internal Sales price'!$AY$218*'External Prices'!$AH$12 -> 3328.1543 | H47: ='Internal Sales price'!$AY$218*'External Prices'!$AH$12 -> 3328.1543 | I47: ='Internal Sales price'!$AY$218*'External Prices'!$AH$12 -> 3328.1543 | J47: ='Internal Sales price'!$AY$218*'External Prices'!$AH$12 -> 3328.1543 | K47: ='Internal Sales price'!$AY$218*'External Prices'!$AH$12 -> 3328.1543 | L47: ='Internal Sales price'!$AY$218*'External Prices'!$AH$12 -> 3328.1543 | N47: ='Internal Sales price'!$AY$218*'External Prices'!$AH$12 -> 3328.1543 | O47: ='Internal Sales price'!$AY$218*'External Prices'!$AH$12 -> 3328.1543
B48: Frequency Converter 18.5 kW | D48: ='Internal Sales price'!$AZ$218*'External Prices'!$AH$12 -> 3625.767 | E48: ='Internal Sales price'!$AZ$218*'External Prices'!$AH$12 -> 3625.767 | F48: ='Internal Sales price'!$AZ$218*'External Prices'!$AH$12 -> 3625.767 | G48: ='Internal Sales price'!$AZ$218*'External Prices'!$AH$12 -> 3625.767 | H48: ='Internal Sales price'!$AZ$218*'External Prices'!$AH$12 -> 3625.767 | I48: ='Internal Sales price'!$AZ$218*'External Prices'!$AH$12 -> 3625.767 | J48: ='Internal Sales price'!$AZ$218*'External Prices'!$AH$12 -> 3625.767 | K48: ='Internal Sales price'!$AZ$218*'External Prices'!$AH$12 -> 3625.767 | L48: ='Internal Sales price'!$AZ$218*'External Prices'!$AH$12 -> 3625.767 | N48: ='Internal Sales price'!$AZ$218*'External Prices'!$AH$12 -> 3625.767 | O48: ='Internal Sales price'!$AZ$218*'External Prices'!$AH$12 -> 3625.767
B49: Frequency Converter 22 kW | D49: ='Internal Sales price'!$BA$218*'External Prices'!$AH$12 -> 3923.3797 | E49: ='Internal Sales price'!$BA$218*'External Prices'!$AH$12 -> 3923.3797 | F49: ='Internal Sales price'!$BA$218*'External Prices'!$AH$12 -> 3923.3797 | G49: ='Internal Sales price'!$BA$218*'External Prices'!$AH$12 -> 3923.3797 | H49: ='Internal Sales price'!$BA$218*'External Prices'!$AH$12 -> 3923.3797 | I49: ='Internal Sales price'!$BA$218*'External Prices'!$AH$12 -> 3923.3797 | J49: ='Internal Sales price'!$BA$218*'External Prices'!$AH$12 -> 3923.3797 | K49: ='Internal Sales price'!$BA$218*'External Prices'!$AH$12 -> 3923.3797 | L49: ='Internal Sales price'!$BA$218*'External Prices'!$AH$12 -> 3923.3797 | N49: ='Internal Sales price'!$BA$218*'External Prices'!$AH$12 -> 3923.3797 | O49: ='Internal Sales price'!$BA$218*'External Prices'!$AH$12 -> 3923.3797
A50: HTEN | B50: MixSing Standard control 22 kW | R50: ='Internal Sales price'!$BB$218*'External Prices'!$AI$12 -> 23285.441 | S50: ='Internal Sales price'!$BB$218*'External Prices'!$AI$12 -> 23285.441 | U50: ='Internal Sales price'!$BB$218*'External Prices'!$AI$12 -> 23285.441 | V50: ='Internal Sales price'!$BB$218*'External Prices'!$AI$12 -> 23285.441
A51: MIAC | B51: MixSing Vacuum control 22 kW | W51: ='Internal Sales price'!$BC$218*'External Prices'!$AI$12 -> 23598.645 | X51: ='Internal Sales price'!$BC$218*'External Prices'!$AI$12 -> 23598.645
A52: HTEN | B52: MixSing Process control 22 kW | Z52: ='Internal Sales price'!$BD$218*'External Prices'!$AI$12 -> 30304.496 | AA52: ='Internal Sales price'!$BD$218*'External Prices'!$AI$12 -> 30304.496
B53: Polish
A54: Extra | B54: ='Cost prices'!B140 -> Polish Vacuum 1000 top - bottom - shell internal 0.6 µm | R54: ='Cost prices'!$H140 /VLOOKUP($A54,Rules!$I$23:$J$27, 2, FALSE) / 7.45* $AH$12 -> 437.89977 | S54: ='Cost prices'!$H140 /VLOOKUP($A54,Rules!$I$23:$J$27, 2, FALSE) / 7.45* $AH$12 -> 437.89977 | U54: ='Cost prices'!$H140 /VLOOKUP($A54,Rules!$I$23:$J$27, 2, FALSE) / 7.45* $AI$12 -> 437.89977 | V54: ='Cost prices'!$H140 /VLOOKUP($A54,Rules!$I$23:$J$27, 2, FALSE) / 7.45* $AI$12 -> 437.89977 | W54: ='Cost prices'!$H140 /VLOOKUP($A54,Rules!$I$23:$J$27, 2, FALSE) / 7.45* $AI$12 -> 437.89977 | X54: ='Cost prices'!$H140 /VLOOKUP($A54,Rules!$I$23:$J$27, 2, FALSE) / 7.45* $AI$12 -> 437.89977 | Z54: ='Cost prices'!$H140 /VLOOKUP($A54,Rules!$I$23:$J$27, 2, FALSE) / 7.45* $AI$12 -> 437.89977 | AA54: ='Cost prices'!$H140 /VLOOKUP($A54,Rules!$I$23:$J$27, 2, FALSE) / 7.45* $AI$12 -> 437.89977
A55: Extra | B55: ='Cost prices'!B141 -> Polish Vacuum 1000 top - bottom - shell external 0.6 µm | R55: ='Cost prices'!$H141 /VLOOKUP($A55,Rules!$I$23:$J$27, 2, FALSE) / 7.45* $AH$12 -> 437.89977 | S55: ='Cost prices'!$H141 /VLOOKUP($A55,Rules!$I$23:$J$27, 2, FALSE) / 7.45* $AH$12 -> 437.89977 | U55: ='Cost prices'!$H141 /VLOOKUP($A55,Rules!$I$23:$J$27, 2, FALSE) / 7.45* $AI$12 -> 437.89977 | V55: ='Cost prices'!$H141 /VLOOKUP($A55,Rules!$I$23:$J$27, 2, FALSE) / 7.45* $AI$12 -> 437.89977 | W55: ='Cost prices'!$H141 /VLOOKUP($A55,Rules!$I$23:$J$27, 2, FALSE) / 7.45* $AI$12 -> 437.89977 | X55: ='Cost prices'!$H141 /VLOOKUP($A55,Rules!$I$23:$J$27, 2, FALSE) / 7.45* $AI$12 -> 437.89977 | Z55: ='Cost prices'!$H141 /VLOOKUP($A55,Rules!$I$23:$J$27, 2, FALSE) / 7.45* $AI$12 -> 437.89977 | AA55: ='Cost prices'!$H141 /VLOOKUP($A55,Rules!$I$23:$J$27, 2, FALSE) / 7.45* $AI$12 -> 437.89977
A56: Extra++ | B56: ='Cost prices'!B142 -> Polish Vacuum 1000 top - bottom - shell internal 0.3 µm | R56: ='Cost prices'!$H142 /VLOOKUP($A56,Rules!$I$23:$J$27, 2, FALSE) / 7.45* $AH$12 -> 903.16827 | S56: ='Cost prices'!$H142 /VLOOKUP($A56,Rules!$I$23:$J$27, 2, FALSE) / 7.45* $AH$12 -> 903.16827 | U56: ='Cost prices'!$H142 /VLOOKUP($A56,Rules!$I$23:$J$27, 2, FALSE) / 7.45* $AI$12 -> 903.16827 | V56: ='Cost prices'!$H142 /VLOOKUP($A56,Rules!$I$23:$J$27, 2, FALSE) / 7.45* $AI$12 -> 903.16827 | W56: ='Cost prices'!$H142 /VLOOKUP($A56,Rules!$I$23:$J$27, 2, FALSE) / 7.45* $AI$12 -> 903.16827 | X56: ='Cost prices'!$H142 /VLOOKUP($A56,Rules!$I$23:$J$27, 2, FALSE) / 7.45* $AI$12 -> 903.16827 | Z56: ='Cost prices'!$H142 /VLOOKUP($A56,Rules!$I$23:$J$27, 2, FALSE) / 7.45* $AI$12 -> 903.16827 | AA56: ='Cost prices'!$H142 /VLOOKUP($A56,Rules!$I$23:$J$27, 2, FALSE) / 7.45* $AI$12 -> 903.16827
A57: Extra++ | B57: ='Cost prices'!B143 -> Polish Vacuum 1000 top - bottom - shell external 0.3 µm | R57: ='Cost prices'!$H143 /VLOOKUP($A57,Rules!$I$23:$J$27, 2, FALSE) / 7.45* $AH$12 -> 903.16827 | S57: ='Cost prices'!$H143 /VLOOKUP($A57,Rules!$I$23:$J$27, 2, FALSE) / 7.45* $AH$12 -> 903.16827 | U57: ='Cost prices'!$H143 /VLOOKUP($A57,Rules!$I$23:$J$27, 2, FALSE) / 7.45* $AI$12 -> 903.16827 | V57: ='Cost prices'!$H143 /VLOOKUP($A57,Rules!$I$23:$J$27, 2, FALSE) / 7.45* $AI$12 -> 903.16827 | W57: ='Cost prices'!$H143 /VLOOKUP($A57,Rules!$I$23:$J$27, 2, FALSE) / 7.45* $AI$12 -> 903.16827 | X57: ='Cost prices'!$H143 /VLOOKUP($A57,Rules!$I$23:$J$27, 2, FALSE) / 7.45* $AI$12 -> 903.16827 | Z57: ='Cost prices'!$H143 /VLOOKUP($A57,Rules!$I$23:$J$27, 2, FALSE) / 7.45* $AI$12 -> 903.16827 | AA57: ='Cost prices'!$H143 /VLOOKUP($A57,Rules!$I$23:$J$27, 2, FALSE) / 7.45* $AI$12 -> 903.16827
A58: Minimum | B58: ='Cost prices'!B144 -> Polish Vacuum 1000 leg support external 0.6 µm - 4 pcs | U58: ='Cost prices'!$H144 /VLOOKUP($A58,Rules!$I$23:$J$27, 2, FALSE) / 7.45* $AI$12 -> 272.01303 | V58: ='Cost prices'!$H144 /VLOOKUP($A58,Rules!$I$23:$J$27, 2, FALSE) / 7.45* $AI$12 -> 272.01303 | W58: ='Cost prices'!$H144 /VLOOKUP($A58,Rules!$I$23:$J$27, 2, FALSE) / 7.45* $AI$12 -> 272.01303 | X58: ='Cost prices'!$H144 /VLOOKUP($A58,Rules!$I$23:$J$27, 2, FALSE) / 7.45* $AI$12 -> 272.01303 | Z58: ='Cost prices'!$H144 /VLOOKUP($A58,Rules!$I$23:$J$27, 2, FALSE) / 7.45* $AI$12 -> 272.01303 | AA58: ='Cost prices'!$H144 /VLOOKUP($A58,Rules!$I$23:$J$27, 2, FALSE) / 7.45* $AI$12 -> 272.01303
A59: Extra++ | B59: ='Cost prices'!B145 -> Polish Vacuum 1000 leg support external 0.3 µm - 4 pcs | U59: ='Cost prices'!$H145 /VLOOKUP($A59,Rules!$I$23:$J$27, 2, FALSE) / 7.45* $AI$12 -> 867.04154 | V59: ='Cost prices'!$H145 /VLOOKUP($A59,Rules!$I$23:$J$27, 2, FALSE) / 7.45* $AI$12 -> 867.04154 | W59: ='Cost prices'!$H145 /VLOOKUP($A59,Rules!$I$23:$J$27, 2, FALSE) / 7.45* $AI$12 -> 867.04154 | X59: ='Cost prices'!$H145 /VLOOKUP($A59,Rules!$I$23:$J$27, 2, FALSE) / 7.45* $AI$12 -> 867.04154 | Z59: ='Cost prices'!$H145 /VLOOKUP($A59,Rules!$I$23:$J$27, 2, FALSE) / 7.45* $AI$12 -> 867.04154 | AA59: ='Cost prices'!$H145 /VLOOKUP($A59,Rules!$I$23:$J$27, 2, FALSE) / 7.45* $AI$12 -> 867.04154
B60: Packaging for freight | D60: ='Internal Sales price'!$BJ$218*'External Prices'!$AH$12 -> 709.33688 | E60: ='Internal Sales price'!$BJ$218*'External Prices'!$AH$12 -> 709.33688 | F60: ='Internal Sales price'!$BJ$218*'External Prices'!$AH$12 -> 709.33688 | G60: ='Internal Sales price'!$BJ$218*'External Prices'!$AH$12 -> 709.33688 | H60: ='Internal Sales price'!$BJ$218*'External Prices'!$AH$12 -> 709.33688 | I60: Included | J60: Included | K60: Included | L60: Included | N60: ='Internal Sales price'!$BJ$218*'External Prices'!$AH$12 -> 709.33688 | O60: ='Internal Sales price'!$BJ$218*'External Prices'!$AH$12 -> 709.33688 | P60: Included | R60: Included | S60: Included | T60: Included | U60: Included | V60: Included | W60: Included | X60: Included | Y60: Included | Z60: Included | AA60: Included | AB60: Included
B61: EWX upgraded to FCA at workshop Vietnam | P61: =('Cost prices'!$H$117)/0.7/7.45*$AI$12 -> 642.71174 | R61: =('Cost prices'!$H$117)/0.7/7.45*$AH$12 -> 642.71174 | S61: =('Cost prices'!$H$117)/0.7/7.45*$AH$12 -> 642.71174 | T61: =('Cost prices'!$H$117)/0.7/7.45*$AH$12 -> 642.71174 | U61: =('Cost prices'!$H$117)/0.7/7.45*$AI$12 -> 642.71174 | V61: =('Cost prices'!$H$117)/0.7/7.45*$AI$12 -> 642.71174 | W61: =('Cost prices'!$H$117)/0.7/7.45*$AI$12 -> 642.71174 | X61: =('Cost prices'!$H$117)/0.7/7.45*$AI$12 -> 642.71174 | Y61: =('Cost prices'!$H$117)/0.7/7.45*$AI$12 -> 642.71174 | Z61: =('Cost prices'!$H$117)/0.7/7.45*$AI$12 -> 642.71174 | AA61: =('Cost prices'!$H$117)/0.7/7.45*$AI$12 -> 642.71174 | AB61: =('Cost prices'!$H$117)/0.7/7.45*$AI$12 -> 642.71174
B62: Seal flush | E62: ='Internal Sales price'!$BH$218*'External Prices'!$AH$12 -> 770.50242 | F62: ='Internal Sales price'!$BH$218*'External Prices'!$AH$12 -> 770.50242 | G62: ='Internal Sales price'!$BH$218*'External Prices'!$AH$12 -> 770.50242 | H62: ='Internal Sales price'!$BH$218*'External Prices'!$AH$12 -> 770.50242 | I62: ='Internal Sales price'!$BH$218*'External Prices'!$AH$12 -> 770.50242 | J62: ='Internal Sales price'!$BH$218*'External Prices'!$AH$12 -> 770.50242 | K62: ='Internal Sales price'!$BH$218*'External Prices'!$AH$12 -> 770.50242 | L62: ='Internal Sales price'!$BH$218*'External Prices'!$AH$12 -> 770.50242 | N62: ='Internal Sales price'!$BH$218*'External Prices'!$AH$12 -> 770.50242 | O62: ='Internal Sales price'!$BH$218*'External Prices'!$AH$12 -> 770.50242 | P62: Included | R62: Included | S62: Included | T62: Included | U62: Included | V62: Included | W62: Included | X62: Included | Y62: Included | Z62: Included | AA62: Included | AB62: Included
B63: Connection SMS/Clamp/Flange | E63: ='Internal Sales price'!$BI$218*'External Prices'!$AH$12 -> 225.33293 | F63: ='Internal Sales price'!$BI$218*'External Prices'!$AH$12 -> 225.33293 | G63: ='Internal Sales price'!$BI$218*'External Prices'!$AH$12 -> 225.33293 | H63: ='Internal Sales price'!$BI$218*'External Prices'!$AH$12 -> 225.33293 | I63: ='Internal Sales price'!$BI$218*'External Prices'!$AH$12 -> 225.33293 | J63: ='Internal Sales price'!$BI$218*'External Prices'!$AH$12 -> 225.33293 | K63: ='Internal Sales price'!$BI$218*'External Prices'!$AH$12 -> 225.33293 | L63: ='Internal Sales price'!$BI$218*'External Prices'!$AH$12 -> 225.33293 | N63: ='Internal Sales price'!$BI$218*'External Prices'!$AH$12 -> 225.33293 | O63: ='Internal Sales price'!$BI$218*'External Prices'!$AH$12 -> 225.33293 | P63: ='Internal Sales price'!$BI$218*'External Prices'!$AI$12 -> 225.33293 | R63: ='Internal Sales price'!$BI$218*'External Prices'!$AH$12 -> 225.33293 | S63: ='Internal Sales price'!$BI$218*'External Prices'!$AH$12 -> 225.33293 | T63: ='Internal Sales price'!$BI$218*'External Prices'!$AH$12 -> 225.33293 | U63: ='Internal Sales price'!$BI$218*'External Prices'!$AI$12 -> 225.33293 | V63: ='Internal Sales price'!$BI$218*'External Prices'!$AI$12 -> 225.33293 | W63: ='Internal Sales price'!$BI$218*'External Prices'!$AI$12 -> 225.33293 | X63: ='Internal Sales price'!$BI$218*'External Prices'!$AI$12 -> 225.33293 | Y63: ='Internal Sales price'!$BI$218*'External Prices'!$AI$12 -> 225.33293 | Z63: ='Internal Sales price'!$BI$218*'External Prices'!$AI$12 -> 225.33293 | AA63: ='Internal Sales price'!$BI$218*'External Prices'!$AI$12 -> 225.33293 | AB63: ='Internal Sales price'!$BI$218*'External Prices'!$AI$12 -> 225.33293
B64: Mesh | G64: ='Internal Sales price'!$BG$218*'External Prices'!$AH$12 -> 904.2645 | I64: Included | L64: Included
B65: Table | G65: ='Internal Sales price'!$BE$218*'External Prices'!$AH$12 -> 2432.5286 | H65: ='Internal Sales price'!$BE$218*'External Prices'!$AH$12 -> 2432.5286 | L65: ='Internal Sales price'!BL218*'External Prices'!$AH$12 -> 1085.7101 | N65: ='Internal Sales price'!BL218*'External Prices'!$AH$12 -> 1085.7101
A66: Minimum | B66: Injector VN - MOTOR BASE SUPPORT ASSY | I66: ='Cost prices'!H77 /VLOOKUP($A66,Rules!$I$23:$J$27, 2, FALSE) / 7.45* $AH$12 -> 564.42704 | J66: Included | K66: Included | L66: Included
A67: Minimum | B67: Injector VN - PUMP COVER | I67: ='Cost prices'!H78 /VLOOKUP($A67,Rules!$I$23:$J$27, 2, FALSE) / 7.45* $AH$12 -> 392.15212 | J67: Included | K67: Included | L67: Included
A68: Minimum | B68: PIPING WO - INJECTOR BODY ASSY | I68: ='Cost prices'!H79 /VLOOKUP($A68,Rules!$I$23:$J$27, 2, FALSE) / 7.45* $AH$12 -> 873.84186 | K68: Included | L68: Included
A69: Minimum | B69: Injector VN - INJECTOR BODY ASSY | I69: ='Cost prices'!H80 /VLOOKUP($A69,Rules!$I$23:$J$27, 2, FALSE) / 7.45* $AH$12 -> 418.22004 | L69: Included
A70: Minimum | B70: Injector VN - FUNNEL ASSEMBLY | C70: Added Full bore | I70: =('Cost prices'!H81+'Cost prices'!H28) /VLOOKUP($A70,Rules!$I$23:$J$27, 2, FALSE) / 7.45* $AH$12 + IFERROR( VLOOKUP( IF(OR('External Prices'!I18="MARTIN",'External Prices'!I18="MARTIN 3A"), "ST. STEEL BASE Ø 60 WITH BLUE EPDM VULCANISED RUBBER TILTING 10° ST. STEEL SCREW M16X150 WITH ST. STEEL BUSH 24X85 – USDA ACCEPTED", IF('External Prices'!I18="NGI", "Machine foot XH80-M20 x 150/85-M20 x 50", "" ) ), 'Cost prices'!$B$6:$H$376, 7, FALSE )*3, "") -> 2193.2186 | L70: Included
A71: Minimum | B71: Injector VN - TABLE ASSEMBLY | I71: ='Internal Sales price'!BL218*'External Prices'!$AH$12 -> 1085.7101
B72: Suction lance | G72: ='Internal Sales price'!$BK$218*'External Prices'!$AH$12 -> 5092.2966
A73: Mark-up
A74: Minimum | B74: Level Switch - Low | R74: ='Cost prices'!$H$263 /VLOOKUP($A74,Rules!$I$23:$J$27, 2, FALSE) / 7.45* $AH$12 -> 340.05435 | S74: ='Cost prices'!$H$263 /VLOOKUP($A74,Rules!$I$23:$J$27, 2, FALSE) / 7.45* $AH$12 -> 340.05435 | T74: ='Cost prices'!$H$263 /VLOOKUP($A74,Rules!$I$23:$J$27, 2, FALSE) / 7.45* $AH$12 -> 340.05435
A75: Minimum | B75: Level Switch - High | R75: ='Cost prices'!$H$263 /VLOOKUP($A75,Rules!$I$23:$J$27, 2, FALSE) / 7.45* $AH$12 -> 340.05435 | S75: ='Cost prices'!$H$263 /VLOOKUP($A75,Rules!$I$23:$J$27, 2, FALSE) / 7.45* $AH$12 -> 340.05435 | T75: ='Cost prices'!$H$263 /VLOOKUP($A75,Rules!$I$23:$J$27, 2, FALSE) / 7.45* $AH$12 -> 340.05435
A76: Minimum | B76: Temperature transmitter | P76: ='Cost prices'!$H$264 /VLOOKUP($A76,Rules!$I$23:$J$27, 2, FALSE) / 7.45* $AI$12 -> 313.88684 | R76: ='Cost prices'!$H$264 /VLOOKUP($A76,Rules!$I$23:$J$27, 2, FALSE) / 7.45* $AI$12 -> 313.88684 | S76: ='Cost prices'!$H$264 /VLOOKUP($A76,Rules!$I$23:$J$27, 2, FALSE) / 7.45* $AI$12 -> 313.88684 | T76: ='Cost prices'!$H$264 /VLOOKUP($A76,Rules!$I$23:$J$27, 2, FALSE) / 7.45* $AI$12 -> 313.88684 | W76: ='Cost prices'!$H$264 /VLOOKUP($A76,Rules!$I$23:$J$27, 2, FALSE) / 7.45* $AI$12 -> 313.88684 | X76: ='Cost prices'!$H$264 /VLOOKUP($A76,Rules!$I$23:$J$27, 2, FALSE) / 7.45* $AI$12 -> 313.88684 | Y76: ='Cost prices'!$H$264 /VLOOKUP($A76,Rules!$I$23:$J$27, 2, FALSE) / 7.45* $AI$12 -> 313.88684
A77: Standard | B77: CIP nozzles & Safety switch | R77: =('Cost prices'!$H$185*2+'Cost prices'!$H$265) /VLOOKUP($A77,Rules!$I$23:$J$27, 2, FALSE) / 7.45* $AH$12 -> 1475.6394 | S77: =('Cost prices'!$H$185*2+'Cost prices'!$H$265) /VLOOKUP($A77,Rules!$I$23:$J$27, 2, FALSE) / 7.45* $AH$12 -> 1475.6394 | T77: =('Cost prices'!$H$185*2+'Cost prices'!$H$265) /VLOOKUP($A77,Rules!$I$23:$J$27, 2, FALSE) / 7.45* $AH$12 -> 1475.6394
A78: Standard | B78: In-line via tank top | R78: =3500/ VLOOKUP($A78,Rules!$I$23:$J$27, 2, FALSE) / 7.45* $AH$12 -> 671.81275 | S78: =3500/ VLOOKUP($A78,Rules!$I$23:$J$27, 2, FALSE) / 7.45* $AH$12 -> 671.81275 | T78: =3500/ VLOOKUP($A78,Rules!$I$23:$J$27, 2, FALSE) / 7.45* $AH$12 -> 671.81275
A79: Standard | B79: Tank feet, two with load cells, hygenic | R79: =('Cost prices'!$H$223*2+'Cost prices'!$H$232*2)/ VLOOKUP($A79,Rules!$I$23:$J$27, 2, FALSE) / 7.45* $AH$12 -> 3527.5433 | S79: =('Cost prices'!$H$223*2+'Cost prices'!$H$232*2)/ VLOOKUP($A79,Rules!$I$23:$J$27, 2, FALSE) / 7.45* $AH$12 -> 3527.5433 | T79: =('Cost prices'!$H$223*2+'Cost prices'!$H$232*2)/ VLOOKUP($A79,Rules!$I$23:$J$27, 2, FALSE) / 7.45* $AH$12 -> 3527.5433
A80: Standard | B80: Tank feet, four standard, hygenic | R80: =('Cost prices'!$H$223*4)/ VLOOKUP($A80,Rules!$I$23:$J$27, 2, FALSE) / 7.45* $AH$12 -> 404.63858 | S80: =('Cost prices'!$H$223*4)/ VLOOKUP($A80,Rules!$I$23:$J$27, 2, FALSE) / 7.45* $AH$12 -> 404.63858 | T80: =('Cost prices'!$H$223*4)/ VLOOKUP($A80,Rules!$I$23:$J$27, 2, FALSE) / 7.45* $AH$12 -> 404.63858
A81: Standard | B81: Site glasses | R81: =('Cost prices'!$H$176+'Cost prices'!$H$177)/ VLOOKUP($A81,Rules!$I$23:$J$27, 2, FALSE) / 7.45* $AH$12 -> 3024.5606 | S81: =('Cost prices'!$H$176+'Cost prices'!$H$177)/ VLOOKUP($A81,Rules!$I$23:$J$27, 2, FALSE) / 7.45* $AH$12 -> 3024.5606 | T81: =('Cost prices'!$H$176+'Cost prices'!$H$177)/ VLOOKUP($A81,Rules!$I$23:$J$27, 2, FALSE) / 7.45* $AH$12 -> 3024.5606
A82: Standard | B82: Manway grid | R82: ='Cost prices'!$H$127/ VLOOKUP($A82,Rules!$I$23:$J$27, 2, FALSE) / 7.45* $AH$12 -> 963.37949 | S82: ='Cost prices'!$H$127/ VLOOKUP($A82,Rules!$I$23:$J$27, 2, FALSE) / 7.45* $AH$12 -> 963.37949 | T82: ='Cost prices'!$H$127/ VLOOKUP($A82,Rules!$I$23:$J$27, 2, FALSE) / 7.45* $AH$12 -> 963.37949
A83: Extra | B83: Tangential tank inlet w/o valve | R83: ='Cost prices'!$H$110/ VLOOKUP($A83,Rules!$I$23:$J$27, 2, FALSE) / 7.45* $AH$12 -> 525.47972 | S83: ='Cost prices'!$H$110/ VLOOKUP($A83,Rules!$I$23:$J$27, 2, FALSE) / 7.45* $AH$12 -> 525.47972 | T83: ='Cost prices'!$H$110/ VLOOKUP($A83,Rules!$I$23:$J$27, 2, FALSE) / 7.45* $AH$12 -> 525.47972
A84: Minimum | B84: Tangential tank inlet w. valve | R84: =('Cost prices'!$H$110+'Cost prices'!$H$196)/ VLOOKUP($A84,Rules!$I$23:$J$27, 2, FALSE) / 7.45* $AH$12 -> 796.08452 | S84: =('Cost prices'!$H$110+'Cost prices'!$H$196)/ VLOOKUP($A84,Rules!$I$23:$J$27, 2, FALSE) / 7.45* $AH$12 -> 796.08452 | T84: =('Cost prices'!$H$110+'Cost prices'!$H$196)/ VLOOKUP($A84,Rules!$I$23:$J$27, 2, FALSE) / 7.45* $AH$12 -> 796.08452 | U84: =('Cost prices'!$H$110+'Cost prices'!$H$196)/ VLOOKUP($A84,Rules!$I$23:$J$27, 2, FALSE) / 7.45* $AI$12 -> 796.08452 | V84: =('Cost prices'!$H$110+'Cost prices'!$H$196)/ VLOOKUP($A84,Rules!$I$23:$J$27, 2, FALSE) / 7.45* $AI$12 -> 796.08452 | W84: =('Cost prices'!$H$110+'Cost prices'!$H$196)/ VLOOKUP($A84,Rules!$I$23:$J$27, 2, FALSE) / 7.45* $AI$12 -> 796.08452 | X84: =('Cost prices'!$H$110+'Cost prices'!$H$196)/ VLOOKUP($A84,Rules!$I$23:$J$27, 2, FALSE) / 7.45* $AI$12 -> 796.08452 | Y84: =('Cost prices'!$H$110+'Cost prices'!$H$196)/ VLOOKUP($A84,Rules!$I$23:$J$27, 2, FALSE) / 7.45* $AI$12 -> 796.08452 | Z84: =('Cost prices'!$H$110+'Cost prices'!$H$196)/ VLOOKUP($A84,Rules!$I$23:$J$27, 2, FALSE) / 7.45* $AI$12 -> 796.08452 | AA84: =('Cost prices'!$H$110+'Cost prices'!$H$196)/ VLOOKUP($A84,Rules!$I$23:$J$27, 2, FALSE) / 7.45* $AI$12 -> 796.08452 | AB84: =('Cost prices'!$H$110+'Cost prices'!$H$196)/ VLOOKUP($A84,Rules!$I$23:$J$27, 2, FALSE) / 7.45* $AI$12 -> 796.08452
A85: Standard | B85: Back pressure valve | G85: ='Cost prices'!$H$197/ VLOOKUP($A85,Rules!$I$23:$J$27, 2, FALSE) / 7.45* $AH$12 -> 144.75461 | I85: ='Cost prices'!$H$197/ VLOOKUP($A85,Rules!$I$23:$J$27, 2, FALSE) / 7.45* $AH$12 -> 144.75461 | J85: ='Cost prices'!$H$197/ VLOOKUP($A85,Rules!$I$23:$J$27, 2, FALSE) / 7.45* $AH$12 -> 144.75461 | K85: ='Cost prices'!$H$197/ VLOOKUP($A85,Rules!$I$23:$J$27, 2, FALSE) / 7.45* $AH$12 -> 144.75461 | L85: ='Cost prices'!$H$197/ VLOOKUP($A85,Rules!$I$23:$J$27, 2, FALSE) / 7.45* $AH$12 -> 144.75461
A86: Minimum | B86: Minor ingredeints 22 liter hopper | P86: ='Cost prices'!$H$384/ VLOOKUP($A86,Rules!$I$23:$J$27, 2, FALSE) / 7.45* $AI$12 -> 946.54848 | W86: ='Cost prices'!$H$384/ VLOOKUP($A86,Rules!$I$23:$J$27, 2, FALSE) / 7.45* $AI$12 -> 946.54848 | X86: ='Cost prices'!$H$384/ VLOOKUP($A86,Rules!$I$23:$J$27, 2, FALSE) / 7.45* $AI$12 -> 946.54848 | Y86: ='Cost prices'!$H$384/ VLOOKUP($A86,Rules!$I$23:$J$27, 2, FALSE) / 7.45* $AI$12 -> 946.54848 | Z86: ='Cost prices'!$H$384/ VLOOKUP($A86,Rules!$I$23:$J$27, 2, FALSE) / 7.45* $AI$12 -> 946.54848 | AA86: ='Cost prices'!$H$384/ VLOOKUP($A86,Rules!$I$23:$J$27, 2, FALSE) / 7.45* $AI$12 -> 946.54848 | AB86: ='Cost prices'!$H$384/ VLOOKUP($A86,Rules!$I$23:$J$27, 2, FALSE) / 7.45* $AI$12 -> 946.54848
A87: Minimum | B87: Powder Hopper 100L system | W87: ='Cost prices'!$H304/ VLOOKUP($A87,Rules!$I$23:$J$27, 2, FALSE) / 7.45* $AI$12 -> 4207.0626 | X87: ='Cost prices'!$H304/ VLOOKUP($A87,Rules!$I$23:$J$27, 2, FALSE) / 7.45* $AI$12 -> 4207.0626 | Y87: ='Cost prices'!$H304/ VLOOKUP($A87,Rules!$I$23:$J$27, 2, FALSE) / 7.45* $AI$12 -> 4207.0626 | Z87: ='Cost prices'!$H304/ VLOOKUP($A87,Rules!$I$23:$J$27, 2, FALSE) / 7.45* $AI$12 -> 4207.0626 | AA87: ='Cost prices'!$H304/ VLOOKUP($A87,Rules!$I$23:$J$27, 2, FALSE) / 7.45* $AI$12 -> 4207.0626 | AB87: ='Cost prices'!$H304/ VLOOKUP($A87,Rules!$I$23:$J$27, 2, FALSE) / 7.45* $AI$12 -> 4207.0626
A88: Minimum | B88: Powder tipping station 25 kg w/o filter | P88: ='Cost prices'!$H375/ VLOOKUP($A88,Rules!$I$23:$J$27, 2, FALSE) / 7.45* $AI$12 -> 13775.924 | U88: ='Cost prices'!$H375/ VLOOKUP($A88,Rules!$I$23:$J$27, 2, FALSE) / 7.45* $AI$12 -> 13775.924 | V88: ='Cost prices'!$H375/ VLOOKUP($A88,Rules!$I$23:$J$27, 2, FALSE) / 7.45* $AI$12 -> 13775.924 | W88: ='Cost prices'!$H375/ VLOOKUP($A88,Rules!$I$23:$J$27, 2, FALSE) / 7.45* $AI$12 -> 13775.924 | X88: ='Cost prices'!$H375/ VLOOKUP($A88,Rules!$I$23:$J$27, 2, FALSE) / 7.45* $AI$12 -> 13775.924 | Y88: ='Cost prices'!$H375/ VLOOKUP($A88,Rules!$I$23:$J$27, 2, FALSE) / 7.45* $AI$12 -> 13775.924 | Z88: ='Cost prices'!$H375/ VLOOKUP($A88,Rules!$I$23:$J$27, 2, FALSE) / 7.45* $AI$12 -> 13775.924 | AA88: ='Cost prices'!$H375/ VLOOKUP($A88,Rules!$I$23:$J$27, 2, FALSE) / 7.45* $AI$12 -> 13775.924 | AB88: ='Cost prices'!$H375/ VLOOKUP($A88,Rules!$I$23:$J$27, 2, FALSE) / 7.45* $AI$12 -> 13775.924
A89: Minimum | B89: Powder tipping station 25 kg w. filter | P89: ='Cost prices'!$H376/ VLOOKUP($A89,Rules!$I$23:$J$27, 2, FALSE) / 7.45* $AI$12 -> 23204.665 | U89: ='Cost prices'!$H376/ VLOOKUP($A89,Rules!$I$23:$J$27, 2, FALSE) / 7.45* $AI$12 -> 23204.665 | V89: ='Cost prices'!$H376/ VLOOKUP($A89,Rules!$I$23:$J$27, 2, FALSE) / 7.45* $AI$12 -> 23204.665 | W89: ='Cost prices'!$H376/ VLOOKUP($A89,Rules!$I$23:$J$27, 2, FALSE) / 7.45* $AI$12 -> 23204.665 | X89: ='Cost prices'!$H376/ VLOOKUP($A89,Rules!$I$23:$J$27, 2, FALSE) / 7.45* $AI$12 -> 23204.665 | Y89: ='Cost prices'!$H376/ VLOOKUP($A89,Rules!$I$23:$J$27, 2, FALSE) / 7.45* $AI$12 -> 23204.665 | Z89: ='Cost prices'!$H376/ VLOOKUP($A89,Rules!$I$23:$J$27, 2, FALSE) / 7.45* $AI$12 -> 23204.665 | AA89: ='Cost prices'!$H376/ VLOOKUP($A89,Rules!$I$23:$J$27, 2, FALSE) / 7.45* $AI$12 -> 23204.665 | AB89: ='Cost prices'!$H376/ VLOOKUP($A89,Rules!$I$23:$J$27, 2, FALSE) / 7.45* $AI$12 -> 23204.665
A90: Minimum | B90: Powder tipping station 25 kg w.filter w. big bag w. hoist and Ibeam | P90: ='Cost prices'!$H377/ VLOOKUP($A90,Rules!$I$23:$J$27, 2, FALSE) / 7.45* $AI$12 -> 74796.85 | U90: ='Cost prices'!$H377/ VLOOKUP($A90,Rules!$I$23:$J$27, 2, FALSE) / 7.45* $AI$12 -> 74796.85 | V90: ='Cost prices'!$H377/ VLOOKUP($A90,Rules!$I$23:$J$27, 2, FALSE) / 7.45* $AI$12 -> 74796.85 | W90: ='Cost prices'!$H377/ VLOOKUP($A90,Rules!$I$23:$J$27, 2, FALSE) / 7.45* $AI$12 -> 74796.85 | X90: ='Cost prices'!$H377/ VLOOKUP($A90,Rules!$I$23:$J$27, 2, FALSE) / 7.45* $AI$12 -> 74796.85 | Y90: ='Cost prices'!$H377/ VLOOKUP($A90,Rules!$I$23:$J$27, 2, FALSE) / 7.45* $AI$12 -> 74796.85 | Z90: ='Cost prices'!$H377/ VLOOKUP($A90,Rules!$I$23:$J$27, 2, FALSE) / 7.45* $AI$12 -> 74796.85 | AA90: ='Cost prices'!$H377/ VLOOKUP($A90,Rules!$I$23:$J$27, 2, FALSE) / 7.45* $AI$12 -> 74796.85 | AB90: ='Cost prices'!$H377/ VLOOKUP($A90,Rules!$I$23:$J$27, 2, FALSE) / 7.45* $AI$12 -> 74796.85
A91: Minimum | B91: V50 TinkTop | P91: ='Cost prices'!$H$208/ VLOOKUP($A91,Rules!$I$23:$J$27, 2, FALSE) / 7.45* $AI$12 -> 467.44779 | U91: ='Cost prices'!$H$208/ VLOOKUP($A91,Rules!$I$23:$J$27, 2, FALSE) / 7.45* $AI$12 -> 467.44779 | V91: ='Cost prices'!$H$208/ VLOOKUP($A91,Rules!$I$23:$J$27, 2, FALSE) / 7.45* $AI$12 -> 467.44779 | W91: ='Cost prices'!$H$208/ VLOOKUP($A91,Rules!$I$23:$J$27, 2, FALSE) / 7.45* $AI$12 -> 467.44779 | X91: ='Cost prices'!$H$208/ VLOOKUP($A91,Rules!$I$23:$J$27, 2, FALSE) / 7.45* $AI$12 -> 467.44779 | Y91: ='Cost prices'!$H$208/ VLOOKUP($A91,Rules!$I$23:$J$27, 2, FALSE) / 7.45* $AI$12 -> 467.44779 | Z91: ='Cost prices'!$H$208/ VLOOKUP($A91,Rules!$I$23:$J$27, 2, FALSE) / 7.45* $AI$12 -> 467.44779 | AA91: ='Cost prices'!$H$208/ VLOOKUP($A91,Rules!$I$23:$J$27, 2, FALSE) / 7.45* $AI$12 -> 467.44779 | AB91: ='Cost prices'!$H$208/ VLOOKUP($A91,Rules!$I$23:$J$27, 2, FALSE) / 7.45* $AI$12 -> 467.44779
A92: Extra | B92: Water flush 25 liter hopper | P92: ='Cost prices'!$H$379/ VLOOKUP($A92,Rules!$I$23:$J$27, 2, FALSE) / 7.45* $AI$12 -> 1457.1359 | W92: ='Cost prices'!$H$379/ VLOOKUP($A92,Rules!$I$23:$J$27, 2, FALSE) / 7.45* $AI$12 -> 1457.1359 | X92: ='Cost prices'!$H$379/ VLOOKUP($A92,Rules!$I$23:$J$27, 2, FALSE) / 7.45* $AI$12 -> 1457.1359 | Y92: ='Cost prices'!$H$379/ VLOOKUP($A92,Rules!$I$23:$J$27, 2, FALSE) / 7.45* $AI$12 -> 1457.1359 | Z92: ='Cost prices'!$H$379/ VLOOKUP($A92,Rules!$I$23:$J$27, 2, FALSE) / 7.45* $AI$12 -> 1457.1359 | AA92: ='Cost prices'!$H$379/ VLOOKUP($A92,Rules!$I$23:$J$27, 2, FALSE) / 7.45* $AI$12 -> 1457.1359 | AB92: ='Cost prices'!$H$379/ VLOOKUP($A92,Rules!$I$23:$J$27, 2, FALSE) / 7.45* $AI$12 -> 1457.1359
A93: Standard | B93: X-ray on tank welds (100% body & 100% T-joints) | P93: ='Cost prices'!$H$121/ VLOOKUP($A93,Rules!$I$23:$J$27, 2, FALSE) / 7.45* $AI$12 -> 578.02769 | U93: ='Cost prices'!$H$121/ VLOOKUP($A93,Rules!$I$23:$J$27, 2, FALSE) / 7.45* $AI$12 -> 578.02769 | V93: ='Cost prices'!$H$121/ VLOOKUP($A93,Rules!$I$23:$J$27, 2, FALSE) / 7.45* $AI$12 -> 578.02769 | W93: ='Cost prices'!$H$121/ VLOOKUP($A93,Rules!$I$23:$J$27, 2, FALSE) / 7.45* $AI$12 -> 578.02769 | X93: ='Cost prices'!$H$121/ VLOOKUP($A93,Rules!$I$23:$J$27, 2, FALSE) / 7.45* $AI$12 -> 578.02769 | Y93: ='Cost prices'!$H$121/ VLOOKUP($A93,Rules!$I$23:$J$27, 2, FALSE) / 7.45* $AI$12 -> 578.02769 | Z93: ='Cost prices'!$H$121/ VLOOKUP($A93,Rules!$I$23:$J$27, 2, FALSE) / 7.45* $AI$12 -> 578.02769 | AA93: ='Cost prices'!$H$121/ VLOOKUP($A93,Rules!$I$23:$J$27, 2, FALSE) / 7.45* $AI$12 -> 578.02769 | AB93: ='Cost prices'!$H$121/ VLOOKUP($A93,Rules!$I$23:$J$27, 2, FALSE) / 7.45* $AI$12 -> 578.02769
A94: Extra | B94: PT nozzles, instruments, flanges on tank | P94: ='Cost prices'!$H$122/ VLOOKUP($A94,Rules!$I$23:$J$27, 2, FALSE) / 7.45* $AI$12 -> 1252.4634 | U94: ='Cost prices'!$H$122/ VLOOKUP($A94,Rules!$I$23:$J$27, 2, FALSE) / 7.45* $AI$12 -> 1252.4634 | V94: ='Cost prices'!$H$122/ VLOOKUP($A94,Rules!$I$23:$J$27, 2, FALSE) / 7.45* $AI$12 -> 1252.4634 | W94: ='Cost prices'!$H$122/ VLOOKUP($A94,Rules!$I$23:$J$27, 2, FALSE) / 7.45* $AI$12 -> 1252.4634 | X94: ='Cost prices'!$H$122/ VLOOKUP($A94,Rules!$I$23:$J$27, 2, FALSE) / 7.45* $AI$12 -> 1252.4634 | Y94: ='Cost prices'!$H$122/ VLOOKUP($A94,Rules!$I$23:$J$27, 2, FALSE) / 7.45* $AI$12 -> 1252.4634 | Z94: ='Cost prices'!$H$122/ VLOOKUP($A94,Rules!$I$23:$J$27, 2, FALSE) / 7.45* $AI$12 -> 1252.4634 | AA94: ='Cost prices'!$H$122/ VLOOKUP($A94,Rules!$I$23:$J$27, 2, FALSE) / 7.45* $AI$12 -> 1252.4634 | AB94: ='Cost prices'!$H$122/ VLOOKUP($A94,Rules!$I$23:$J$27, 2, FALSE) / 7.45* $AI$12 -> 1252.4634
A95: Standard | B95: Frame Tank AISI 304 | U95: ='Cost prices'!$H$123/ VLOOKUP($A95,Rules!$I$23:$J$27, 2, FALSE) / 7.45* $AI$12 -> 1513.8821 | V95: ='Cost prices'!$H$123/ VLOOKUP($A95,Rules!$I$23:$J$27, 2, FALSE) / 7.45* $AI$12 -> 1513.8821 | W95: ='Cost prices'!$H$123/ VLOOKUP($A95,Rules!$I$23:$J$27, 2, FALSE) / 7.45* $AI$12 -> 1513.8821 | X95: ='Cost prices'!$H$123/ VLOOKUP($A95,Rules!$I$23:$J$27, 2, FALSE) / 7.45* $AI$12 -> 1513.8821 | Y95: ='Cost prices'!$H$123/ VLOOKUP($A95,Rules!$I$23:$J$27, 2, FALSE) / 7.45* $AI$12 -> 1513.8821 | Z95: ='Cost prices'!$H$123/ VLOOKUP($A95,Rules!$I$23:$J$27, 2, FALSE) / 7.45* $AI$12 -> 1513.8821 | AA95: ='Cost prices'!$H$123/ VLOOKUP($A95,Rules!$I$23:$J$27, 2, FALSE) / 7.45* $AI$12 -> 1513.8821 | AB95: ='Cost prices'!$H$123/ VLOOKUP($A95,Rules!$I$23:$J$27, 2, FALSE) / 7.45* $AI$12 -> 1513.8821
A96: Minimum | B96: Freight Hoang Lam to Hamburg port, CIF | P96: ='Cost prices'!$H$124/ VLOOKUP($A96,Rules!$I$23:$J$27, 2, FALSE) / 7.45 -> 4765.6581 | U96: ='Cost prices'!$H$124/ VLOOKUP($A96,Rules!$I$23:$J$27, 2, FALSE) / 7.45 -> 4765.6581 | V96: ='Cost prices'!$H$124/ VLOOKUP($A96,Rules!$I$23:$J$27, 2, FALSE) / 7.45 -> 4765.6581 | W96: ='Cost prices'!$H$124/ VLOOKUP($A96,Rules!$I$23:$J$27, 2, FALSE) / 7.45 -> 4765.6581 | X96: ='Cost prices'!$H$124/ VLOOKUP($A96,Rules!$I$23:$J$27, 2, FALSE) / 7.45 -> 4765.6581 | Z96: ='Cost prices'!$H$124/ VLOOKUP($A96,Rules!$I$23:$J$27, 2, FALSE) / 7.45 -> 4765.6581 | AA96: ='Cost prices'!$H$124/ VLOOKUP($A96,Rules!$I$23:$J$27, 2, FALSE) / 7.45 -> 4765.6581
A97: Minimum | B97: Freight Hoang Lam to city in Germany, DAP (ship plus truck) | P97: ='Cost prices'!$H$125/ VLOOKUP($A97,Rules!$I$23:$J$27, 2, FALSE) / 7.45 -> 7666.4935 | U97: ='Cost prices'!$H$125/ VLOOKUP($A97,Rules!$I$23:$J$27, 2, FALSE) / 7.45 -> 7666.4935 | V97: ='Cost prices'!$H$125/ VLOOKUP($A97,Rules!$I$23:$J$27, 2, FALSE) / 7.45 -> 7666.4935 | W97: ='Cost prices'!$H$125/ VLOOKUP($A97,Rules!$I$23:$J$27, 2, FALSE) / 7.45 -> 7666.4935 | X97: ='Cost prices'!$H$125/ VLOOKUP($A97,Rules!$I$23:$J$27, 2, FALSE) / 7.45 -> 7666.4935 | Z97: ='Cost prices'!$H$125/ VLOOKUP($A97,Rules!$I$23:$J$27, 2, FALSE) / 7.45 -> 7666.4935 | AA97: ='Cost prices'!$H$125/ VLOOKUP($A97,Rules!$I$23:$J$27, 2, FALSE) / 7.45 -> 7666.4935
A98: Standard | B98: Extra MixSing Wall Valve incl. ThinkTop®, 1 pcs | P98: =('Cost prices'!$H$195+'Cost prices'!$H$208+'Cost prices'!$H$252)/ VLOOKUP($A98,Rules!$I$23:$J$27, 2, FALSE) / 7.45*$AI$12 -> 2220.8371 | U98: =('Cost prices'!$H$195+'Cost prices'!$H$208+'Cost prices'!$H$250)/ VLOOKUP($A98,Rules!$I$23:$J$27, 2, FALSE) / 7.45*$AI$12 -> 2231.4906 | V98: =('Cost prices'!$H$195+'Cost prices'!$H$208+'Cost prices'!$H$250)/ VLOOKUP($A98,Rules!$I$23:$J$27, 2, FALSE) / 7.45*$AI$12 -> 2231.4906 | W98: =('Cost prices'!$H$195+'Cost prices'!$H$208+'Cost prices'!$H$250)/ VLOOKUP($A98,Rules!$I$23:$J$27, 2, FALSE) / 7.45*$AI$12 -> 2231.4906 | X98: =('Cost prices'!$H$195+'Cost prices'!$H$208+'Cost prices'!$H$250)/ VLOOKUP($A98,Rules!$I$23:$J$27, 2, FALSE) / 7.45*$AI$12 -> 2231.4906 | Y98: =('Cost prices'!$H$195+'Cost prices'!$H$208+'Cost prices'!$H$250)/ VLOOKUP($A98,Rules!$I$23:$J$27, 2, FALSE) / 7.45*$AI$12 -> 2231.4906 | Z98: =('Cost prices'!$H$195+'Cost prices'!$H$208+'Cost prices'!$H$250)/ VLOOKUP($A98,Rules!$I$23:$J$27, 2, FALSE) / 7.45*$AI$12 -> 2231.4906 | AA98: =('Cost prices'!$H$195+'Cost prices'!$H$208+'Cost prices'!$H$250)/ VLOOKUP($A98,Rules!$I$23:$J$27, 2, FALSE) / 7.45*$AI$12 -> 2231.4906 | AB98: =('Cost prices'!$H$195+'Cost prices'!$H$208+'Cost prices'!$H$250)/ VLOOKUP($A98,Rules!$I$23:$J$27, 2, FALSE) / 7.45*$AI$12 -> 2231.4906
A99: Standard | B99: Bin lift system | Z99: =('Cost prices'!$H$463)/ VLOOKUP($A99,Rules!$I$23:$J$27, 2, FALSE) / 7.45*$AI$12 -> 41683.42 | AA99: =('Cost prices'!$H$463)/ VLOOKUP($A99,Rules!$I$23:$J$27, 2, FALSE) / 7.45*$AI$12 -> 41683.42 | AB99: =('Cost prices'!$H$463)/ VLOOKUP($A99,Rules!$I$23:$J$27, 2, FALSE) / 7.45*$AI$12 -> 41683.42
A100: Minimum | B100: German translation | P100: ='Cost prices'!$H$373/ VLOOKUP($A100,Rules!$I$23:$J$27, 2, FALSE) / 7.45* $AI$12 -> 1896.8831 | U100: ='Cost prices'!$H$373/ VLOOKUP($A100,Rules!$I$23:$J$27, 2, FALSE) / 7.45* $AI$12 -> 1896.8831 | V100: ='Cost prices'!$H$373/ VLOOKUP($A100,Rules!$I$23:$J$27, 2, FALSE) / 7.45* $AI$12 -> 1896.8831 | W100: ='Cost prices'!$H$373/ VLOOKUP($A100,Rules!$I$23:$J$27, 2, FALSE) / 7.45* $AI$12 -> 1896.8831 | X100: ='Cost prices'!$H$373/ VLOOKUP($A100,Rules!$I$23:$J$27, 2, FALSE) / 7.45* $AI$12 -> 1896.8831 | Y100: ='Cost prices'!$H$373/ VLOOKUP($A100,Rules!$I$23:$J$27, 2, FALSE) / 7.45* $AI$12 -> 1896.8831 | Z100: ='Cost prices'!$H$373/ VLOOKUP($A100,Rules!$I$23:$J$27, 2, FALSE) / 7.45* $AI$12 -> 1896.8831 | AA100: ='Cost prices'!$H$373/ VLOOKUP($A100,Rules!$I$23:$J$27, 2, FALSE) / 7.45* $AI$12 -> 1896.8831 | AB100: ='Cost prices'!$H$373/ VLOOKUP($A100,Rules!$I$23:$J$27, 2, FALSE) / 7.45* $AI$12 -> 1896.8831
A101: Standard | B101: Installation, Mechanical & Product supervision, daily rate | P101: ='Cost prices'!$H412/ VLOOKUP($A101,Rules!$I$23:$J$27, 2, FALSE) / 7.45* $AI$12 -> 578.02769 | R101: ='Cost prices'!$H412/ VLOOKUP($A101,Rules!$I$23:$J$27, 2, FALSE) / 7.45* $AH$12 -> 578.02769 | S101: ='Cost prices'!$H412/ VLOOKUP($A101,Rules!$I$23:$J$27, 2, FALSE) / 7.45* $AH$12 -> 578.02769 | T101: ='Cost prices'!$H412/ VLOOKUP($A101,Rules!$I$23:$J$27, 2, FALSE) / 7.45* $AH$12 -> 578.02769 | U101: ='Cost prices'!$H412/ VLOOKUP($A101,Rules!$I$23:$J$27, 2, FALSE) / 7.45* $AI$12 -> 578.02769 | V101: ='Cost prices'!$H412/ VLOOKUP($A101,Rules!$I$23:$J$27, 2, FALSE) / 7.45* $AI$12 -> 578.02769 | W101: ='Cost prices'!$H412/ VLOOKUP($A101,Rules!$I$23:$J$27, 2, FALSE) / 7.45* $AI$12 -> 578.02769 | X101: ='Cost prices'!$H412/ VLOOKUP($A101,Rules!$I$23:$J$27, 2, FALSE) / 7.45* $AI$12 -> 578.02769 | Y101: ='Cost prices'!$H412/ VLOOKUP($A101,Rules!$I$23:$J$27, 2, FALSE) / 7.45* $AI$12 -> 578.02769 | Z101: ='Cost prices'!$H412/ VLOOKUP($A101,Rules!$I$23:$J$27, 2, FALSE) / 7.45* $AI$12 -> 578.02769 | AA101: ='Cost prices'!$H412/ VLOOKUP($A101,Rules!$I$23:$J$27, 2, FALSE) / 7.45* $AI$12 -> 578.02769 | AB101: ='Cost prices'!$H412/ VLOOKUP($A101,Rules!$I$23:$J$27, 2, FALSE) / 7.45* $AI$12 -> 578.02769
A102: Minimum | B102: Mechanical & Product commissioning Malaysia, 5 days | P102: ='Cost prices'!$H413/ VLOOKUP($A102,Rules!$I$23:$J$27, 2, FALSE) / 7.45* $AI$12 -> 4646.8893 | R102: ='Cost prices'!$H413/ VLOOKUP($A102,Rules!$I$23:$J$27, 2, FALSE) / 7.45* $AH$12 -> 4646.8893 | S102: ='Cost prices'!$H413/ VLOOKUP($A102,Rules!$I$23:$J$27, 2, FALSE) / 7.45* $AH$12 -> 4646.8893 | T102: ='Cost prices'!$H413/ VLOOKUP($A102,Rules!$I$23:$J$27, 2, FALSE) / 7.45* $AH$12 -> 4646.8893 | U102: ='Cost prices'!$H413/ VLOOKUP($A102,Rules!$I$23:$J$27, 2, FALSE) / 7.45* $AI$12 -> 4646.8893 | V102: ='Cost prices'!$H413/ VLOOKUP($A102,Rules!$I$23:$J$27, 2, FALSE) / 7.45* $AI$12 -> 4646.8893 | W102: ='Cost prices'!$H413/ VLOOKUP($A102,Rules!$I$23:$J$27, 2, FALSE) / 7.45* $AI$12 -> 4646.8893 | X102: ='Cost prices'!$H413/ VLOOKUP($A102,Rules!$I$23:$J$27, 2, FALSE) / 7.45* $AI$12 -> 4646.8893 | Y102: ='Cost prices'!$H413/ VLOOKUP($A102,Rules!$I$23:$J$27, 2, FALSE) / 7.45* $AI$12 -> 4646.8893 | Z102: ='Cost prices'!$H413/ VLOOKUP($A102,Rules!$I$23:$J$27, 2, FALSE) / 7.45* $AI$12 -> 4646.8893 | AA102: ='Cost prices'!$H413/ VLOOKUP($A102,Rules!$I$23:$J$27, 2, FALSE) / 7.45* $AI$12 -> 4646.8893 | AB102: ='Cost prices'!$H413/ VLOOKUP($A102,Rules!$I$23:$J$27, 2, FALSE) / 7.45* $AI$12 -> 4646.8893
A103: Minimum | B103: Mechanical & Product commissioning Germany, 5 days | P103: ='Cost prices'!$H414/ VLOOKUP($A103,Rules!$I$23:$J$27, 2, FALSE) / 7.45* $AI$12 -> 7253.6808 | R103: ='Cost prices'!$H414/ VLOOKUP($A103,Rules!$I$23:$J$27, 2, FALSE) / 7.45* $AH$12 -> 7253.6808 | S103: ='Cost prices'!$H414/ VLOOKUP($A103,Rules!$I$23:$J$27, 2, FALSE) / 7.45* $AH$12 -> 7253.6808 | T103: ='Cost prices'!$H414/ VLOOKUP($A103,Rules!$I$23:$J$27, 2, FALSE) / 7.45* $AH$12 -> 7253.6808 | U103: ='Cost prices'!$H414/ VLOOKUP($A103,Rules!$I$23:$J$27, 2, FALSE) / 7.45* $AI$12 -> 7253.6808 | V103: ='Cost prices'!$H414/ VLOOKUP($A103,Rules!$I$23:$J$27, 2, FALSE) / 7.45* $AI$12 -> 7253.6808 | W103: ='Cost prices'!$H414/ VLOOKUP($A103,Rules!$I$23:$J$27, 2, FALSE) / 7.45* $AI$12 -> 7253.6808 | X103: ='Cost prices'!$H414/ VLOOKUP($A103,Rules!$I$23:$J$27, 2, FALSE) / 7.45* $AI$12 -> 7253.6808 | Y103: ='Cost prices'!$H414/ VLOOKUP($A103,Rules!$I$23:$J$27, 2, FALSE) / 7.45* $AI$12 -> 7253.6808 | Z103: ='Cost prices'!$H414/ VLOOKUP($A103,Rules!$I$23:$J$27, 2, FALSE) / 7.45* $AI$12 -> 7253.6808 | AA103: ='Cost prices'!$H414/ VLOOKUP($A103,Rules!$I$23:$J$27, 2, FALSE) / 7.45* $AI$12 -> 7253.6808 | AB103: ='Cost prices'!$H414/ VLOOKUP($A103,Rules!$I$23:$J$27, 2, FALSE) / 7.45* $AI$12 -> 7253.6808
A104: Minimum | B104: Mechanical & Product commissioning Zambia, 5 days | P104: ='Cost prices'!$H415/ VLOOKUP($A104,Rules!$I$23:$J$27, 2, FALSE) / 7.45* $AI$12 -> 5780.2769 | R104: ='Cost prices'!$H415/ VLOOKUP($A104,Rules!$I$23:$J$27, 2, FALSE) / 7.45* $AH$12 -> 5780.2769 | S104: ='Cost prices'!$H415/ VLOOKUP($A104,Rules!$I$23:$J$27, 2, FALSE) / 7.45* $AH$12 -> 5780.2769 | T104: ='Cost prices'!$H415/ VLOOKUP($A104,Rules!$I$23:$J$27, 2, FALSE) / 7.45* $AH$12 -> 5780.2769 | U104: ='Cost prices'!$H415/ VLOOKUP($A104,Rules!$I$23:$J$27, 2, FALSE) / 7.45* $AI$12 -> 5780.2769 | V104: ='Cost prices'!$H415/ VLOOKUP($A104,Rules!$I$23:$J$27, 2, FALSE) / 7.45* $AI$12 -> 5780.2769 | W104: ='Cost prices'!$H415/ VLOOKUP($A104,Rules!$I$23:$J$27, 2, FALSE) / 7.45* $AI$12 -> 5780.2769 | X104: ='Cost prices'!$H415/ VLOOKUP($A104,Rules!$I$23:$J$27, 2, FALSE) / 7.45* $AI$12 -> 5780.2769 | Y104: ='Cost prices'!$H415/ VLOOKUP($A104,Rules!$I$23:$J$27, 2, FALSE) / 7.45* $AI$12 -> 5780.2769 | Z104: ='Cost prices'!$H415/ VLOOKUP($A104,Rules!$I$23:$J$27, 2, FALSE) / 7.45* $AI$12 -> 5780.2769 | AA104: ='Cost prices'!$H415/ VLOOKUP($A104,Rules!$I$23:$J$27, 2, FALSE) / 7.45* $AI$12 -> 5780.2769 | AB104: ='Cost prices'!$H415/ VLOOKUP($A104,Rules!$I$23:$J$27, 2, FALSE) / 7.45* $AI$12 -> 5780.2769
...

Sheet Internal Sales price
E1: Shear | F1: Shear L | H1: Injector | J1: Vortex | L1: Injector site assemble | N1: Shear VN | P1: Loop VN | R1: Injector VN | T1: Vortex site assemble | V1: Vortex VN | X1: Vortex VN 800 | Z1: Vortex Vacuum 2000 | AB1: Bottom Shear | AD1: LC 500 | AE1: LC 1000 | AF1: LC 3000 | AH1: Standard 500 | AI1: Standard 1000 | AK1: Vacuum 500 | AL1: Vacuum 1000 | AM1: Vacuum 3000 | AO1: Process 500 | AP1: Process 1000 | AQ1: Process 3000 | AS1: Control Panel & VSD, 11 kW | AT1: Control Panel & VSD, 15 kW | AU1: Control Panel & VSD, 18.5 kW | AV1: Control Panel & VSD, 22 kW | AW1: Control Panel & VSD, 30 kW | AX1: Frequency Converter 11 kW | AY1: Frequency Converter 15 kW | AZ1: Frequency Converter 18.5 kW | BA1: Frequency Converter 22 kW | BB1: MixSing Standard control 22 kW | BC1: MixSing Vacuum control 22 kW | BD1: MixSing Process control 22 kW | BE1: Table | BG1: Mesh | BH1: Seal flush | BI1: Connection to Client | BJ1: Packaging | BK1: Suction lance | BL1: Injector VN - TABLE ASSEMBLY
BC2: MIAC
E3: DK | F3: DK | H3: DK | J3: DK | L3: VN | N3: VN | R3: VN | T3: VN | V3: VN | X3: VN | Z3: VN | AB3: DK | AD3: VN | AE3: VN | AF3: VN | AH3: VN | AI3: VN | AK3: VN | AL3: VN | AM3: VN | AO3: VN | AP3: VN | AQ3: VN | AS3: VN | AT3: VN | AU3: VN | AV3: VN | AW3: VN | AX3: DK | AY3: DK | AZ3: DK | BA3: DK | BE3: DK | BG3: DK | BH3: DK
A4: TPS essiential package
B5: xx Mixer, diameter | E5: 160mm | F5: 160mm | Z5: 160mm | AB5: 160mm | AD5: 160mm | AE5: 160mm | AF5: 300mm | AK5: 160mm | AL5: 160mm | AM5: 300mm | AO5: 160mm | AP5: 160mm | AQ5: 300mm
B6: Motor consol | E6: =VLOOKUP($B6,'Cost prices'!$B$6:$H$538,7, FALSE) -> 5081 | F6: =VLOOKUP($B6,'Cost prices'!$B$6:$H$538,7, FALSE) -> 5081 | H6: =VLOOKUP($B6,'Cost prices'!$B$6:$H$538,7, FALSE) -> 5081 | J6: =VLOOKUP($B6,'Cost prices'!$B$6:$H$538,7, FALSE) -> 5081 | L6: =VLOOKUP($B6,'Cost prices'!$B$6:$H$538,7, FALSE) -> 5081 | N6: =VLOOKUP($B6,'Cost prices'!$B$6:$H$538,7, FALSE) -> 5081 | P6: =VLOOKUP($B6,'Cost prices'!$B$6:$H$538,7, FALSE) -> 5081 | R6: =VLOOKUP($B6,'Cost prices'!$B$6:$H$538,7, FALSE) -> 5081 | T6: =VLOOKUP($B6,'Cost prices'!$B$6:$H$538,7, FALSE) -> 5081 | V6: =VLOOKUP($B6,'Cost prices'!$B$6:$H$538,7, FALSE) -> 5081 | X6: =VLOOKUP($B6,'Cost prices'!$B$6:$H$538,7, FALSE) -> 5081 | Z6: =IF('External Prices'!P$24="No",VLOOKUP($B6,'Cost prices'!$B$6:$H$538,7,FALSE),VLOOKUP($B6,'Cost prices'!$B$6:$H$538,7,FALSE)*2) -> 5081 | AB6: =VLOOKUP($B6,'Cost prices'!$B$6:$H$538,7, FALSE) -> 5081 | AD6: =VLOOKUP($B6,'Cost prices'!$B$6:$H$538,7, FALSE) -> 5081 | AE6: =VLOOKUP($B6,'Cost prices'!$B$6:$H$538,7, FALSE)* IF('External Prices'!S$28<>"No",2,1) -> 5081 | AF6: =IF('External Prices'!T$24="No",VLOOKUP($B6,'Cost prices'!$B$6:$H$538,7,FALSE),VLOOKUP($B6,'Cost prices'!$B$6:$H$538,7,FALSE)*2)* IF('External Prices'!T$28<>"No",2,1) -> 5081 | AH6: =VLOOKUP($B6,'Cost prices'!$B$6:$H$538,7, FALSE) -> 5081 | AI6: =VLOOKUP($B6,'Cost prices'!$B$6:$H$538,7, FALSE) -> 5081 | AK6: =VLOOKUP($B6,'Cost prices'!$B$6:$H$538,7, FALSE) -> 5081 | AL6: =IF('External Prices'!X$24="No",VLOOKUP($B6,'Cost prices'!$B$6:$H$538,7,FALSE),VLOOKUP($B6,'Cost prices'!$B$6:$H$538,7,FALSE)*2) -> 5081 | AM6: =IF('External Prices'!Y$24="No",VLOOKUP($B6,'Cost prices'!$B$6:$H$538,7,FALSE),VLOOKUP($B6,'Cost prices'!$B$6:$H$538,7,FALSE)*2)* IF('External Prices'!Y$28<>"No",2,1) -> 10162 | AO6: =VLOOKUP($B6,'Cost prices'!$B$6:$H$538,7, FALSE)* IF('External Prices'!Z$28<>"No",2,1) -> 5081 | AP6: =IF('External Prices'!AA$24="No",VLOOKUP($B6,'Cost prices'!$B$6:$H$538,7,FALSE),VLOOKUP($B6,'Cost prices'!$B$6:$H$538,7,FALSE)*2)* IF('External Prices'!AA$28<>"No",2,1) -> 5081 | AQ6: =IF('External Prices'!AB$24="No",VLOOKUP($B6,'Cost prices'!$B$6:$H$538,7,FALSE),VLOOKUP($B6,'Cost prices'!$B$6:$H$538,7,FALSE)*2)* IF('External Prices'!AB$28<>"No",2,1) -> 10162
B7: Stator | E7: =VLOOKUP($B7,'Cost prices'!$B$6:$H$538,7, FALSE) -> 4720 | F7: =VLOOKUP($B7,'Cost prices'!$B$6:$H$538,7, FALSE) -> 4720 | H7: =VLOOKUP($B7,'Cost prices'!$B$6:$H$538,7, FALSE) -> 4720 | J7: =VLOOKUP($B7,'Cost prices'!$B$6:$H$538,7, FALSE) -> 4720 | L7: =VLOOKUP($B7,'Cost prices'!$B$6:$H$538,7, FALSE) -> 4720 | N7: =VLOOKUP($B7,'Cost prices'!$B$6:$H$538,7, FALSE) -> 4720 | P7: =VLOOKUP($B7,'Cost prices'!$B$6:$H$538,7, FALSE) -> 4720 | R7: =VLOOKUP($B7,'Cost prices'!$B$6:$H$538,7, FALSE) -> 4720 | T7: =VLOOKUP($B7,'Cost prices'!$B$6:$H$538,7, FALSE) -> 4720 | V7: =VLOOKUP($B7,'Cost prices'!$B$6:$H$538,7, FALSE) -> 4720 | X7: =VLOOKUP($B7,'Cost prices'!$B$6:$H$538,7, FALSE) -> 4720 | Z7: =IF('External Prices'!P$24="No",VLOOKUP($B7,'Cost prices'!$B$6:$H$538,7,FALSE),VLOOKUP($B7,'Cost prices'!$B$6:$H$538,7,FALSE)*1.5) -> 4720 | AB7: =VLOOKUP($B7,'Cost prices'!$B$6:$H$538,7, FALSE) -> 4720 | AD7: =VLOOKUP($B7,'Cost prices'!$B$6:$H$538,7, FALSE) -> 4720 | AE7: =VLOOKUP($B7,'Cost prices'!$B$6:$H$538,7, FALSE)* IF('External Prices'!S$28<>"No",2,1) -> 4720 | AF7: =IF('External Prices'!T$24="No",VLOOKUP($B7,'Cost prices'!$B$6:$H$538,7,FALSE),VLOOKUP($B7,'Cost prices'!$B$6:$H$538,7,FALSE)*1.5)* IF('External Prices'!T$28<>"No",2,1) -> 4720 | AH7: =VLOOKUP($B7,'Cost prices'!$B$6:$H$538,7, FALSE) -> 4720 | AI7: =VLOOKUP($B7,'Cost prices'!$B$6:$H$538,7, FALSE) -> 4720 | AK7: =VLOOKUP($B7,'Cost prices'!$B$6:$H$538,7, FALSE) -> 4720 | AL7: =IF('External Prices'!X$24="No",VLOOKUP($B7,'Cost prices'!$B$6:$H$538,7,FALSE),VLOOKUP($B7,'Cost prices'!$B$6:$H$538,7,FALSE)*1.5) -> 4720 | AM7: =IF('External Prices'!Y$24="No",VLOOKUP($B7,'Cost prices'!$B$6:$H$538,7,FALSE),VLOOKUP($B7,'Cost prices'!$B$6:$H$538,7,FALSE)*1.5)* IF('External Prices'!Y$28<>"No",2,1) -> 9440 | AO7: =VLOOKUP($B7,'Cost prices'!$B$6:$H$538,7, FALSE)* IF('External Prices'!Z$28<>"No",2,1) -> 4720 | AP7: =IF('External Prices'!AA$24="No",VLOOKUP($B7,'Cost prices'!$B$6:$H$538,7,FALSE),VLOOKUP($B7,'Cost prices'!$B$6:$H$538,7,FALSE)*1.5)* IF('External Prices'!AA$28<>"No",2,1) -> 4720 | AQ7: =IF('External Prices'!AB$24="No",VLOOKUP($B7,'Cost prices'!$B$6:$H$538,7,FALSE),VLOOKUP($B7,'Cost prices'!$B$6:$H$538,7,FALSE)*1.5)* IF('External Prices'!AB$28<>"No",2,1) -> 9440
B8: Impeller | E8: =VLOOKUP($B8,'Cost prices'!$B$6:$H$538,7, FALSE) -> 4307 | F8: =VLOOKUP($B8,'Cost prices'!$B$6:$H$538,7, FALSE) -> 4307 | H8: =VLOOKUP($B8,'Cost prices'!$B$6:$H$538,7, FALSE) -> 4307 | J8: =VLOOKUP($B8,'Cost prices'!$B$6:$H$538,7, FALSE) -> 4307 | L8: =VLOOKUP($B8,'Cost prices'!$B$6:$H$538,7, FALSE) -> 4307 | N8: =VLOOKUP($B8,'Cost prices'!$B$6:$H$538,7, FALSE) -> 4307 | P8: =VLOOKUP($B8,'Cost prices'!$B$6:$H$538,7, FALSE) -> 4307 | R8: =VLOOKUP($B8,'Cost prices'!$B$6:$H$538,7, FALSE) -> 4307 | T8: =VLOOKUP($B8,'Cost prices'!$B$6:$H$538,7, FALSE) -> 4307 | V8: =VLOOKUP($B8,'Cost prices'!$B$6:$H$538,7, FALSE) -> 4307 | X8: =VLOOKUP($B8,'Cost prices'!$B$6:$H$538,7, FALSE) -> 4307 | Z8: =IF('External Prices'!P$24="No",VLOOKUP($B8,'Cost prices'!$B$6:$H$538,7,FALSE),VLOOKUP($B8,'Cost prices'!$B$6:$H$538,7,FALSE)*1.5) -> 4307 | AB8: =VLOOKUP($B8,'Cost prices'!$B$6:$H$538,7, FALSE) -> 4307 | AD8: =VLOOKUP($B8,'Cost prices'!$B$6:$H$538,7, FALSE) -> 4307 | AE8: =VLOOKUP($B8,'Cost prices'!$B$6:$H$538,7, FALSE)* IF('External Prices'!S$28<>"No",2,1) -> 4307 | AF8: =IF('External Prices'!T$24="No",VLOOKUP($B8,'Cost prices'!$B$6:$H$538,7,FALSE),VLOOKUP($B8,'Cost prices'!$B$6:$H$538,7,FALSE)*1.5)* IF('External Prices'!T$28<>"No",2,1) -> 4307 | AH8: =VLOOKUP($B8,'Cost prices'!$B$6:$H$538,7, FALSE) -> 4307 | AI8: =VLOOKUP($B8,'Cost prices'!$B$6:$H$538,7, FALSE) -> 4307 | AK8: =VLOOKUP($B8,'Cost prices'!$B$6:$H$538,7, FALSE) -> 4307 | AL8: =IF('External Prices'!X$24="No",VLOOKUP($B8,'Cost prices'!$B$6:$H$538,7,FALSE),VLOOKUP($B8,'Cost prices'!$B$6:$H$538,7,FALSE)*1.5) -> 4307 | AM8: =IF('External Prices'!Y$24="No",VLOOKUP($B8,'Cost prices'!$B$6:$H$538,7,FALSE),VLOOKUP($B8,'Cost prices'!$B$6:$H$538,7,FALSE)*1.5)* IF('External Prices'!Y$28<>"No",2,1) -> 8614 | AO8: =VLOOKUP($B8,'Cost prices'!$B$6:$H$538,7, FALSE)* IF('External Prices'!Z$28<>"No",2,1) -> 4307 | AP8: =IF('External Prices'!AA$24="No",VLOOKUP($B8,'Cost prices'!$B$6:$H$538,7,FALSE),VLOOKUP($B8,'Cost prices'!$B$6:$H$538,7,FALSE)*1.5)* IF('External Prices'!AA$28<>"No",2,1) -> 4307 | AQ8: =IF('External Prices'!AB$24="No",VLOOKUP($B8,'Cost prices'!$B$6:$H$538,7,FALSE),VLOOKUP($B8,'Cost prices'!$B$6:$H$538,7,FALSE)*1.5)* IF('External Prices'!AB$28<>"No",2,1) -> 8614
B9: Pump house | E9: =VLOOKUP($B9,'Cost prices'!$B$6:$H$538,7, FALSE) -> 8591 | F9: =VLOOKUP($B9,'Cost prices'!$B$6:$H$538,7, FALSE) -> 8591 | H9: =VLOOKUP($B9,'Cost prices'!$B$6:$H$538,7, FALSE) -> 8591 | J9: =VLOOKUP($B9,'Cost prices'!$B$6:$H$538,7, FALSE) -> 8591 | L9: =VLOOKUP($B9,'Cost prices'!$B$6:$H$538,7, FALSE) -> 8591 | N9: =VLOOKUP($B9,'Cost prices'!$B$6:$H$538,7, FALSE) -> 8591 | P9: =VLOOKUP($B9,'Cost prices'!$B$6:$H$538,7, FALSE) -> 8591 | R9: =VLOOKUP($B9,'Cost prices'!$B$6:$H$538,7, FALSE) -> 8591 | T9: =VLOOKUP($B9,'Cost prices'!$B$6:$H$538,7, FALSE) -> 8591 | V9: =VLOOKUP($B9,'Cost prices'!$B$6:$H$538,7, FALSE) -> 8591 | X9: =VLOOKUP($B9,'Cost prices'!$B$6:$H$538,7, FALSE) -> 8591
A10: Not used | B10: Bottom
B11: Shaft seal | E11: =VLOOKUP($B11,'Cost prices'!$B$6:$H$538,7, FALSE) -> 1005 | F11: =VLOOKUP($B11,'Cost prices'!$B$6:$H$538,7, FALSE) -> 1005 | H11: =VLOOKUP($B11,'Cost prices'!$B$6:$H$538,7, FALSE) -> 1005 | J11: =VLOOKUP($B11,'Cost prices'!$B$6:$H$538,7, FALSE) -> 1005 | L11: =VLOOKUP($B11,'Cost prices'!$B$6:$H$538,7, FALSE) -> 1005 | N11: =VLOOKUP($B11,'Cost prices'!$B$6:$H$538,7, FALSE) -> 1005 | P11: =VLOOKUP($B11,'Cost prices'!$B$6:$H$538,7, FALSE) -> 1005 | R11: =VLOOKUP($B11,'Cost prices'!$B$6:$H$538,7, FALSE) -> 1005 | T11: =VLOOKUP($B11,'Cost prices'!$B$6:$H$538,7, FALSE) -> 1005 | V11: =VLOOKUP($B11,'Cost prices'!$B$6:$H$538,7, FALSE) -> 1005 | X11: =VLOOKUP($B11,'Cost prices'!$B$6:$H$538,7, FALSE) -> 1005 | Z11: =VLOOKUP($B11,'Cost prices'!$B$6:$H$538,7, FALSE) -> 1005 | AB11: =VLOOKUP($B11,'Cost prices'!$B$6:$H$538,7, FALSE) -> 1005 | AD11: =VLOOKUP($B11,'Cost prices'!$B$6:$H$538,7, FALSE) -> 1005 | AE11: =VLOOKUP($B11,'Cost prices'!$B$6:$H$538,7, FALSE)* IF('External Prices'!S$28<>"No",2,1) -> 1005 | AF11: =VLOOKUP($B11,'Cost prices'!$B$6:$H$538,7, FALSE)* IF('External Prices'!T$28<>"No",2,1) -> 1005 | AH11: =VLOOKUP($B11,'Cost prices'!$B$6:$H$538,7, FALSE) -> 1005 | AI11: =VLOOKUP($B11,'Cost prices'!$B$6:$H$538,7, FALSE) -> 1005 | AK11: =VLOOKUP($B11,'Cost prices'!$B$6:$H$538,7, FALSE) -> 1005 | AL11: =VLOOKUP($B11,'Cost prices'!$B$6:$H$538,7, FALSE) -> 1005 | AM11: =VLOOKUP($B11,'Cost prices'!$B$6:$H$538,7, FALSE)* IF('External Prices'!Y$28<>"No",2,1) -> 2010 | AO11: =VLOOKUP($B11,'Cost prices'!$B$6:$H$538,7, FALSE)* IF('External Prices'!Z$28<>"No",2,1) -> 1005 | AP11: =VLOOKUP($B11,'Cost prices'!$B$6:$H$538,7, FALSE)* IF('External Prices'!AA$28<>"No",2,1) -> 1005 | AQ11: =VLOOKUP($B11,'Cost prices'!$B$6:$H$538,7, FALSE)* IF('External Prices'!AB$28<>"No",2,1) -> 2010
B12: Shaft | E12: =VLOOKUP($B12,'Cost prices'!$B$6:$H$538,7, FALSE) -> Incl Seneberg | F12: =VLOOKUP($B12,'Cost prices'!$B$6:$H$538,7, FALSE) -> Incl Seneberg | H12: =VLOOKUP($B12,'Cost prices'!$B$6:$H$538,7, FALSE) -> Incl Seneberg | J12: =VLOOKUP($B12,'Cost prices'!$B$6:$H$538,7, FALSE) -> Incl Seneberg | L12: =VLOOKUP($B12,'Cost prices'!$B$6:$H$538,7, FALSE) -> Incl Seneberg | N12: =VLOOKUP($B12,'Cost prices'!$B$6:$H$538,7, FALSE) -> Incl Seneberg | P12: =VLOOKUP($B12,'Cost prices'!$B$6:$H$538,7, FALSE) -> Incl Seneberg | R12: =VLOOKUP($B12,'Cost prices'!$B$6:$H$538,7, FALSE) -> Incl Seneberg | T12: =VLOOKUP($B12,'Cost prices'!$B$6:$H$538,7, FALSE) -> Incl Seneberg | V12: =VLOOKUP($B12,'Cost prices'!$B$6:$H$538,7, FALSE) -> Incl Seneberg | X12: =VLOOKUP($B12,'Cost prices'!$B$6:$H$538,7, FALSE) -> Incl Seneberg | Z12: =VLOOKUP($B12,'Cost prices'!$B$6:$H$538,7, FALSE) -> Incl Seneberg | AB12: =VLOOKUP($B12,'Cost prices'!$B$6:$H$538,7, FALSE) -> Incl Seneberg | AD12: =VLOOKUP($B12,'Cost prices'!$B$6:$H$538,7, FALSE) -> Incl Seneberg | AE12: =VLOOKUP($B12,'Cost prices'!$B$6:$H$538,7, FALSE) -> Incl Seneberg | AF12: =VLOOKUP($B12,'Cost prices'!$B$6:$H$538,7, FALSE) -> Incl Seneberg | AH12: =VLOOKUP($B12,'Cost prices'!$B$6:$H$538,7, FALSE) -> Incl Seneberg | AI12: =VLOOKUP($B12,'Cost prices'!$B$6:$H$538,7, FALSE) -> Incl Seneberg | AK12: =VLOOKUP($B12,'Cost prices'!$B$6:$H$538,7, FALSE) -> Incl Seneberg | AL12: =VLOOKUP($B12,'Cost prices'!$B$6:$H$538,7, FALSE) -> Incl Seneberg | AM12: =VLOOKUP($B12,'Cost prices'!$B$6:$H$538,7, FALSE) -> Incl Seneberg | AO12: =VLOOKUP($B12,'Cost prices'!$B$6:$H$538,7, FALSE) -> Incl Seneberg | AP12: =VLOOKUP($B12,'Cost prices'!$B$6:$H$538,7, FALSE) -> Incl Seneberg | AQ12: =VLOOKUP($B12,'Cost prices'!$B$6:$H$538,7, FALSE) -> Incl Seneberg
B13: Dan Seneberg, Pump house fabrication | E13: =VLOOKUP($B13,'Cost prices'!$B$6:$H$538,7, FALSE) -> 4960.955 | F13: =VLOOKUP($B13,'Cost prices'!$B$6:$H$538,7, FALSE) -> 4960.955 | H13: =VLOOKUP($B13,'Cost prices'!$B$6:$H$538,7, FALSE) -> 4960.955 | J13: =VLOOKUP($B13,'Cost prices'!$B$6:$H$538,7, FALSE) -> 4960.955 | L13: =VLOOKUP($B13,'Cost prices'!$B$6:$H$538,7, FALSE) -> 4960.955 | N13: =VLOOKUP($B13,'Cost prices'!$B$6:$H$538,7, FALSE) -> 4960.955 | P13: =VLOOKUP($B13,'Cost prices'!$B$6:$H$538,7, FALSE) -> 4960.955 | R13: =VLOOKUP($B13,'Cost prices'!$B$6:$H$538,7, FALSE) -> 4960.955 | T13: =VLOOKUP($B13,'Cost prices'!$B$6:$H$538,7, FALSE) -> 4960.955 | V13: =VLOOKUP($B13,'Cost prices'!$B$6:$H$538,7, FALSE) -> 4960.955 | X13: =VLOOKUP($B13,'Cost prices'!$B$6:$H$538,7, FALSE) -> 4960.955 | Z13: =VLOOKUP($B13,'Cost prices'!$B$6:$H$538,7, FALSE) -> 4960.955
B14: Dan Seneberg, assemble and test | E14: =VLOOKUP($B14,'Cost prices'!$B$6:$H$538,7, FALSE) -> 8223.757 | F14: =VLOOKUP($B14,'Cost prices'!$B$6:$H$538,7, FALSE) -> 8223.757 | H14: =VLOOKUP($B14,'Cost prices'!$B$6:$H$538,7, FALSE) -> 8223.757 | J14: =VLOOKUP($B14,'Cost prices'!$B$6:$H$538,7, FALSE) -> 8223.757 | L14: =VLOOKUP($B14,'Cost prices'!$B$6:$H$538,7, FALSE) -> 8223.757 | N14: =VLOOKUP($B14,'Cost prices'!$B$6:$H$538,7, FALSE) -> 8223.757 | P14: =VLOOKUP($B14,'Cost prices'!$B$6:$H$538,7, FALSE) -> 8223.757 | R14: =VLOOKUP($B14,'Cost prices'!$B$6:$H$538,7, FALSE) -> 8223.757 | T14: =VLOOKUP($B14,'Cost prices'!$B$6:$H$538,7, FALSE) -> 8223.757 | V14: =VLOOKUP($B14,'Cost prices'!$B$6:$H$538,7, FALSE) -> 8223.757 | X14: =VLOOKUP($B14,'Cost prices'!$B$6:$H$538,7, FALSE) -> 8223.757 | Z14: =VLOOKUP($B14,'Cost prices'!$B$6:$H$538,7, FALSE) -> 8223.757 | AB14: =VLOOKUP($B14,'Cost prices'!$B$6:$H$538,7, FALSE) -> 8223.757 | AD14: =VLOOKUP($B14,'Cost prices'!$B$6:$H$538,7, FALSE) -> 8223.757 | AE14: =VLOOKUP($B14,'Cost prices'!$B$6:$H$538,7, FALSE) -> 8223.757 | AF14: =VLOOKUP($B14,'Cost prices'!$B$6:$H$538,7, FALSE) -> 8223.757 | AH14: =VLOOKUP($B14,'Cost prices'!$B$6:$H$538,7, FALSE) -> 8223.757 | AI14: =VLOOKUP($B14,'Cost prices'!$B$6:$H$538,7, FALSE) -> 8223.757 | AK14: =VLOOKUP($B14,'Cost prices'!$B$6:$H$538,7, FALSE) -> 8223.757 | AL14: =VLOOKUP($B14,'Cost prices'!$B$6:$H$538,7, FALSE) -> 8223.757 | AM14: =VLOOKUP($B14,'Cost prices'!$B$6:$H$538,7, FALSE) -> 8223.757 | AO14: =VLOOKUP($B14,'Cost prices'!$B$6:$H$538,7, FALSE) -> 8223.757 | AP14: =VLOOKUP($B14,'Cost prices'!$B$6:$H$538,7, FALSE) -> 8223.757 | AQ14: =VLOOKUP($B14,'Cost prices'!$B$6:$H$538,7, FALSE) -> 8223.757
B15: Dan Seneberg workshop, 35 holes | E15: =VLOOKUP($B15,'Cost prices'!$B$6:$H$538,7, FALSE) -> 14519.082 | F15: =VLOOKUP($B15,'Cost prices'!$B$6:$H$538,7, FALSE) -> 14519.082 | H15: =VLOOKUP($B15,'Cost prices'!$B$6:$H$538,7, FALSE) -> 14519.082 | J15: =VLOOKUP($B15,'Cost prices'!$B$6:$H$538,7, FALSE) -> 14519.082 | L15: =VLOOKUP($B15,'Cost prices'!$B$6:$H$538,7, FALSE) -> 14519.082 | N15: =VLOOKUP($B15,'Cost prices'!$B$6:$H$538,7, FALSE) -> 14519.082 | P15: =VLOOKUP($B15,'Cost prices'!$B$6:$H$538,7, FALSE) -> 14519.082 | R15: =VLOOKUP($B15,'Cost prices'!$B$6:$H$538,7, FALSE) -> 14519.082 | T15: =VLOOKUP($B15,'Cost prices'!$B$6:$H$538,7, FALSE) -> 14519.082 | V15: =VLOOKUP($B15,'Cost prices'!$B$6:$H$538,7, FALSE) -> 14519.082 | X15: =VLOOKUP($B15,'Cost prices'!$B$6:$H$538,7, FALSE) -> 14519.082
B16: Dan Seneberg workshop, 105 holes | Z16: =VLOOKUP($B16,'Cost prices'!$B$6:$H$538,7, FALSE) -> 16009.082 | AB16: =VLOOKUP($B16,'Cost prices'!$B$6:$H$538,7, FALSE) -> 16009.082 | AD16: =VLOOKUP($B16,'Cost prices'!$B$6:$H$538,7, FALSE) -> 16009.082 | AE16: =VLOOKUP($B16,'Cost prices'!$B$6:$H$538,7, FALSE)* IF('External Prices'!S$28<>"No",2,1) -> 16009.082 | AF16: =VLOOKUP($B16,'Cost prices'!$B$6:$H$538,7, FALSE)* IF('External Prices'!T$28<>"No",2,1) -> 16009.082 | AH16: =VLOOKUP($B16,'Cost prices'!$B$6:$H$538,7, FALSE) -> 16009.082 | AI16: =VLOOKUP($B16,'Cost prices'!$B$6:$H$538,7, FALSE) -> 16009.082 | AK16: =VLOOKUP($B16,'Cost prices'!$B$6:$H$538,7, FALSE) -> 16009.082 | AL16: =VLOOKUP($B16,'Cost prices'!$B$6:$H$538,7, FALSE) -> 16009.082 | AM16: =VLOOKUP($B16,'Cost prices'!$B$6:$H$538,7, FALSE)* IF('External Prices'!Y$28<>"No",2,1) -> 32018.163 | AO16: =VLOOKUP($B16,'Cost prices'!$B$6:$H$538,7, FALSE)* IF('External Prices'!Z$28<>"No",2,1) -> 16009.082 | AP16: =VLOOKUP($B16,'Cost prices'!$B$6:$H$538,7, FALSE)* IF('External Prices'!AA$28<>"No",2,1) -> 16009.082 | AQ16: =VLOOKUP($B16,'Cost prices'!$B$6:$H$538,7, FALSE)* IF('External Prices'!AB$28<>"No",2,1) -> 32018.163
A18: Danish supplys
B19: Water flush mixer parts
A20: RS components | B20: *Y-strainer | Z20: =VLOOKUP($B20,'Cost prices'!$B$6:$H$538,7, FALSE) -> 473.67 | AD20: =VLOOKUP($B20,'Cost prices'!$B$6:$H$538,7, FALSE) -> 473.67 | AE20: =VLOOKUP($B20,'Cost prices'!$B$6:$H$538,7, FALSE)* IF('External Prices'!S$28<>"No",2,1) -> 473.67 | AF20: =VLOOKUP($B20,'Cost prices'!$B$6:$H$538,7, FALSE)* IF('External Prices'!T$28<>"No",2,1) -> 473.67 | AH20: =VLOOKUP($B20,'Cost prices'!$B$6:$H$538,7, FALSE) -> 473.67 | AI20: =VLOOKUP($B20,'Cost prices'!$B$6:$H$538,7, FALSE) -> 473.67 | AK20: =VLOOKUP($B20,'Cost prices'!$B$6:$H$538,7, FALSE) -> 473.67 | AL20: =VLOOKUP($B20,'Cost prices'!$B$6:$H$538,7, FALSE) -> 473.67 | AM20: =VLOOKUP($B20,'Cost prices'!$B$6:$H$538,7, FALSE)* IF('External Prices'!Y$28<>"No",2,1) -> 947.34 | AO20: =VLOOKUP($B20,'Cost prices'!$B$6:$H$538,7, FALSE)* IF('External Prices'!Z$28<>"No",2,1) -> 473.67 | AP20: =VLOOKUP($B20,'Cost prices'!$B$6:$H$538,7, FALSE)* IF('External Prices'!AA$28<>"No",2,1) -> 473.67 | AQ20: =VLOOKUP($B20,'Cost prices'!$B$6:$H$538,7, FALSE)* IF('External Prices'!AB$28<>"No",2,1) -> 947.34 | BH20: =VLOOKUP($B20,'Cost prices'!$B$6:$H$538,7, FALSE) -> 473.67
A21: Bürkert | B21: *2/2-waY-solenoId valve, servo assisted 6213-EV-A10,0AAVAGM82-6-024/DC-10 *NA38 | Z21: =VLOOKUP($B21,'Cost prices'!$B$6:$H$538,7, FALSE) -> 2083.3209 | AD21: =VLOOKUP($B21,'Cost prices'!$B$6:$H$538,7, FALSE) -> 2083.3209 | AE21: =VLOOKUP($B21,'Cost prices'!$B$6:$H$538,7, FALSE)* IF('External Prices'!S$28<>"No",2,1) -> 2083.3209 | AF21: =VLOOKUP($B21,'Cost prices'!$B$6:$H$538,7, FALSE)* IF('External Prices'!T$28<>"No",2,1) -> 2083.3209 | AH21: =VLOOKUP($B21,'Cost prices'!$B$6:$H$538,7, FALSE) -> 2083.3209 | AI21: =VLOOKUP($B21,'Cost prices'!$B$6:$H$538,7, FALSE) -> 2083.3209 | AK21: =VLOOKUP($B21,'Cost prices'!$B$6:$H$538,7, FALSE) -> 2083.3209 | AL21: =VLOOKUP($B21,'Cost prices'!$B$6:$H$538,7, FALSE) -> 2083.3209 | AM21: =VLOOKUP($B21,'Cost prices'!$B$6:$H$538,7, FALSE)* IF('External Prices'!Y$28<>"No",2,1) -> 4166.6418 | AO21: =VLOOKUP($B21,'Cost prices'!$B$6:$H$538,7, FALSE)* IF('External Prices'!Z$28<>"No",2,1) -> 2083.3209 | AP21: =VLOOKUP($B21,'Cost prices'!$B$6:$H$538,7, FALSE)* IF('External Prices'!AA$28<>"No",2,1) -> 2083.3209 | AQ21: =VLOOKUP($B21,'Cost prices'!$B$6:$H$538,7, FALSE)* IF('External Prices'!AB$28<>"No",2,1) -> 4166.6418 | BH21: =VLOOKUP($B21,'Cost prices'!$B$6:$H$538,7, FALSE) -> 2083.3209
A22: Bürkert | B22: *Kabelstik 2518 28mm Form A UL approva 2518-A-BCS/UC-00-3-N50-00-0-00000 JLO4 | Z22: =VLOOKUP($B22,'Cost prices'!$B$6:$H$538,7, FALSE) -> 118.5213 | AD22: =VLOOKUP($B22,'Cost prices'!$B$6:$H$538,7, FALSE) -> 118.5213 | AE22: =VLOOKUP($B22,'Cost prices'!$B$6:$H$538,7, FALSE)* IF('External Prices'!S$28<>"No",2,1) -> 118.5213 | AF22: =VLOOKUP($B22,'Cost prices'!$B$6:$H$538,7, FALSE)* IF('External Prices'!T$28<>"No",2,1) -> 118.5213 | AH22: =VLOOKUP($B22,'Cost prices'!$B$6:$H$538,7, FALSE) -> 118.5213 | AI22: =VLOOKUP($B22,'Cost prices'!$B$6:$H$538,7, FALSE) -> 118.5213 | AK22: =VLOOKUP($B22,'Cost prices'!$B$6:$H$538,7, FALSE) -> 118.5213 | AL22: =VLOOKUP($B22,'Cost prices'!$B$6:$H$538,7, FALSE) -> 118.5213 | AM22: =VLOOKUP($B22,'Cost prices'!$B$6:$H$538,7, FALSE)* IF('External Prices'!Y$28<>"No",2,1) -> 237.0426 | AO22: =VLOOKUP($B22,'Cost prices'!$B$6:$H$538,7, FALSE)* IF('External Prices'!Z$28<>"No",2,1) -> 118.5213 | AP22: =VLOOKUP($B22,'Cost prices'!$B$6:$H$538,7, FALSE)* IF('External Prices'!AA$28<>"No",2,1) -> 118.5213 | AQ22: =VLOOKUP($B22,'Cost prices'!$B$6:$H$538,7, FALSE)* IF('External Prices'!AB$28<>"No",2,1) -> 237.0426 | BH22: =VLOOKUP($B22,'Cost prices'!$B$6:$H$538,7, FALSE) -> 118.5213
A23: DVC | B23: Needel valve | Z23: =VLOOKUP($B23,'Cost prices'!$B$6:$H$538,7, FALSE) -> 593 | AD23: =VLOOKUP($B23,'Cost prices'!$B$6:$H$538,7, FALSE) -> 593 | AE23: =VLOOKUP($B23,'Cost prices'!$B$6:$H$538,7, FALSE)* IF('External Prices'!S$28<>"No",2,1) -> 593 | AF23: =VLOOKUP($B23,'Cost prices'!$B$6:$H$538,7, FALSE)* IF('External Prices'!T$28<>"No",2,1) -> 593 | AH23: =VLOOKUP($B23,'Cost prices'!$B$6:$H$538,7, FALSE) -> 593 | AI23: =VLOOKUP($B23,'Cost prices'!$B$6:$H$538,7, FALSE) -> 593 | AK23: =VLOOKUP($B23,'Cost prices'!$B$6:$H$538,7, FALSE) -> 593 | AL23: =VLOOKUP($B23,'Cost prices'!$B$6:$H$538,7, FALSE) -> 593 | AM23: =VLOOKUP($B23,'Cost prices'!$B$6:$H$538,7, FALSE)* IF('External Prices'!Y$28<>"No",2,1) -> 1186 | AO23: =VLOOKUP($B23,'Cost prices'!$B$6:$H$538,7, FALSE)* IF('External Prices'!Z$28<>"No",2,1) -> 593 | AP23: =VLOOKUP($B23,'Cost prices'!$B$6:$H$538,7, FALSE)* IF('External Prices'!AA$28<>"No",2,1) -> 593 | AQ23: =VLOOKUP($B23,'Cost prices'!$B$6:$H$538,7, FALSE)* IF('External Prices'!AB$28<>"No",2,1) -> 1186 | BH23: =VLOOKUP($B23,'Cost prices'!$B$6:$H$538,7, FALSE) -> 593
A24: DVC | B24: Ball Valve (full bore) | H24: Incl Brian
A25: FOOT | B25: FOOT | E25: Incl Brian | F25: Incl Brian | J25: Incl Brian | L25: =IFERROR( VLOOKUP( IF('External Prices'!I18="MARTIN","M16x2 ø60",IF('External Prices'!I18="NGI","XH65-M16 x 150/85-M16 x 50","")), 'Cost prices'!$B$6:$H$376, 7, FALSE )*7, "") | N25: =IFERROR( VLOOKUP( IF('External Prices'!J18="MARTIN","M16x2 ø60",IF('External Prices'!J18="NGI","XH65-M16 x 150/85-M16 x 50","")), 'Cost prices'!$B$6:$H$376, 7, FALSE )*4, "") | P25: =IFERROR( VLOOKUP( IF('External Prices'!K18="MARTIN","M16x2 ø60",IF('External Prices'!K18="NGI","XH65-M16 x 150/85-M16 x 50","")), 'Cost prices'!$B$6:$H$376, 7, FALSE )*4, "") | R25: =IFERROR( VLOOKUP( IF('External Prices'!L18="MARTIN","M16x2 ø60",IF('External Prices'!L18="NGI","XH65-M16 x 150/85-M16 x 50","")), 'Cost prices'!$B$6:$H$376, 7, FALSE )*7, "") -> 2056.67 | T25: =VLOOKUP($B25,'Cost prices'!$B$6:$H$376,7, FALSE)*S25 -> #N/A | V25: =IFERROR( VLOOKUP( IF('External Prices'!N18="MARTIN","M16x2 ø60",IF('External Prices'!N18="NGI","XH65-M16 x 150/85-M16 x 50","")), 'Cost prices'!$B$6:$H$376, 7, FALSE )*7, "") -> 2056.67 | BE25: ='Cost prices'!$H$244*4 -> 842.7784 | BL25: ='Cost prices'!$H$244*4 -> 842.7784
B26: xx kW motor | E26: =VLOOKUP('External Prices'!E14,'Cost prices'!$B$6:$H$538,7, FALSE) -> 11970.57 | F26: =VLOOKUP('External Prices'!F14,'Cost prices'!$B$6:$H$538,7, FALSE) -> 11970.57 | H26: =VLOOKUP('External Prices'!G14,'Cost prices'!$B$6:$H$538,7, FALSE) -> 11970.57 | J26: =VLOOKUP('External Prices'!H14,'Cost prices'!$B$6:$H$538,7, FALSE) -> 11970.57 | L26: =VLOOKUP('External Prices'!I14,'Cost prices'!$B$6:$H$538,7, FALSE) -> 9301.92 | N26: =VLOOKUP('External Prices'!J14,'Cost prices'!$B$6:$H$538,7, FALSE) -> 9301.92 | P26: =VLOOKUP('External Prices'!K14,'Cost prices'!$B$6:$H$538,7, FALSE) -> 11970.57 | R26: =VLOOKUP('External Prices'!L14,'Cost prices'!$B$6:$H$538,7, FALSE) -> 11970.57 | T26: =VLOOKUP('External Prices'!L14,'Cost prices'!$B$6:$H$538,7, FALSE) -> 11970.57 | V26: =VLOOKUP('External Prices'!N14,'Cost prices'!$B$6:$H$538,7, FALSE) -> 11970.57 | X26: =VLOOKUP('External Prices'!O14,'Cost prices'!$B$6:$H$538,7, FALSE) -> 11970.57 | Z26: =VLOOKUP('External Prices'!P14,'Cost prices'!$B$6:$H$538,7, FALSE) -> 11970.57 | AB26: =9473+1500 -> 10973 | AD26: =VLOOKUP('External Prices'!R14,'Cost prices'!$B$6:$H$538,7, FALSE) -> 11970.57 | AE26: =VLOOKUP('External Prices'!S14,'Cost prices'!$B$6:$H$538,7, FALSE)* IF('External Prices'!S$28<>"No",2,1) -> 11970.57 | AF26: =VLOOKUP('External Prices'!T14,'Cost prices'!$B$6:$H$538,7, FALSE)* IF('External Prices'!T$28<>"No",2,1) -> 11970.57 | AH26: =VLOOKUP('External Prices'!U14,'Cost prices'!$B$6:$H$538,7, FALSE) -> 11970.57 | AI26: =VLOOKUP('External Prices'!V14,'Cost prices'!$B$6:$H$538,7, FALSE) -> 11970.57 | AK26: =VLOOKUP('External Prices'!W14,'Cost prices'!$B$6:$H$538,7, FALSE) -> 11970.57 | AL26: =VLOOKUP('External Prices'!X14,'Cost prices'!$B$6:$H$538,7, FALSE) -> 17983.92 | AM26: =VLOOKUP('External Prices'!Y14,'Cost prices'!$B$6:$H$538,7, FALSE)* IF('External Prices'!Y$28<>"No",2,1) -> 32995.84 | AO26: =VLOOKUP('External Prices'!Z14,'Cost prices'!$B$6:$H$538,7, FALSE)* IF('External Prices'!Z$28<>"No",2,1) -> 11970.57 | AP26: =VLOOKUP('External Prices'!AA14,'Cost prices'!$B$6:$H$538,7, FALSE)* IF('External Prices'!AA$28<>"No",2,1) -> 11970.57 | AQ26: =VLOOKUP('External Prices'!AB14,'Cost prices'!$B$6:$H$538,7, FALSE)* IF('External Prices'!AB$28<>"No",2,1) -> 32995.84 | AS26: =VLOOKUP(AS$1,'Cost prices'!$B$6:$H$538,7, FALSE) -> 13054 | AT26: =VLOOKUP(AT$1,'Cost prices'!$B$6:$H$538,7, FALSE) -> 14016 | AU26: =VLOOKUP(AU$1,'Cost prices'!$B$6:$H$538,7, FALSE) -> 14978 | AV26: =VLOOKUP(AV$1,'Cost prices'!$B$6:$H$538,7, FALSE) -> 17663 | AW26: =VLOOKUP(AW$1,'Cost prices'!$B$6:$H$538,7, FALSE) -> 11990
A27: Norland | B27: Control cabinet (VN version) | AS27: =VLOOKUP($B27,'Cost prices'!$B$6:$H$538,7, FALSE) -> 12612.03 | AT27: =VLOOKUP($B27,'Cost prices'!$B$6:$H$538,7, FALSE) -> 12612.03 | AU27: =VLOOKUP($B27,'Cost prices'!$B$6:$H$538,7, FALSE) -> 12612.03 | AV27: =VLOOKUP($B27,'Cost prices'!$B$6:$H$538,7, FALSE) -> 12612.03 | AW27: =VLOOKUP($B27,'Cost prices'!$B$6:$H$538,7, FALSE) -> 12612.03 | AX27: On display | AY27: On display | AZ27: On display | BA27: On display
A28: Eletrician | B28: Cables inst (part of Brian cost) | AV28: =$C$28 -> 0
B29: SMS, Clamp, Flange | BI29: 500
B30: xx kW frequency Inverter | E30: NOT INCLUDED | F30: NOT INCLUDED | H30: NOT INCLUDED | J30: NOT INCLUDED | L30: NOT INCLUDED | N30: NOT INCLUDED | P30: NOT INCLUDED | R30: NOT INCLUDED | T30: NOT INCLUDED | V30: NOT INCLUDED | X30: NOT INCLUDED | Z30: NOT INCLUDED | AB30: NOT INCLUDED | AD30: NOT INCLUDED | AE30: NOT INCLUDED | AF30: NOT INCLUDED | AH30: NOT INCLUDED | AI30: NOT INCLUDED | AK30: NOT INCLUDED | AL30: NOT INCLUDED | AM30: NOT INCLUDED | AO30: NOT INCLUDED | AP30: NOT INCLUDED | AQ30: NOT INCLUDED | AS30: Included | AT30: Included | AU30: Included | AV30: Included | AW30: Included | AX30: =VLOOKUP(AX$1,'Cost prices'!$B$6:$H$538,7, FALSE) -> 9683.25 | AY30: =VLOOKUP(AY$1,'Cost prices'!$B$6:$H$538,7, FALSE) -> 11919.75 | AZ30: =VLOOKUP(AZ$1,'Cost prices'!$B$6:$H$538,7, FALSE) -> 13715.25 | BA30: =VLOOKUP(BA$1,'Cost prices'!$B$6:$H$538,7, FALSE) -> 15510.75
A31: HTEN | B31: xx kW frequency Inverter | BB31: ='Cost prices'!H388 -> 138517.23 | BC31: ='Cost prices'!H389 -> 126658.56 | BD31: ='Cost prices'!H408 -> 180863.25
A33: Brian | B33: Mixer complete unit [incl unit parts] | E33: =VLOOKUP(E$1,'Cost prices'!$B$6:$H$538,7, FALSE) -> 14905 | F33: =VLOOKUP(F$1,'Cost prices'!$B$6:$H$538,7, FALSE) -> 26290 | H33: =VLOOKUP(H$1,'Cost prices'!$B$6:$H$538,7, FALSE) -> 51590 | J33: =VLOOKUP(J$1,'Cost prices'!$B$6:$H$538,7, FALSE) -> 90310
B34: Mesh | BG34: =VLOOKUP(BG$1,'Cost prices'!$B$6:$H$538,7, FALSE) -> 4796 | BK34: 1500
B35: Table | BE35: =VLOOKUP($B35,'Cost prices'!$B$6:$H$538,7, FALSE) -> 13134 | BK35: =8*600 -> 4800
B36: Control system (fitting/conection of panel) | AS36: =VLOOKUP($B36,'Cost prices'!$B$6:$H$538,7, FALSE) -> 5720 | AT36: =VLOOKUP($B36,'Cost prices'!$B$6:$H$538,7, FALSE) -> 5720 | AU36: =VLOOKUP($B36,'Cost prices'!$B$6:$H$538,7, FALSE) -> 5720 | AV36: =VLOOKUP($B36,'Cost prices'!$B$6:$H$538,7, FALSE) -> 5720 | AW36: =VLOOKUP($B36,'Cost prices'!$B$6:$H$538,7, FALSE) -> 5720 | AX36: =VLOOKUP($B36,'Cost prices'!$B$6:$H$538,7, FALSE) -> 5720 | AY36: =VLOOKUP($B36,'Cost prices'!$B$6:$H$538,7, FALSE) -> 5720 | AZ36: =VLOOKUP($B36,'Cost prices'!$B$6:$H$538,7, FALSE) -> 5720 | BA36: =VLOOKUP($B36,'Cost prices'!$B$6:$H$538,7, FALSE) -> 5720
B37: Test / packing
B38: Time (hourly rate) | BI38: 500
B39: Seal water | BH39: =VLOOKUP($B39,'Cost prices'!$B$6:$H$538,7, FALSE) -> 720.5
B41: Parts | W41: PCS | Y41: Pcs | AC41: PCS | AG41: PCS | AJ41: PCS | AN41: PCS
A42: Bolts | B42: Nut NDXH M8, AISI 316 | AC42: 0 | AD42: =IF($AC42="x","incl",VLOOKUP($B42,'Cost prices'!$B$6:$H$538,7,FALSE)*$AC42) -> 0 | AE42: =IF($AC42="x","incl",VLOOKUP($B42,'Cost prices'!$B$6:$H$538,7,FALSE)*$AC42) -> 0 | AF42: =IF($AC42="x","incl",VLOOKUP($B42,'Cost prices'!$B$6:$H$538,7,FALSE)*$AC42) -> 0 | AG42: 40 | AH42: =IF($AG42="x","incl",VLOOKUP($B42,'Cost prices'!$B$6:$H$538,7,FALSE)*$AG42) -> 1090.16 | AI42: =IF($AG42="x","incl",VLOOKUP($B42,'Cost prices'!$B$6:$H$538,7,FALSE)*$AG42) -> 1090.16 | AJ42: 40 | AK42: =IF($AJ42="x","incl",VLOOKUP($B42,'Cost prices'!$B$6:$H$538,7,FALSE)*$AJ42) -> 1090.16 | AL42: =IF($AJ42="x","incl",VLOOKUP($B42,'Cost prices'!$B$6:$H$538,7,FALSE)*$AJ42) -> 1090.16 | AM42: =IF($AJ42="x","incl",VLOOKUP($B42,'Cost prices'!$B$6:$H$538,7,FALSE)*$AJ42) -> 1090.16 | AN42: 40 | AO42: =IF($AN42="x","incl",VLOOKUP($B42,'Cost prices'!$B$6:$H$538,7,FALSE)*$AN42) -> 1090.16 | AP42: =IF($AN42="x","incl",VLOOKUP($B42,'Cost prices'!$B$6:$H$538,7,FALSE)*$AN42) -> 1090.16 | AQ42: =IF($AN42="x","incl",VLOOKUP($B42,'Cost prices'!$B$6:$H$538,7,FALSE)*$AN42) -> 1090.16
A43: Top | B43: Site glass with wiber | Z43: {=IFERROR( VLOOKUP( _xlfn.SWITCH('External Prices'!P19, "EBORA EU","SITE GLASS WITH WIPER", "NO NAME CN","SITE GLASS CN", "" ), 'Cost prices'!$B$6:$H$376,7,FALSE )*1, "")} -> 6528.5444 | AD43: {=IFERROR( VLOOKUP( _xlfn.SWITCH('External Prices'!R19, "EBORA EU","SITE GLASS WITH WIPER", "NO NAME CN","SITE GLASS CN", "" ), 'Cost prices'!$B$6:$H$376,7,FALSE )*1, "")} | AE43: {=IFERROR( VLOOKUP( _xlfn.SWITCH('External Prices'!S19, "EBORA EU","SITE GLASS WITH WIPER", "NO NAME CN","SITE GLASS CN", "" ), 'Cost prices'!$B$6:$H$376,7,FALSE )*1, "")} | AF43: {=IFERROR( VLOOKUP( _xlfn.SWITCH('External Prices'!T19, "EBORA EU","SITE GLASS WITH WIPER", "NO NAME CN","SITE GLASS CN", "" ), 'Cost prices'!$B$6:$H$376,7,FALSE )*1, "")} | AH43: {=IFERROR( VLOOKUP( _xlfn.SWITCH('External Prices'!U19, "EBORA EU","SITE GLASS WITH WIPER", "NO NAME CN","SITE GLASS CN", "" ), 'Cost prices'!$B$6:$H$376,7,FALSE )*1, "")} -> 6528.5444 | AI43: {=IFERROR( VLOOKUP( _xlfn.SWITCH('External Prices'!V19, "EBORA EU","SITE GLASS WITH WIPER", "NO NAME CN","SITE GLASS CN", "" ), 'Cost prices'!$B$6:$H$376,7,FALSE )*1, "")} -> 6528.5444 | AK43: {=IFERROR( VLOOKUP( _xlfn.SWITCH('External Prices'!W19, "EBORA EU","SITE GLASS WITH WIPER", "NO NAME CN","SITE GLASS CN", "" ), 'Cost prices'!$B$6:$H$376,7,FALSE )*1, "")} -> 6528.5444 | AL43: {=IFERROR( VLOOKUP( _xlfn.SWITCH('External Prices'!X19, "EBORA EU","SITE GLASS WITH WIPER", "NO NAME CN","SITE GLASS CN", "" ), 'Cost prices'!$B$6:$H$376,7,FALSE )*1, "")} -> 6528.5444 | AM43: {=IFERROR( VLOOKUP( _xlfn.SWITCH('External Prices'!Y19, "EBORA EU","SITE GLASS WITH WIPER", "NO NAME CN","SITE GLASS CN", "" ), 'Cost prices'!$B$6:$H$376,7,FALSE )*1, "")} -> 6528.5444 | AO43: {=IFERROR( VLOOKUP( _xlfn.SWITCH('External Prices'!Z19, "EBORA EU","SITE GLASS WITH WIPER", "NO NAME CN","SITE GLASS CN", "" ), 'Cost prices'!$B$6:$H$376,7,FALSE )*1, "")} -> 6528.5444 | AP43: {=IFERROR( VLOOKUP( _xlfn.SWITCH('External Prices'!AA19, "EBORA EU","SITE GLASS WITH WIPER", "NO NAME CN","SITE GLASS CN", "" ), 'Cost prices'!$B$6:$H$376,7,FALSE )*1, "")} -> 6528.5444 | AQ43: {=IFERROR( VLOOKUP( _xlfn.SWITCH('External Prices'!AB19, "EBORA EU","SITE GLASS WITH WIPER", "NO NAME CN","SITE GLASS CN", "" ), 'Cost prices'!$B$6:$H$376,7,FALSE )*1, "")} -> 6528.5444
A44: Top | B44: Site glass with light | Z44: {=IFERROR( VLOOKUP( _xlfn.SWITCH('External Prices'!P19, "EBORA EU","SITE GLASS WITH LIGHT", "NO NAME CN","SITE GLASS CN", "" ), 'Cost prices'!$B$6:$H$376,7,FALSE )*1, "")} -> 9228.766 | AD44: {=IFERROR( VLOOKUP( _xlfn.SWITCH('External Prices'!R19, "EBORA EU","SITE GLASS WITH LIGHT", "NO NAME CN","SITE GLASS CN", "" ), 'Cost prices'!$B$6:$H$376,7,FALSE )*1, "")} | AE44: {=IFERROR( VLOOKUP( _xlfn.SWITCH('External Prices'!S19, "EBORA EU","SITE GLASS WITH LIGHT", "NO NAME CN","SITE GLASS CN", "" ), 'Cost prices'!$B$6:$H$376,7,FALSE )*1, "")} | AF44: {=IFERROR( VLOOKUP( _xlfn.SWITCH('External Prices'!T19, "EBORA EU","SITE GLASS WITH LIGHT", "NO NAME CN","SITE GLASS CN", "" ), 'Cost prices'!$B$6:$H$376,7,FALSE )*1, "")} | AH44: {=IFERROR( VLOOKUP( _xlfn.SWITCH('External Prices'!U19, "EBORA EU","SITE GLASS WITH LIGHT", "NO NAME CN","SITE GLASS CN", "" ), 'Cost prices'!$B$6:$H$376,7,FALSE )*1, "")} -> 9228.766 | AI44: {=IFERROR( VLOOKUP( _xlfn.SWITCH('External Prices'!V19, "EBORA EU","SITE GLASS WITH LIGHT", "NO NAME CN","SITE GLASS CN", "" ), 'Cost prices'!$B$6:$H$376,7,FALSE )*1, "")} -> 9228.766 | AK44: {=IFERROR( VLOOKUP( _xlfn.SWITCH('External Prices'!W19, "EBORA EU","SITE GLASS WITH LIGHT", "NO NAME CN","SITE GLASS CN", "" ), 'Cost prices'!$B$6:$H$376,7,FALSE )*1, "")} -> 9228.766 | AL44: {=IFERROR( VLOOKUP( _xlfn.SWITCH('External Prices'!X19, "EBORA EU","SITE GLASS WITH LIGHT", "NO NAME CN","SITE GLASS CN", "" ), 'Cost prices'!$B$6:$H$376,7,FALSE )*1, "")} -> 9228.766 | AM44: {=IFERROR( VLOOKUP( _xlfn.SWITCH('External Prices'!Y19, "EBORA EU","SITE GLASS WITH LIGHT", "NO NAME CN","SITE GLASS CN", "" ), 'Cost prices'!$B$6:$H$376,7,FALSE )*1, "")} -> 9228.766 | AO44: {=IFERROR( VLOOKUP( _xlfn.SWITCH('External Prices'!Z19, "EBORA EU","SITE GLASS WITH LIGHT", "NO NAME CN","SITE GLASS CN", "" ), 'Cost prices'!$B$6:$H$376,7,FALSE )*1, "")} -> 9228.766 | AP44: {=IFERROR( VLOOKUP( _xlfn.SWITCH('External Prices'!AA19, "EBORA EU","SITE GLASS WITH LIGHT", "NO NAME CN","SITE GLASS CN", "" ), 'Cost prices'!$B$6:$H$376,7,FALSE )*1, "")} -> 9228.766 | AQ44: {=IFERROR( VLOOKUP( _xlfn.SWITCH('External Prices'!AB19, "EBORA EU","SITE GLASS WITH LIGHT", "NO NAME CN","SITE GLASS CN", "" ), 'Cost prices'!$B$6:$H$376,7,FALSE )*1, "")} -> 9228.766
A45: Bottom | B45: *fan | AC45: 0 | AD45: =IF($AC45="x","incl",VLOOKUP($B45,'Cost prices'!$B$6:$H$538,7,FALSE)*$AC45) -> 0 | AE45: =IF($AC45="x","incl",VLOOKUP($B45,'Cost prices'!$B$6:$H$538,7,FALSE)*$AC45) -> 0 | AF45: =IF($AC45="x","incl",VLOOKUP($B45,'Cost prices'!$B$6:$H$538,7,FALSE)*$AC45) -> 0 | AG45: 1 | AH45: =IF($AG45="x","incl",VLOOKUP($B45,'Cost prices'!$B$6:$H$538,7,FALSE)*$AG45) -> 541.88 | AI45: =IF($AG45="x","incl",VLOOKUP($B45,'Cost prices'!$B$6:$H$538,7,FALSE)*$AG45) -> 541.88 | AJ45: 1 | AK45: =IF($AJ45="x","incl",VLOOKUP($B45,'Cost prices'!$B$6:$H$538,7,FALSE)*$AJ45) -> 541.88 | AL45: =IF($AJ45="x","incl",VLOOKUP($B45,'Cost prices'!$B$6:$H$538,7,FALSE)*$AJ45) -> 541.88 | AM45: =IF($AJ45="x","incl",VLOOKUP($B45,'Cost prices'!$B$6:$H$538,7,FALSE)*$AJ45) -> 541.88 | AN45: 1 | AO45: =IF($AN45="x","incl",VLOOKUP($B45,'Cost prices'!$B$6:$H$538,7,FALSE)*$AN45) -> 541.88 | AP45: =IF($AN45="x","incl",VLOOKUP($B45,'Cost prices'!$B$6:$H$538,7,FALSE)*$AN45) -> 541.88 | AQ45: =IF($AN45="x","incl",VLOOKUP($B45,'Cost prices'!$B$6:$H$538,7,FALSE)*$AN45) -> 541.88
A46: Top | B46: Manway | I46: 1 | J46: Incl Brian | Y46: 1 | Z46: =IF($Y46="x","incl",VLOOKUP($B46,'Cost prices'!$B$6:$H$538,7,FALSE)*$Y46) -> 3512.177 | AC46: 1 | AD46: =IF($AC46="x","incl",VLOOKUP($B46,'Cost prices'!$B$6:$H$538,7,FALSE)*$AC46) -> 3512.177 | AE46: =IF($AC46="x","incl",VLOOKUP($B46,'Cost prices'!$B$6:$H$538,7,FALSE)*$AC46) -> 3512.177 | AF46: =IF($AC46="x","incl",VLOOKUP($B46,'Cost prices'!$B$6:$H$538,7,FALSE)) -> 3512.177 | AG46: 1 | AH46: =IF($AG46="x","incl",VLOOKUP($B46,'Cost prices'!$B$6:$H$538,7,FALSE)*$AG46) -> 3512.177 | AI46: =IF($AG46="x","incl",VLOOKUP($B46,'Cost prices'!$B$6:$H$538,7,FALSE)*$AG46) -> 3512.177 | AJ46: 1 | AK46: =IF($AJ46="x","incl",VLOOKUP($B46,'Cost prices'!$B$6:$H$538,7,FALSE)*$AJ46) -> 3512.177 | AL46: =IF($AJ46="x","incl",VLOOKUP($B46,'Cost prices'!$B$6:$H$538,7,FALSE)*$AJ46) -> 3512.177 | AM46: =IF($AJ46="x","incl",VLOOKUP($B46,'Cost prices'!$B$6:$H$538,7,FALSE)*$AJ46) -> 3512.177 | AN46: 1 | AO46: =IF($AN46="x","incl",VLOOKUP($B46,'Cost prices'!$B$6:$H$538,7,FALSE)*$AN46) -> 3512.177 | AP46: =IF($AN46="x","incl",VLOOKUP($B46,'Cost prices'!$B$6:$H$538,7,FALSE)*$AN46) -> 3512.177 | AQ46: =IF($AN46="x","incl",VLOOKUP($B46,'Cost prices'!$B$6:$H$538,7,FALSE)*$AN46) -> 3512.177
A47: Top | B47: Sanimidget | W47: 2 | X47: =IF($W47="x","incl",VLOOKUP($B47,'Cost prices'!$B$6:$H$538,7,FALSE)*$W47) -> 4929.2876 | Z47: =IF('External Prices'!P$20<>"No",VLOOKUP($B47,'Cost prices'!$B$6:$H$538,7,FALSE)*2,0) -> 4929.2876 | AD47: =IF('External Prices'!R$20<>"No",VLOOKUP($B47,'Cost prices'!$B$6:$H$538,7,FALSE)*2,0) -> 0 | AE47: =IF('External Prices'!S$20<>"No",VLOOKUP($B47,'Cost prices'!$B$6:$H$538,7,FALSE)*2,0) -> 0 | AF47: =IF('External Prices'!T$20<>"No",VLOOKUP($B47,'Cost prices'!$B$6:$H$538,7,FALSE)*2,0) -> 0 | AH47: =IF('External Prices'!U$20<>"No",VLOOKUP($B47,'Cost prices'!$B$6:$H$538,7,FALSE)*2,0) -> 4929.2876 | AI47: =IF('External Prices'!V$20<>"No",VLOOKUP($B47,'Cost prices'!$B$6:$H$538,7,FALSE)*2,0) -> 4929.2876 | AK47: =IF('External Prices'!W$20<>"No",VLOOKUP($B47,'Cost prices'!$B$6:$H$538,7,FALSE)*2,0) -> 4929.2876 | AL47: =IF('External Prices'!X$20<>"No",VLOOKUP($B47,'Cost prices'!$B$6:$H$538,7,FALSE)*2,0) -> 4929.2876 | AM47: =IF('External Prices'!Y$20<>"No",VLOOKUP($B47,'Cost prices'!$B$6:$H$538,7,FALSE)*2,0) -> 4929.2876 | AO47: =IF('External Prices'!Z$20<>"No",VLOOKUP($B47,'Cost prices'!$B$6:$H$538,7,FALSE)*2,0) -> 4929.2876 | AP47: =IF('External Prices'!AA$20<>"No",VLOOKUP($B47,'Cost prices'!$B$6:$H$538,7,FALSE)*2,0) -> 4929.2876 | AQ47: =IF('External Prices'!AB$20<>"No",VLOOKUP($B47,'Cost prices'!$B$6:$H$538,7,FALSE)*2,0) -> 4929.2876
A48: Bottom | B48: FOOT | L48: =IFERROR( VLOOKUP( IF(OR('External Prices'!I18="MARTIN",'External Prices'!I18="MARTIN 3A"), "ST. STEEL BASE Ø 60 WITH BLUE EPDM VULCANISED RUBBER TILTING 10° ST. STEEL SCREW M16X150 WITH ST. STEEL BUSH 24X85 – USDA ACCEPTED", IF('External Prices'!I18="NGI", "Machine foot XH80-M20 x 150/85-M20 x 50", "" ) ), 'Cost prices'!$B$6:$H$376, 7, FALSE )*4, "") -> 842.7784 | N48: =IFERROR( VLOOKUP( IF(OR('External Prices'!J18="MARTIN",'External Prices'!J18="MARTIN 3A"), "ST. STEEL BASE Ø 60 WITH BLUE EPDM VULCANISED RUBBER TILTING 10° ST. STEEL SCREW M16X150 WITH ST. STEEL BUSH 24X85 – USDA ACCEPTED", IF('External Prices'!J18="NGI", "Machine foot XH80-M20 x 150/85-M20 x 50", "" ) ), 'Cost prices'!$B$6:$H$376, 7, FALSE )*4, "") -> 842.7784 | P48: =IFERROR( VLOOKUP( IF(OR('External Prices'!K18="MARTIN",'External Prices'!K18="MARTIN 3A"), "ST. STEEL BASE Ø 60 WITH BLUE EPDM VULCANISED RUBBER TILTING 10° ST. STEEL SCREW M16X150 WITH ST. STEEL BUSH 24X85 – USDA ACCEPTED", IF('External Prices'!K18="NGI", "Machine foot XH80-M20 x 150/85-M20 x 50", "" ) ), 'Cost prices'!$B$6:$H$376, 7, FALSE )*4, "") -> 842.7784 | R48: =IFERROR( VLOOKUP( IF(OR('External Prices'!L18="MARTIN",'External Prices'!L18="MARTIN 3A"), "ST. STEEL BASE Ø 60 WITH BLUE EPDM VULCANISED RUBBER TILTING 10° ST. STEEL SCREW M16X150 WITH ST. STEEL BUSH 24X85 – USDA ACCEPTED", IF('External Prices'!L18="NGI", "Machine foot XH80-M20 x 150/85-M20 x 50", "" ) ), 'Cost prices'!$B$6:$H$376, 7, FALSE )*7, "") -> 2381.3125 | V48: =IFERROR( VLOOKUP( IF(OR('External Prices'!N18="MARTIN",'External Prices'!N18="MARTIN 3A"), "ST. STEEL BASE Ø 60 WITH BLUE EPDM VULCANISED RUBBER TILTING 10° ST. STEEL SCREW M16X150 WITH ST. STEEL BUSH 24X85 – USDA ACCEPTED", IF('External Prices'!N18="NGI", "Machine foot XH80-M20 x 150/85-M20 x 50", "" ) ), 'Cost prices'!$B$6:$H$376, 7, FALSE )*7, "") -> 2381.3125 | X48: =IFERROR( VLOOKUP( IF(OR('External Prices'!O18="MARTIN",'External Prices'!O18="MARTIN 3A"), "ST. STEEL BASE Ø 120 WITH BLUE EPDM VULCANISED RUBBER TILTING 10° ST. STEEL SCREW M16X200 WITH ST. STEEL BUSH 30X85 – USDA ACCEPTED", IF('External Prices'!O18="NGI", "XH125-XH20150-RHOX2050", "" ) ), 'Cost prices'!$B$6:$H$376, 7, FALSE )*4, "") -> 1203.2456 | Z48: =IFERROR( VLOOKUP( IF(OR('External Prices'!P18="MARTIN",'External Prices'!P18="MARTIN 3A"), "ST. STEEL BASE Ø 120 WITH BLUE EPDM VULCANISED RUBBER TILTING 10° ST. STEEL SCREW M16X200 WITH ST. STEEL BUSH 30X85 – USDA ACCEPTED", IF('External Prices'!P18="NGI", "XH125-XH20150-RHOX2050", "" ) ), 'Cost prices'!$B$6:$H$376, 7, FALSE )*2, "") -> 1054.04 | AD48: =IFERROR( VLOOKUP( IF(OR('External Prices'!R18="MARTIN",'External Prices'!R18="MARTIN 3A"), "ST. STEEL BASE Ø 120 WITH BLUE EPDM VULCANISED RUBBER TILTING 10° ST. STEEL SCREW M16X200 WITH ST. STEEL BUSH 30X85 – USDA ACCEPTED", IF('External Prices'!R18="NGI", "XH125-XH20150-RHOX2050", "" ) ), 'Cost prices'!$B$6:$H$376, 7, FALSE )*4, "") -> 1203.2456 | AE48: =IFERROR( VLOOKUP( IF(OR('External Prices'!S18="MARTIN",'External Prices'!S18="MARTIN 3A"), "ST. STEEL BASE Ø 120 WITH BLUE EPDM VULCANISED RUBBER TILTING 10° ST. STEEL SCREW M16X200 WITH ST. STEEL BUSH 30X85 – USDA ACCEPTED", IF('External Prices'!S18="NGI", "XH125-XH20150-RHOX2050", "" ) ), 'Cost prices'!$B$6:$H$376, 7, FALSE )*4, "") -> 1203.2456 | AF48: =IFERROR( VLOOKUP( IF(OR('External Prices'!T18="MARTIN",'External Prices'!T18="MARTIN 3A"), "ST. STEEL BASE Ø 120 WITH BLUE EPDM VULCANISED RUBBER TILTING 10° ST. STEEL SCREW M16X200 WITH ST. STEEL BUSH 30X85 – USDA ACCEPTED", IF('External Prices'!T18="NGI", "XH125-XH20150-RHOX2050", "" ) ), 'Cost prices'!$B$6:$H$376, 7, FALSE )*4, "") -> 1203.2456 | AH48: =IFERROR( VLOOKUP( IF(OR('External Prices'!U18="MARTIN",'External Prices'!U18="MARTIN 3A"), "ST. STEEL BASE Ø 120 WITH BLUE EPDM VULCANISED RUBBER TILTING 10° ST. STEEL SCREW M16X200 WITH ST. STEEL BUSH 30X85 – USDA ACCEPTED", IF('External Prices'!U18="NGI", "XH125-XH20150-RHOX2050", "" ) ), 'Cost prices'!$B$6:$H$376, 7, FALSE )*4, "") -> 2108.08 | AI48: =IFERROR( VLOOKUP( IF(OR('External Prices'!V18="MARTIN",'External Prices'!V18="MARTIN 3A"), "ST. STEEL BASE Ø 120 WITH BLUE EPDM VULCANISED RUBBER TILTING 10° ST. STEEL SCREW M16X200 WITH ST. STEEL BUSH 30X85 – USDA ACCEPTED", IF('External Prices'!V18="NGI", "XH125-XH20150-RHOX2050", "" ) ), 'Cost prices'!$B$6:$H$376, 7, FALSE )*4, "") -> 2108.08 | AK48: =IFERROR( VLOOKUP( IF(OR('External Prices'!W18="MARTIN",'External Prices'!W18="MARTIN 3A"), "ST. STEEL BASE Ø 120 WITH BLUE EPDM VULCANISED RUBBER TILTING 10° ST. STEEL SCREW M16X200 WITH ST. STEEL BUSH 30X85 – USDA ACCEPTED", IF('External Prices'!W18="NGI", "XH125-XH20150-RHOX2050", "" ) ), 'Cost prices'!$B$6:$H$376, 7, FALSE )*2, "") -> 1054.04 | AL48: =IFERROR( VLOOKUP( IF(OR('External Prices'!X18="MARTIN",'External Prices'!X18="MARTIN 3A"), "ST. STEEL BASE Ø 120 WITH BLUE EPDM VULCANISED RUBBER TILTING 10° ST. STEEL SCREW M16X200 WITH ST. STEEL BUSH 30X85 – USDA ACCEPTED", IF('External Prices'!X18="NGI", "XH125-XH20150-RHOX2050", "" ) ), 'Cost prices'!$B$6:$H$376, 7, FALSE )*2, "") -> 1054.04 | AM48: =IFERROR( VLOOKUP( IF(OR('External Prices'!Y18="MARTIN",'External Prices'!Y18="MARTIN 3A"), "ST. STEEL BASE Ø 120 WITH BLUE EPDM VULCANISED RUBBER TILTING 10° ST. STEEL SCREW M16X200 WITH ST. STEEL BUSH 30X85 – USDA ACCEPTED", IF('External Prices'!Y18="NGI", "XH125-XH20150-RHOX2050", "" ) ), 'Cost prices'!$B$6:$H$376, 7, FALSE )*2, "") -> 1054.04 | AO48: =IFERROR( VLOOKUP( IF(OR('External Prices'!Z18="MARTIN",'External Prices'!Z18="MARTIN 3A"), "ST. STEEL BASE Ø 120 WITH BLUE EPDM VULCANISED RUBBER TILTING 10° ST. STEEL SCREW M16X200 WITH ST. STEEL BUSH 30X85 – USDA ACCEPTED", IF('External Prices'!Z18="NGI", "XH125-XH20150-RHOX2050", "" ) ), 'Cost prices'!$B$6:$H$376, 7, FALSE )*2, "") -> 601.6228 | AP48: =IFERROR( VLOOKUP( IF(OR('External Prices'!AA18="MARTIN",'External Prices'!AA18="MARTIN 3A"), "ST. STEEL BASE Ø 120 WITH BLUE EPDM VULCANISED RUBBER TILTING 10° ST. STEEL SCREW M16X200 WITH ST. STEEL BUSH 30X85 – USDA ACCEPTED", IF('External Prices'!AA18="NGI", "XH125-XH20150-RHOX2050", "" ) ), 'Cost prices'!$B$6:$H$376, 7, FALSE )*2, "") -> 1054.04 | AQ48: =IFERROR( VLOOKUP( IF(OR('External Prices'!AB18="MARTIN",'External Prices'!AB18="MARTIN 3A"), "ST. STEEL BASE Ø 120 WITH BLUE EPDM VULCANISED RUBBER TILTING 10° ST. STEEL SCREW M16X200 WITH ST. STEEL BUSH 30X85 – USDA ACCEPTED", IF('External Prices'!AB18="NGI", "XH125-XH20150-RHOX2050", "" ) ), 'Cost prices'!$B$6:$H$376, 7, FALSE )*2, "") -> 1054.04
A49: Bottom | B49: LOAD CELL | Z49: =IFERROR( VLOOKUP( IF('External Prices'!P18="MARTIN", "HYGIENIC LOAD CELL Ø31/78/45, H143, M12, LOAD 10.000 N, IP67", IF('External Prices'!P18="MARTIN 3A", "HYGIENIC LOAD CELL Ø40/78/24, H178, M12, LOAD 10.000 N, 3A + IP69K", IF('External Prices'!P18="NGI", "Load cell, hygenic", "" ) ) ), 'Cost prices'!$B$6:$H$376, 7, FALSE )*2, "") -> 17323.702 | AK49: =IFERROR( VLOOKUP( IF('External Prices'!W18="MARTIN", "HYGIENIC LOAD CELL Ø31/78/45, H143, M12, LOAD 10.000 N, IP67", IF('External Prices'!W18="MARTIN 3A", "HYGIENIC LOAD CELL Ø40/78/24, H178, M12, LOAD 10.000 N, 3A + IP69K", IF('External Prices'!W18="NGI", "Load cell, hygenic", "" ) ) ), 'Cost prices'!$B$6:$H$376, 7, FALSE )*2, "") -> 17323.702 | AL49: =IFERROR( VLOOKUP( IF('External Prices'!X18="MARTIN", "HYGIENIC LOAD CELL Ø31/78/45, H143, M12, LOAD 10.000 N, IP67", IF('External Prices'!X18="MARTIN 3A", "HYGIENIC LOAD CELL Ø40/78/24, H178, M12, LOAD 10.000 N, 3A + IP69K", IF('External Prices'!X18="NGI", "Load cell, hygenic", "" ) ) ), 'Cost prices'!$B$6:$H$376, 7, FALSE )*2, "") -> 17323.702 | AM49: =IFERROR( VLOOKUP( IF('External Prices'!Y18="MARTIN", "HYGIENIC LOAD CELL Ø31/78/45, H143, M12, LOAD 10.000 N, IP67", IF('External Prices'!Y18="MARTIN 3A", "HYGIENIC LOAD CELL Ø40/78/24, H178, M12, LOAD 10.000 N, 3A + IP69K", IF('External Prices'!Y18="NGI", "Load cell, hygenic", "" ) ) ), 'Cost prices'!$B$6:$H$376, 7, FALSE )*2, "") -> 17323.702 | AO49: =IFERROR( VLOOKUP( IF('External Prices'!Z18="MARTIN", "HYGIENIC LOAD CELL Ø31/78/45, H143, M12, LOAD 10.000 N, IP67", IF('External Prices'!Z18="MARTIN 3A", "HYGIENIC LOAD CELL Ø40/78/24, H178, M12, LOAD 10.000 N, 3A + IP69K", IF('External Prices'!Z18="NGI", "Load cell, hygenic", "" ) ) ), 'Cost prices'!$B$6:$H$376, 7, FALSE )*2, "") -> 4065.45 | AP49: =IFERROR( VLOOKUP( IF('External Prices'!AA18="MARTIN", "HYGIENIC LOAD CELL Ø31/78/45, H143, M12, LOAD 10.000 N, IP67", IF('External Prices'!AA18="MARTIN 3A", "HYGIENIC LOAD CELL Ø40/78/24, H178, M12, LOAD 10.000 N, 3A + IP69K", IF('External Prices'!AA18="NGI", "Load cell, hygenic", "" ) ) ), 'Cost prices'!$B$6:$H$376, 7, FALSE )*2, "") -> 17323.702 | AQ49: =IFERROR( VLOOKUP( IF('External Prices'!AB18="MARTIN", "HYGIENIC LOAD CELL Ø31/78/45, H143, M12, LOAD 10.000 N, IP67", IF('External Prices'!AB18="MARTIN 3A", "HYGIENIC LOAD CELL Ø40/78/24, H178, M12, LOAD 10.000 N, 3A + IP69K", IF('External Prices'!AB18="NGI", "Load cell, hygenic", "" ) ) ), 'Cost prices'!$B$6:$H$376, 7, FALSE )*2, "") -> 17323.702
A50: Tangential Inlet hose | B50: OILY FOOD 1000MM | Z50: =IF('External Prices'!P$34<>"No",VLOOKUP($B50,'Cost prices'!$B$6:$H$538,7,FALSE),0) -> 0 | AD50: =IF('External Prices'!R34<>"No",VLOOKUP($B50,'Cost prices'!$B$6:$H$538,7,FALSE),0) -> 0 | AE50: =IF('External Prices'!S34<>"No",VLOOKUP($B50,'Cost prices'!$B$6:$H$538,7,FALSE),0) -> 0 | AF50: =IF('External Prices'!T34<>"No",VLOOKUP($B50,'Cost prices'!$B$6:$H$538,7,FALSE),0) -> 0 | AH50: =IF('External Prices'!U34<>"No",VLOOKUP($B50,'Cost prices'!$B$6:$H$538,7,FALSE),0) -> 0 | AI50: =IF('External Prices'!V34<>"No",VLOOKUP($B50,'Cost prices'!$B$6:$H$538,7,FALSE),0) -> 0 | AK50: =IF('External Prices'!W$34<>"No",VLOOKUP($B50,'Cost prices'!$B$6:$H$538,7,FALSE),0) -> 0 | AL50: =IF('External Prices'!X$34<>"No",VLOOKUP($B50,'Cost prices'!$B$6:$H$538,7,FALSE),0) -> 0 | AM50: =IF('External Prices'!Y$34<>"No",VLOOKUP($B50,'Cost prices'!$B$6:$H$538,7,FALSE),0) -> 0 | AO50: =IF('External Prices'!Z$34<>"No",VLOOKUP($B50,'Cost prices'!$B$6:$H$538,7,FALSE),0) -> 0 | AP50: =IF('External Prices'!AA$34<>"No",VLOOKUP($B50,'Cost prices'!$B$6:$H$538,7,FALSE),0) -> 0 | AQ50: =IF('External Prices'!AB$34<>"No",VLOOKUP($B50,'Cost prices'!$B$6:$H$538,7,FALSE),0) -> 0 | BK50: 8000
A51: Vaccum pipe hose | B51: MILKLAND 500MM | Z51: =IF('External Prices'!P$17<>"No",VLOOKUP($B51,'Cost prices'!$B$6:$H$538,7,FALSE),0) -> 3803.1826 | AK51: =IF('External Prices'!W$17<>"No",VLOOKUP($B51,'Cost prices'!$B$6:$H$538,7,FALSE),0) -> 3803.1826 | AL51: =IF('External Prices'!X$17<>"No",VLOOKUP($B51,'Cost prices'!$B$6:$H$538,7,FALSE),0) -> 3803.1826 | AM51: =IF('External Prices'!Y$17<>"No",VLOOKUP($B51,'Cost prices'!$B$6:$H$538,7,FALSE),0) -> 3803.1826 | AO51: =IF('External Prices'!Z$17<>"No",VLOOKUP($B51,'Cost prices'!$B$6:$H$538,7,FALSE),0) -> 3803.1826 | AP51: =IF('External Prices'!AA$17<>"No",VLOOKUP($B51,'Cost prices'!$B$6:$H$538,7,FALSE),0) -> 3803.1826 | AQ51: =IF('External Prices'!AB$17<>"No",VLOOKUP($B51,'Cost prices'!$B$6:$H$538,7,FALSE),0) -> 3803.1826
A52: CIP to Vacuum hose | B52: MILKLAND 500MM | Z52: =IF('External Prices'!P$17<>"No",VLOOKUP($B52,'Cost prices'!$B$6:$H$538,7,FALSE),0) -> 3803.1826 | AK52: =IF('External Prices'!W$17<>"No",VLOOKUP($B52,'Cost prices'!$B$6:$H$538,7,FALSE),0) -> 3803.1826 | AL52: =IF('External Prices'!X$17<>"No",VLOOKUP($B52,'Cost prices'!$B$6:$H$538,7,FALSE),0) -> 3803.1826 | AM52: =IF('External Prices'!Y$17<>"No",VLOOKUP($B52,'Cost prices'!$B$6:$H$538,7,FALSE),0) -> 3803.1826 | AO52: =IF('External Prices'!Z$17<>"No",VLOOKUP($B52,'Cost prices'!$B$6:$H$538,7,FALSE),0) -> 3803.1826 | AP52: =IF('External Prices'!AA$17<>"No",VLOOKUP($B52,'Cost prices'!$B$6:$H$538,7,FALSE),0) -> 3803.1826 | AQ52: =IF('External Prices'!AB$17<>"No",VLOOKUP($B52,'Cost prices'!$B$6:$H$538,7,FALSE),0) -> 3803.1826
A53: Outlet hose | B53: OILY FOOD 3000MM | Z53: =IF('External Prices'!P35<>"No",VLOOKUP($B53,'Cost prices'!$B$6:$H$538,7,FALSE),0) -> 0 | AD53: =IF('External Prices'!R35<>"No",VLOOKUP($B53,'Cost prices'!$B$6:$H$538,7,FALSE),0) -> 0 | AE53: =IF('External Prices'!S35<>"No",VLOOKUP($B53,'Cost prices'!$B$6:$H$538,7,FALSE),0) -> 0 | AF53: =IF('External Prices'!T35<>"No",VLOOKUP($B53,'Cost prices'!$B$6:$H$538,7,FALSE),0) -> 0 | AH53: =IF('External Prices'!U35<>"No",VLOOKUP($B53,'Cost prices'!$B$6:$H$538,7,FALSE),0) -> 0 | AI53: =IF('External Prices'!V35<>"No",VLOOKUP($B53,'Cost prices'!$B$6:$H$538,7,FALSE),0) -> 0 | AK53: =IF('External Prices'!W35<>"No",VLOOKUP($B53,'Cost prices'!$B$6:$H$538,7,FALSE),0) -> 0 | AL53: =IF('External Prices'!X35<>"No",VLOOKUP($B53,'Cost prices'!$B$6:$H$538,7,FALSE),0) -> 0 | AM53: =IF('External Prices'!Y35<>"No",VLOOKUP($B53,'Cost prices'!$B$6:$H$538,7,FALSE),0) -> 0 | AO53: =IF('External Prices'!Z34<>"No",VLOOKUP($B53,'Cost prices'!$B$6:$H$538,7,FALSE),0) -> 0 | AP53: =IF('External Prices'!AA34<>"No",VLOOKUP($B53,'Cost prices'!$B$6:$H$538,7,FALSE),0) -> 0 | AQ53: =IF('External Prices'!AB34<>"No",VLOOKUP($B53,'Cost prices'!$B$6:$H$538,7,FALSE),0) -> 0
A54: Ingredients inlet hoses | B54: PHARMASTEEL 1000MM | Z54: =IF('External Prices'!P36<>"No", VLOOKUP($B54,'Cost prices'!$B$6:$H$538,7,FALSE) * ('External Prices'!K15+1), 0) -> 0 | AK54: =IF('External Prices'!W36<>"No", VLOOKUP($B54,'Cost prices'!$B$6:$H$538,7,FALSE) * ('External Prices'!W15+1), 0) -> 0 | AL54: =IF('External Prices'!X36<>"No", VLOOKUP($B54,'Cost prices'!$B$6:$H$538,7,FALSE) * ('External Prices'!X15+1), 0) -> 22967.923 | AM54: =IF('External Prices'!Y36<>"No", VLOOKUP($B54,'Cost prices'!$B$6:$H$538,7,FALSE) * ('External Prices'!Y15+1), 0) -> 0 | AO54: =IF('External Prices'!Z36<>"No", VLOOKUP($B54,'Cost prices'!$B$6:$H$538,7,FALSE) * ('External Prices'!Z15+1), 0) -> 0 | AP54: =IF('External Prices'!AA36<>"No", VLOOKUP($B54,'Cost prices'!$B$6:$H$538,7,FALSE) * ('External Prices'!AA15+1), 0) -> 22967.923 | AQ54: =IF('External Prices'!AB36<>"No", VLOOKUP($B54,'Cost prices'!$B$6:$H$538,7,FALSE) * ('External Prices'!AB15+1), 0) -> 0
B56: Manway OEM ø800 | W56: 1 | X56: =IF($W56="x","incl",VLOOKUP($B56,'Cost prices'!$B$6:$H$538,7,FALSE)*$W56) -> 14124
B58: Valves
A59: Full bore vavle | B59: BALL VALVE SBV-ISO51-W/W-MAN BALL VALVE SBV-ISO51-W/W-MAN - NBR | R59: =VLOOKUP($B59,'Cost prices'!$B$6:$H$376,7, FALSE) -> 4398.4996
A60: Vacuum | B60: Alfa Laval SSV - Vacuum
A61: CIP Vacuum Pump | B61: Alfa Laval SSV 2.5" SSV CIP model | Z61: =IF('External Prices'!P$17<>"No",VLOOKUP($B61,'Cost prices'!$B$6:$H$538,7,FALSE),0) -> 6028.5096 | AK61: =IF('External Prices'!W$17<>"No",VLOOKUP($B61,'Cost prices'!$B$6:$H$538,7,FALSE),0) -> 6028.5096 | AL61: =IF('External Prices'!X$17<>"No",VLOOKUP($B61,'Cost prices'!$B$6:$H$538,7,FALSE),0) -> 6028.5096 | AM61: =IF('External Prices'!Y$17<>"No",VLOOKUP($B61,'Cost prices'!$B$6:$H$538,7,FALSE),0) -> 6028.5096 | AO61: =IF('External Prices'!Z$17<>"No",VLOOKUP($B61,'Cost prices'!$B$6:$H$538,7,FALSE),0) -> 6028.5096 | AP61: =IF('External Prices'!AA$17<>"No",VLOOKUP($B61,'Cost prices'!$B$6:$H$538,7,FALSE),0) -> 6028.5096 | AQ61: =IF('External Prices'!AB$17<>"No",VLOOKUP($B61,'Cost prices'!$B$6:$H$538,7,FALSE),0) -> 6028.5096
A62: CIP Vacuum Pump | B62: Alfa Laval LKB - 2.5" SSV Tangential inlet | Z62: =IF('External Prices'!P$17<>"No",VLOOKUP($B62,'Cost prices'!$B$6:$H$538,7,FALSE),0) -> 6035.9696 | AK62: =IF('External Prices'!W$17<>"No",VLOOKUP($B62,'Cost prices'!$B$6:$H$538,7,FALSE),0) -> 6035.9696 | AL62: =IF('External Prices'!X$17<>"No",VLOOKUP($B62,'Cost prices'!$B$6:$H$538,7,FALSE),0) -> 6035.9696 | AM62: =IF('External Prices'!Y$17<>"No",VLOOKUP($B62,'Cost prices'!$B$6:$H$538,7,FALSE),0) -> 6035.9696 | AO62: =IF('External Prices'!Z$17<>"No",VLOOKUP($B62,'Cost prices'!$B$6:$H$538,7,FALSE),0) -> 6035.9696 | AP62: =IF('External Prices'!AA$17<>"No",VLOOKUP($B62,'Cost prices'!$B$6:$H$538,7,FALSE),0) -> 6035.9696 | AQ62: =IF('External Prices'!AB$17<>"No",VLOOKUP($B62,'Cost prices'!$B$6:$H$538,7,FALSE),0) -> 6035.9696
A63: CIP Vacuum Pump | B63: Alfa Laval LKB - 2 Vent pipe | Z63: =IF('External Prices'!P$17<>"No",VLOOKUP($B63,'Cost prices'!$B$6:$H$538,7,FALSE),0) -> 2588.629 | AK63: =IF('External Prices'!W$17<>"No",VLOOKUP($B63,'Cost prices'!$B$6:$H$538,7,FALSE),0) -> 2588.629 | AL63: =IF('External Prices'!X$17<>"No",VLOOKUP($B63,'Cost prices'!$B$6:$H$538,7,FALSE),0) -> 2588.629 | AM63: =IF('External Prices'!Y$17<>"No",VLOOKUP($B63,'Cost prices'!$B$6:$H$538,7,FALSE),0) -> 2588.629 | AO63: =IF('External Prices'!Z$17<>"No",VLOOKUP($B63,'Cost prices'!$B$6:$H$538,7,FALSE),0) -> 2588.629 | AP63: =IF('External Prices'!AA$17<>"No",VLOOKUP($B63,'Cost prices'!$B$6:$H$538,7,FALSE),0) -> 2588.629 | AQ63: =IF('External Prices'!AB$17<>"No",VLOOKUP($B63,'Cost prices'!$B$6:$H$538,7,FALSE),0) -> 2588.629
A64: CIP Vacuum Pump | B64: Alfa Laval LKB - 2 hose | Z64: =IF('External Prices'!P$17<>"No",VLOOKUP($B64,'Cost prices'!$B$6:$H$538,7,FALSE),0) -> 2588.629 | AK64: =IF('External Prices'!W$17<>"No",VLOOKUP($B64,'Cost prices'!$B$6:$H$538,7,FALSE),0) -> 2588.629 | AL64: =IF('External Prices'!X$17<>"No",VLOOKUP($B64,'Cost prices'!$B$6:$H$538,7,FALSE),0) -> 2588.629 | AM64: =IF('External Prices'!Y$17<>"No",VLOOKUP($B64,'Cost prices'!$B$6:$H$538,7,FALSE),0) -> 2588.629 | AO64: =IF('External Prices'!Z$17<>"No",VLOOKUP($B64,'Cost prices'!$B$6:$H$538,7,FALSE),0) -> 2588.629 | AP64: =IF('External Prices'!AA$17<>"No",VLOOKUP($B64,'Cost prices'!$B$6:$H$538,7,FALSE),0) -> 2588.629 | AQ64: =IF('External Prices'!AB$17<>"No",VLOOKUP($B64,'Cost prices'!$B$6:$H$538,7,FALSE),0) -> 2588.629
A65: CIP | B65: Alfa Laval SSV - CIP | Z65: - | AK65: - | AL65: - | AM65: - | AO65: - | AP65: - | AQ65: -
A66: Non-foam inlet | B66: Alfa Laval LKB - Non-foam inlet | Z66: =IF('External Prices'!P$21<>"No",VLOOKUP($B66,'Cost prices'!$B$6:$H$538,7,FALSE),0) -> 4498.9946 | AD66: =IF('External Prices'!R$21<>"No",VLOOKUP($B66,'Cost prices'!$B$6:$H$538,7,FALSE),0) -> 0 | AE66: =IF('External Prices'!S$21<>"No",VLOOKUP($B66,'Cost prices'!$B$6:$H$538,7,FALSE),0) -> 0 | AF66: =IF('External Prices'!T$21<>"No",VLOOKUP($B66,'Cost prices'!$B$6:$H$538,7,FALSE),0) -> 0 | AH66: =IF('External Prices'!U$21<>"No",VLOOKUP($B66,'Cost prices'!$B$6:$H$538,7,FALSE),0) -> 4498.9946 | AI66: =IF('External Prices'!V$21<>"No",VLOOKUP($B66,'Cost prices'!$B$6:$H$538,7,FALSE),0) -> 4498.9946 | AK66: =IF('External Prices'!W$21<>"No",VLOOKUP($B66,'Cost prices'!$B$6:$H$538,7,FALSE),0) -> 4498.9946 | AL66: =IF('External Prices'!X$21<>"No",VLOOKUP($B66,'Cost prices'!$B$6:$H$538,7,FALSE),0) -> 4498.9946 | AM66: =IF('External Prices'!Y$21<>"No",VLOOKUP($B66,'Cost prices'!$B$6:$H$538,7,FALSE),0) -> 4498.9946 | AO66: =IF('External Prices'!Z$21<>"No",VLOOKUP($B66,'Cost prices'!$B$6:$H$538,7,FALSE),0) -> 4498.9946 | AP66: =IF('External Prices'!AA$21<>"No",VLOOKUP($B66,'Cost prices'!$B$6:$H$538,7,FALSE),0) -> 4498.9946 | AQ66: =IF('External Prices'!AB$21<>"No",VLOOKUP($B66,'Cost prices'!$B$6:$H$538,7,FALSE),0) -> 4498.9946
A67: Tank relief valve BV | B67: Alfa Laval LKB - Relief valve BV | Z67: =IF($AJ67="x","incl",VLOOKUP($B67,'Cost prices'!$B$6:$H$538,7,FALSE)*$AJ67) -> 0 | AC67: 1 | AD67: =IF($AC67="x","incl",VLOOKUP($B67,'Cost prices'!$B$6:$H$538,7,FALSE)*$AC67) -> 4879.3864 | AE67: =IF($AC67="x","incl",VLOOKUP($B67,'Cost prices'!$B$6:$H$538,7,FALSE)*$AC67) -> 4879.3864 | AF67: =IF($AC67="x","incl",VLOOKUP($B67,'Cost prices'!$B$6:$H$538,7,FALSE)*$AC67) -> 4879.3864 | AG67: 1 | AH67: =IF($AG67="x","incl",VLOOKUP($B67,'Cost prices'!$B$6:$H$538,7,FALSE)*$AG67) -> 4879.3864 | AI67: =IF($AG67="x","incl",VLOOKUP($B67,'Cost prices'!$B$6:$H$538,7,FALSE)*$AG67) -> 4879.3864 | AK67: =IF($AJ67="x","incl",VLOOKUP($B67,'Cost prices'!$B$6:$H$538,7,FALSE)*$AJ67) -> 0 | AL67: =IF($AJ67="x","incl",VLOOKUP($B67,'Cost prices'!$B$6:$H$538,7,FALSE)*$AJ67) -> 0 | AM67: =IF($AJ67="x","incl",VLOOKUP($B67,'Cost prices'!$B$6:$H$538,7,FALSE)*$AJ67) -> 0 | AN67: 0 | AO67: =IF($AN67="x","incl",VLOOKUP($B67,'Cost prices'!$B$6:$H$538,7,FALSE)*$AN67) -> 0 | AP67: =IF($AN67="x","incl",VLOOKUP($B67,'Cost prices'!$B$6:$H$538,7,FALSE)*$AN67) -> 0 | AQ67: =IF($AN67="x","incl",VLOOKUP($B67,'Cost prices'!$B$6:$H$538,7,FALSE)*$AN67) -> 0
A68: Powder Wall | B68: Alfa Laval LKB - Powder Wall | Z68: =IF('External Prices'!P$17<>"No",VLOOKUP($B68,'Cost prices'!$B$6:$H$538,7,FALSE),0)*('External Prices'!K$15+1) -> 4497.9946 | AD68: - | AE68: - | AF68: - | AH68: - | AI68: - | AK68: =IF('External Prices'!W$17<>"No",VLOOKUP($B68,'Cost prices'!$B$6:$H$538,7,FALSE),0)*('External Prices'!W$15+1) -> 4497.9946 | AL68: =IF('External Prices'!X$17<>"No",VLOOKUP($B68,'Cost prices'!$B$6:$H$538,7,FALSE),0)*('External Prices'!X$15+1) -> 13493.984 | AM68: =IF('External Prices'!Y$17<>"No",VLOOKUP($B68,'Cost prices'!$B$6:$H$538,7,FALSE),0)*('External Prices'!Y$15+1) -> 4497.9946 | AO68: =IF('External Prices'!Z$17<>"No",VLOOKUP($B68,'Cost prices'!$B$6:$H$538,7,FALSE),0)*('External Prices'!Z$15+1) -> 13493.984 | AP68: =IF('External Prices'!AA$17<>"No",VLOOKUP($B68,'Cost prices'!$B$6:$H$538,7,FALSE),0)*('External Prices'!AA$15+1) -> 13493.984 | AQ68: =IF('External Prices'!AB$17<>"No",VLOOKUP($B68,'Cost prices'!$B$6:$H$538,7,FALSE),0)*('External Prices'!AB$15+1) -> 4497.9946
A69: Tangential | B69: Alfa Laval LKB - Tangential inlet | W69: 3 | X69: =IF($W69="x","incl",VLOOKUP($B69,'Cost prices'!$B$6:$H$538,7,FALSE)*$W69) -> 8655.492 | Z69: - | AD69: =IF('External Prices'!R$22<>"No",VLOOKUP($B69,'Cost prices'!$B$6:$H$538,7,FALSE),0) -> 0 | AE69: =IF('External Prices'!S$22<>"No",VLOOKUP($B69,'Cost prices'!$B$6:$H$538,7,FALSE),0) -> 0 | AF69: =IF('External Prices'!T$22<>"No",VLOOKUP($B69,'Cost prices'!$B$6:$H$538,7,FALSE),0) -> 0 | AH69: =IF('External Prices'!U$22<>"No",VLOOKUP($B69,'Cost prices'!$B$6:$H$538,7,FALSE),0) -> 0 | AI69: =IF('External Prices'!V$22<>"No",VLOOKUP($B69,'Cost prices'!$B$6:$H$538,7,FALSE),0) -> 0 | AK69: - | AL69: - | AM69: - | AO69: - | AP69: - | AQ69: -
A70: Small tanks | B70: Alfa Laval Manual butterfly valve | Z70: =IF('External Prices'!P$23<>"No",VLOOKUP($B70,'Cost prices'!$B$6:$H$538,7,FALSE),0) -> 754.1404 | AD70: - | AE70: - | AF70: - | AH70: - | AI70: - | AK70: =IF('External Prices'!W$23<>"No",VLOOKUP($B70,'Cost prices'!$B$6:$H$538,7,FALSE),0) -> 754.1404 | AL70: =IF('External Prices'!X$23<>"No",VLOOKUP($B70,'Cost prices'!$B$6:$H$538,7,FALSE),0) -> 754.1404 | AM70: =IF('External Prices'!Y$23<>"No",VLOOKUP($B70,'Cost prices'!$B$6:$H$538,7,FALSE),0) -> 754.1404 | AO70: =IF('External Prices'!Z$23<>"No",VLOOKUP($B70,'Cost prices'!$B$6:$H$538,7,FALSE),0) -> 754.1404 | AP70: =IF('External Prices'!AA$23<>"No",VLOOKUP($B70,'Cost prices'!$B$6:$H$538,7,FALSE),0) -> 754.1404 | AQ70: =IF('External Prices'!AB$23<>"No",VLOOKUP($B70,'Cost prices'!$B$6:$H$538,7,FALSE),0) -> 754.1404
A71: Bottom | B71: Outlet valve | Y71: 1 | Z71: =IF($AJ71="x","incl",VLOOKUP($B71,'Cost prices'!$B$6:$H$538,7,FALSE)*$Y71) -> 5718.4552 | AC71: 1 | AD71: =IF($AC71="x","incl",VLOOKUP($B71,'Cost prices'!$B$6:$H$538,7,FALSE)*$AC71) -> 5718.4552 | AE71: =IF($AC71="x","incl",VLOOKUP($B71,'Cost prices'!$B$6:$H$538,7,FALSE)*$AC71) -> 5718.4552 | AF71: =IF($AC71="x","incl",VLOOKUP($B71,'Cost prices'!$B$6:$H$538,7,FALSE)*$AC71) -> 5718.4552 | AG71: 1 | AH71: =IF($AG71="x","incl",VLOOKUP($B71,'Cost prices'!$B$6:$H$538,7,FALSE)*$AG71) -> 5718.4552 | AI71: =IF($AG71="x","incl",VLOOKUP($B71,'Cost prices'!$B$6:$H$538,7,FALSE)*$AG71) -> 5718.4552 | AJ71: 1 | AK71: =IF($AJ71="x","incl",VLOOKUP($B71,'Cost prices'!$B$6:$H$538,7,FALSE)*$AJ71) -> 5718.4552 | AL71: =IF($AJ71="x","incl",VLOOKUP($B71,'Cost prices'!$B$6:$H$538,7,FALSE)*$AJ71) -> 5718.4552 | AM71: =IF($AJ71="x","incl",VLOOKUP($B71,'Cost prices'!$B$6:$H$538,7,FALSE)*$AJ71) -> 5718.4552 | AN71: 1 | AO71: =IF($AN71="x","incl",VLOOKUP($B71,'Cost prices'!$B$6:$H$538,7,FALSE)*$AN71) -> 5718.4552 | AP71: =IF($AN71="x","incl",VLOOKUP($B71,'Cost prices'!$B$6:$H$538,7,FALSE)*$AN71) -> 5718.4552 | AQ71: =IF($AN71="x","incl",VLOOKUP($B71,'Cost prices'!$B$6:$H$538,7,FALSE)*$AN71) -> 5718.4552
A72: Actuated valves | B72: V50 TinkTop | J72: =IF('External Prices'!H$16="Yes",VLOOKUP($B72,'Cost prices'!$B$6:$H$538,7,FALSE)*$I$75,0) -> 0 | V72: =IF('External Prices'!N$16="Yes",VLOOKUP($B72,'Cost prices'!$B$6:$H$538,7,FALSE)*$I$75,0) -> 5914.306 | X72: =IF('External Prices'!O$16="Yes",VLOOKUP($B72,'Cost prices'!$B$6:$H$538,7,FALSE)*$W$69,0) -> 0 | Z72: =IF('External Prices'!P$16="Yes", VLOOKUP($B72, 'Cost prices'!$B$6:$H$538, 7, FALSE) * (COUNTIFS(Z$61:Z$71, "<>0", Z$61:Z$71, "<>-") -1 + 'External Prices'!K$15), 0) -> 0 | AD72: =IF('External Prices'!R$16="Yes", VLOOKUP($B72, 'Cost prices'!$B$6:$H$538, 7, FALSE) * (COUNTIFS(AD$66:AD$71, "<>0", AD$66:AD$71, "<>-") + 'External Prices'!R$15), 0) -> 0 | AE72: =IF('External Prices'!S$16="Yes", VLOOKUP($B72, 'Cost prices'!$B$6:$H$538, 7, FALSE) * (COUNTIFS(AE$66:AE$71, "<>0", AE$66:AE$71, "<>-") + 'External Prices'!S$15), 0) -> 0 | AF72: =IF('External Prices'!T$16="Yes", VLOOKUP($B72, 'Cost prices'!$B$6:$H$538, 7, FALSE) * (COUNTIFS(AF$66:AF$71, "<>0", AF$66:AF$71, "<>-") + 'External Prices'!T$15), 0) -> 0 | AH72: =IF('External Prices'!U$16="Yes", VLOOKUP($B72, 'Cost prices'!$B$6:$H$538, 7, FALSE) * (COUNTIFS(AH$66:AH$71, "<>0", AH$66:AH$71, "<>-") + 'External Prices'!V$15), 0) -> 0 | AI72: =IF('External Prices'!V$16="Yes", VLOOKUP($B72, 'Cost prices'!$B$6:$H$538, 7, FALSE) * (COUNTIFS(AI$66:AI$71, "<>0", AI$66:AI$71, "<>-") + 'External Prices'!W$15), 0) -> 0 | AK72: =IF('External Prices'!W$16="Yes", VLOOKUP($B72, 'Cost prices'!$B$6:$H$538, 7, FALSE) * (COUNTIFS(AK$61:AK$71, "<>0", AK$61:AK$71, "<>-") -1 + 'External Prices'!W$15), 0) -> 0 | AL72: =IF('External Prices'!X$16="Yes", VLOOKUP($B72, 'Cost prices'!$B$6:$H$538, 7, FALSE) * (COUNTIFS(AL$61:AL$71, "<>0", AL$61:AL$71, "<>-") -1 + 'External Prices'!X$15), 0) -> 26614.377 | AM72: =IF('External Prices'!Y$16="Yes", VLOOKUP($B72, 'Cost prices'!$B$6:$H$538, 7, FALSE) * (COUNTIFS(AM$61:AM$71, "<>0", AM$61:AM$71, "<>-") -1 + 'External Prices'!Y$15), 0) -> 0 | AO72: =IF('External Prices'!Z$16="Yes", VLOOKUP($B72, 'Cost prices'!$B$6:$H$538, 7, FALSE) * (COUNTIFS(AO$61:AO$71, "<>0", AO$61:AO$71, "<>-") -1 + 'External Prices'!Z$15), 0) -> 0 | AP72: =IF('External Prices'!AA$16="Yes", VLOOKUP($B72, 'Cost prices'!$B$6:$H$538, 7, FALSE) * (COUNTIFS(AP$61:AP$71, "<>0", AP$61:AP$71, "<>-") -1 + 'External Prices'!AA$15), 0) -> 26614.377 | AQ72: =IF('External Prices'!AB$16="Yes", VLOOKUP($B72, 'Cost prices'!$B$6:$H$538, 7, FALSE) * (COUNTIFS(AQ$61:AQ$71, "<>0", AQ$61:AQ$71, "<>-") -1 + 'External Prices'!AB$15), 0) -> 0
A73: Drain | B73: VALVE LKB 25/1" ISO W/W EPDM 316L | F73: Incl Brian | H73: Incl Brian | I73: 1 | J73: Incl Brian | L73: =IF($I73="x","incl",VLOOKUP($B73,'Cost prices'!$B$6:$H$538,7,FALSE)*$I73) -> 566.8198 | P73: =IF($I73="x","incl",VLOOKUP($B73,'Cost prices'!$B$6:$H$538,7,FALSE)*$I73) -> 566.8198 | R73: =IF($I73="x","incl",VLOOKUP($B73,'Cost prices'!$B$6:$H$538,7,FALSE)*$I73) -> 566.8198 | V73: =IF($I73="x","incl",VLOOKUP($B73,'Cost prices'!$B$6:$H$538,7,FALSE)*$I73) -> 566.8198 | W73: 1 | X73: =IF($W73="x","incl",VLOOKUP($B73,'Cost prices'!$B$6:$H$538,7,FALSE)*$W73) -> 566.8198 | Y73: 1 | Z73: =IF($Y73="x","incl",VLOOKUP($B73,'Cost prices'!$B$6:$H$538,7,FALSE)*$Y73) -> 566.8198
A74: Drain | B74: HANDLE 1.1 FOR LKB POS.A REGULATING 90 25-63.5/DN25-50 | I74: 1 | L74: =IF($I74="x","incl",VLOOKUP($B74,'Cost prices'!$B$6:$H$538,7,FALSE)*$I74) -> 480.2092 | P74: =IF($I74="x","incl",VLOOKUP($B74,'Cost prices'!$B$6:$H$538,7,FALSE)*$I74) -> 480.2092 | R74: =IF($I74="x","incl",VLOOKUP($B74,'Cost prices'!$B$6:$H$538,7,FALSE)*$I74) -> 480.2092 | V74: =IF($I74="x","incl",VLOOKUP($B74,'Cost prices'!$B$6:$H$538,7,FALSE)*$I74) -> 480.2092 | W74: 1 | X74: =IF($W74="x","incl",VLOOKUP($B74,'Cost prices'!$B$6:$H$538,7,FALSE)*$W74) -> 480.2092 | Y74: 1 | Z74: =IF($Y74="x","incl",VLOOKUP($B74,'Cost prices'!$B$6:$H$538,7,FALSE)*$Y74) -> 480.2092
A75: Regulating | B75: VALVE LKB 63,5/2½" ISO W/W EPDM 316L | I75: 2 | J75: Incl Brian | V75: =IF($I75="x","incl",VLOOKUP($B75,'Cost prices'!$B$6:$H$538,7,FALSE)*$I75) -> 1572.7352 | X75: =IF($I75="x","incl",VLOOKUP($B75,'Cost prices'!$B$6:$H$538,7,FALSE)*$I75) -> 1572.7352
A76: Regulating | B76: HANDLE 1.1 FOR LKB POS.A REGULATING 90 25-63.5/DN25-50 | I76: 2 | V76: =IF($I76="x","incl",VLOOKUP($B76,'Cost prices'!$B$6:$H$538,7,FALSE)*$I76) -> 960.4184 | X76: =IF($I76="x","incl",VLOOKUP($B76,'Cost prices'!$B$6:$H$538,7,FALSE)*$I76) -> 960.4184
A77: Regulating Automatic | B77: 9618582903 VALVE LKB 76/3" ISO W/W PFA 316L KIT ACT LKLA-T Ø85 NC 6MM POS W/DISPLAY | I77: 0 | J77: Incl Brian | V77: =IF($I77="x","incl",VLOOKUP($B77,'Cost prices'!$B$6:$H$538,7,FALSE)*$I77) -> 0 | X77: =IF($I77="x","incl",VLOOKUP($B77,'Cost prices'!$B$6:$H$538,7,FALSE)*$I77) -> 0
A78: Regulating | B78: HANDLE 1.1 FOR LKB POS.A REGULATING 90 76.1/DN65-80 | I78: 1 | V78: =IF($I78="x","incl",VLOOKUP($B78,'Cost prices'!$B$6:$H$538,7,FALSE)*$I78) -> 524.5216 | X78: =IF($I78="x","incl",VLOOKUP($B78,'Cost prices'!$B$6:$H$538,7,FALSE)*$I78) -> 524.5216
A79: Regulating Automatic | B79: VALVE LKB 76/3" ISO W/W. EPDM 316L | I79: 1 | V79: =IF($I79="x","incl",VLOOKUP($B79,'Cost prices'!$B$6:$H$538,7,FALSE)*$I79) -> 1001.887 | X79: =IF($I79="x","incl",VLOOKUP($B79,'Cost prices'!$B$6:$H$538,7,FALSE)*$I79) -> 1001.887
A80: CIP | B80: SPRAYBALL LKRK-2F Ø64MM FOR 25MM INCH TUBE 2 MM HOLES 316L | I80: 1 | V80: =IF($I80="x","incl",VLOOKUP($B80,'Cost prices'!$B$6:$H$538,7,FALSE)*$I80) -> 733.9984
A81: CIP | B81: TE14B23001 SaniMicro 360° 3/4" WELD | I81: 1 | J81: Incl Brian | X81: =IF($I81="x","incl",VLOOKUP($B81,'Cost prices'!$B$6:$H$538,7,FALSE)*$I81) -> 2420.3314
A82: CIP valve | B82: VALVE LKB 25/1" ISO W/W EPDM 316L | I82: 1 | V82: =IF($I82="x","incl",VLOOKUP($B82,'Cost prices'!$B$6:$H$538,7,FALSE)*$I82) -> 566.8198
A83: CIP valve | B83: HANDLE 1.1 FOR LKB POS.A REGULATING 90 25-63.5/DN25-50 | I83: 1 | V83: =IF($I83="x","incl",VLOOKUP($B83,'Cost prices'!$B$6:$H$538,7,FALSE)*$I83) -> 480.2092
A84: CIP valve | B84: 9618581826 VALVE LKB 38/1½" ISO W/W PFA 316L KIT HANDLE 1.1 W/2 POS TYPE | I84: 1 | J84: Incl Brian | W84: 1 | X84: =IF($W84="x","incl",VLOOKUP($B84,'Cost prices'!$B$6:$H$538,7,FALSE)*$W84) -> 1418.8264 | Y84: 1
A85: CIP pneumatic | B85: 9612194002 LUFTMOTOR LKLA-T Ö85 25-63,5/ 25-63.5/DN25-50 NC | I85: 1 | J85: Incl Brian | V85: =IF($I85="x","incl",VLOOKUP($B85,'Cost prices'!$B$6:$H$538,7,FALSE)*$I85) -> 2031.1432 | W85: 1 | X85: =IF($W85="x","incl",VLOOKUP($B85,'Cost prices'!$B$6:$H$538,7,FALSE)*$W85) -> 2031.1432 | Y85: 1
A86: Back pressure | B86: VALVE LKB 63,5/2½" ISO W/W EPDM 316L | I86: 1 | P86: =IF($I86="x","incl",VLOOKUP($B86,'Cost prices'!$B$6:$H$538,7,FALSE)*$I86) -> 786.3676 | R86: =IF($I86="x","incl",VLOOKUP($B86,'Cost prices'!$B$6:$H$538,7,FALSE)*$I86) -> 786.3676
A87: Back pressure | B87: HANDLE 1.1 FOR LKB POS.A REGULATING 90 25-63.5/DN25-50 | I87: 1 | P87: =IF($I87="x","incl",VLOOKUP($B87,'Cost prices'!$B$6:$H$538,7,FALSE)*$I87) -> 480.2092 | R87: =IF($I87="x","incl",VLOOKUP($B87,'Cost prices'!$B$6:$H$538,7,FALSE)*$I87) -> 480.2092
A88: Air Vent | B88: RELIEF VALVE, TWOWAY 316 MAX. FLOW 300hl/h, OIL WORKING | I88: 1 | J88: Incl Brian | W88: 1 | X88: =IF($W88="x","incl",VLOOKUP($B88,'Cost prices'!$B$6:$H$538,7,FALSE)*$W88) -> 857.909
A89: IFM | B89: MN501S++ | I89: 1 | J89: Incl Brian
A90: IFM | B90: LMT102++ | I90: 1 | J90: Incl Brian
A91: IFM | B91: PM1608++ | I91: 0 | J91: =IF($I91="x","incl",VLOOKUP($B91,'Cost prices'!$B$6:$H$538,7,FALSE)*$I91) -> 0
B93: Process parts
B94: Nordgan motor | AN94: 1 | AO94: =IF('External Prices'!Z$27<>"No",0, IF($AN94="x","incl",VLOOKUP($B94,'Cost prices'!$B$6:$H$538,7,FALSE)*$AN94)) -> 15364.14 | AP94: =IF('External Prices'!AA$27<>"No",0, IF($AN94="x","incl",VLOOKUP($B94,'Cost prices'!$B$6:$H$538,7,FALSE)*$AN94)) -> 15364.14 | AQ94: =IF('External Prices'!AB$27<>"No",0, IF($AN94="x","incl",VLOOKUP($B94,'Cost prices'!$B$6:$H$538,7,FALSE)*$AN94)*1.5) -> 23046.21
B95: Seal | AN95: 1 | AO95: =IF($AN95="x","incl",VLOOKUP($B95,'Cost prices'!$B$6:$H$538,7,FALSE)*$AN95) -> 1000 | AP95: =IF($AN95="x","incl",VLOOKUP($B95,'Cost prices'!$B$6:$H$538,7,FALSE)*$AN95) -> 1000 | AQ95: =IF($AN95="x","incl",VLOOKUP($B95,'Cost prices'!$B$6:$H$538,7,FALSE)*$AN95) -> 1000
B96: Peek blades | AN96: 12 | AO96: =IF($AN96="x","incl",VLOOKUP($B96,'Cost prices'!$B$6:$H$538,7,FALSE)*$AN96) -> 15600 | AP96: =IF($AN96="x","incl",VLOOKUP($B96,'Cost prices'!$B$6:$H$538,7,FALSE)*$AN96) -> 15600 | AQ96: =IF($AN96="x","incl",VLOOKUP($B96,'Cost prices'!$B$6:$H$538,7,FALSE)*$AN96)*1.5 -> 23400
B97: Other | AN97: 1 | AO97: =IF($AN97="x","incl",VLOOKUP($B97,'Cost prices'!$B$6:$H$538,7,FALSE)*$AN97) -> 3500 | AP97: =IF($AN97="x","incl",VLOOKUP($B97,'Cost prices'!$B$6:$H$538,7,FALSE)*$AN97) -> 3500 | AQ97: =IF($AN97="x","incl",VLOOKUP($B97,'Cost prices'!$B$6:$H$538,7,FALSE)*$AN97)*1.5 -> 5250
B99: Coaxial system | AO99: =IF('External Prices'!Z$27<>"No",VLOOKUP('External Prices'!B27,'Cost prices'!$B$6:$H$538,7,FALSE),0) -> 0 | AP99: =IF('External Prices'!AA$27<>"No",VLOOKUP('External Prices'!B27,'Cost prices'!$B$6:$H$538,7,FALSE),0) -> 0 | AQ99: =IF('External Prices'!AB$27<>"No",VLOOKUP('External Prices'!B27,'Cost prices'!$B$6:$H$538,7,FALSE),0) -> 0
B100: Steam Injection nozzles | AO100: =IF('External Prices'!Z$29<>"No",VLOOKUP('External Prices'!B29,'Cost prices'!$B$6:$H$538,7,FALSE),0) -> 0 | AP100: =IF('External Prices'!AA$29<>"No",VLOOKUP('External Prices'!B29,'Cost prices'!$B$6:$H$538,7,FALSE),0) -> 0 | AQ100: =IF('External Prices'!AB$29<>"No",VLOOKUP('External Prices'!B29,'Cost prices'!$B$6:$H$538,7,FALSE),0) -> 0
B101: Culinary steam unit, 5 µm | AO101: =IF('External Prices'!Z$30<>"No",VLOOKUP('External Prices'!B30,'Cost prices'!$B$6:$H$538,7,FALSE),0) -> 0 | AP101: =IF('External Prices'!AA$30<>"No",VLOOKUP('External Prices'!B30,'Cost prices'!$B$6:$H$538,7,FALSE),0) -> 0 | AQ101: =IF('External Prices'!AB$30<>"No",VLOOKUP('External Prices'!B30,'Cost prices'!$B$6:$H$538,7,FALSE),0) -> 0
B103: Vacuum system
A104: Busch | B104: Vacuum pump | Z104: =IF('External Prices'!P$17<>"No",VLOOKUP('External Prices'!P17,'Cost prices'!$B$6:$H$538,7,FALSE),0) -> 38815.05 | AK104: =IF('External Prices'!W$17<>"No",VLOOKUP('External Prices'!W17,'Cost prices'!$B$6:$H$538,7,FALSE),0) -> 60595.85 | AL104: =IF('External Prices'!X$17<>"No",VLOOKUP('External Prices'!X17,'Cost prices'!$B$6:$H$538,7,FALSE),0) -> 60595.85 | AM104: =IF('External Prices'!Y$17<>"No",VLOOKUP('External Prices'!Y17,'Cost prices'!$B$6:$H$538,7,FALSE),0) -> 60595.85 | AO104: =IF('External Prices'!Z$17<>"No",VLOOKUP('External Prices'!Z17,'Cost prices'!$B$6:$H$538,7,FALSE),0) -> 51957.45 | AP104: =IF('External Prices'!AA$17<>"No",VLOOKUP('External Prices'!AA17,'Cost prices'!$B$6:$H$538,7,FALSE),0) -> 60595.85 | AQ104: =IF('External Prices'!AB$17<>"No",VLOOKUP('External Prices'!AB17,'Cost prices'!$B$6:$H$538,7,FALSE),0) -> 60595.85
B106: Internal DK shipment Fredensborg to Bjerringbro | D106: 1 | E106: =IF(D106="x","incl",VLOOKUP($B106,'Cost prices'!$B$6:$H$538,7,FALSE)*D106) -> 950 | F106: =IF(D106="x","incl",VLOOKUP($B106,'Cost prices'!$B$6:$H$538,7,FALSE)*D106) -> 950 | G106: 1 | H106: =IF($G106="x","incl",VLOOKUP($B106,'Cost prices'!$B$6:$H$538,7,FALSE)*$G106) -> 950 | I106: 1 | J106: =IF($I106="x","incl",VLOOKUP($B106,'Cost prices'!$B$6:$H$538,7,FALSE)*$I106) -> 950 | K106: 1 | L106: =IF(K106="x","incl",VLOOKUP($B106,'Cost prices'!$B$6:$H$538,7,FALSE)*K106) -> 950 | N106: =IF($M106="x","incl",VLOOKUP($B106,'Cost prices'!$B$6:$H$538,7,FALSE)*$M106) -> 0 | P106: =IF($M106="x","incl",VLOOKUP($B106,'Cost prices'!$B$6:$H$538,7,FALSE)*$M106) -> 0 | R106: =IF($Q106="x","incl",VLOOKUP($B106,'Cost prices'!$B$6:$H$538,7,FALSE)*$Q106) -> 0 | U106: 0 | V106: =IF($U106="x","incl",VLOOKUP($B106,'Cost prices'!$B$6:$H$538,7,FALSE)*$U106) -> 0 | W106: 0 | X106: =IF($W106="x","incl",VLOOKUP($B106,'Cost prices'!$B$6:$H$538,7,FALSE)*$W106) -> 0 | Y106: 0 | Z106: =IF($Y106="x","incl",VLOOKUP($B106,'Cost prices'!$B$6:$H$538,7,FALSE)*$Y106) -> 0 | AA106: 0 | AB106: =IF($AA106="x","incl",VLOOKUP($B106,'Cost prices'!$B$6:$H$538,7,FALSE)*$AA106) -> 0 | AC106: 0 | AD106: =IF($AC106="x","incl",VLOOKUP($B106,'Cost prices'!$B$6:$H$538,7,FALSE)*$AC106) -> 0 | AE106: =IF($AC106="x","incl",VLOOKUP($B106,'Cost prices'!$B$6:$H$538,7,FALSE)*$AC106) -> 0 | AF106: =IF($AC106="x","incl",VLOOKUP($B106,'Cost prices'!$B$6:$H$538,7,FALSE)*$AC106) -> 0 | AG106: 0 | AH106: =IF($AG106="x","incl",VLOOKUP($B106,'Cost prices'!$B$6:$H$538,7,FALSE)*$AG106) -> 0 | AI106: =IF($AG106="x","incl",VLOOKUP($B106,'Cost prices'!$B$6:$H$538,7,FALSE)*$AG106) -> 0 | AJ106: 0 | AK106: =IF($AJ106="x","incl",VLOOKUP($B106,'Cost prices'!$B$6:$H$538,7,FALSE)*$AJ106) -> 0 | AL106: =IF($AJ106="x","incl",VLOOKUP($B106,'Cost prices'!$B$6:$H$538,7,FALSE)*$AJ106) -> 0 | AM106: =IF($AJ106="x","incl",VLOOKUP($B106,'Cost prices'!$B$6:$H$538,7,FALSE)*$AJ106) -> 0 | AN106: 0 | AO106: =IF($AN106="x","incl",VLOOKUP($B106,'Cost prices'!$B$6:$H$538,7,FALSE)*$AN106) -> 0 | AP106: =IF($AN106="x","incl",VLOOKUP($B106,'Cost prices'!$B$6:$H$538,7,FALSE)*$AN106) -> 0 | AQ106: =IF($AN106="x","incl",VLOOKUP($B106,'Cost prices'!$B$6:$H$538,7,FALSE)*$AN106) -> 0 | AR106: 0.5 | AS106: =IF($AR106="x","incl",VLOOKUP($B106,'Cost prices'!$B$6:$H$538,7,FALSE)*$AR106) -> 475 | AT106: =IF($AR106="x","incl",VLOOKUP($B106,'Cost prices'!$B$6:$H$538,7,FALSE)*$AR106) -> 475 | AU106: =IF($AR106="x","incl",VLOOKUP($B106,'Cost prices'!$B$6:$H$538,7,FALSE)*$AR106) -> 475 | AV106: =IF($AR106="x","incl",VLOOKUP($B106,'Cost prices'!$B$6:$H$538,7,FALSE)*$AR106) -> 475 | AW106: =IF($AR106="x","incl",VLOOKUP($B106,'Cost prices'!$B$6:$H$538,7,FALSE)*$AR106) -> 475 | AX106: =IF($AR106="x","incl",VLOOKUP($B106,'Cost prices'!$B$6:$H$538,7,FALSE)*$AR106) -> 475 | AY106: =IF($AR106="x","incl",VLOOKUP($B106,'Cost prices'!$B$6:$H$538,7,FALSE)*$AR106) -> 475 | AZ106: =IF($AR106="x","incl",VLOOKUP($B106,'Cost prices'!$B$6:$H$538,7,FALSE)*$AR106) -> 475 | BA106: =IF($AR106="x","incl",VLOOKUP($B106,'Cost prices'!$B$6:$H$538,7,FALSE)*$AR106) -> 475
B107: Internal DK shipment Bjerringbro to Hartrodt | D107: 1 | E107: =IF(D107="x","incl",VLOOKUP($B107,'Cost prices'!$B$6:$H$538,7,FALSE)*D107) -> 1025 | F107: =IF(D107="x","incl",VLOOKUP($B107,'Cost prices'!$B$6:$H$538,7,FALSE)*D107) -> 1025 | G107: 1 | H107: =IF($G107="x","incl",VLOOKUP($B107,'Cost prices'!$B$6:$H$538,7,FALSE)*$G107) -> 1025 | I107: 1 | J107: =IF($I107="x","incl",VLOOKUP($B107,'Cost prices'!$B$6:$H$538,7,FALSE)*$I107) -> 1025 | K107: 1 | L107: =IF(K107="x","incl",VLOOKUP($B107,'Cost prices'!$B$6:$H$538,7,FALSE)*K107) -> 1025 | N107: =IF($M107="x","incl",VLOOKUP($B107,'Cost prices'!$B$6:$H$538,7,FALSE)*$M107) -> 0 | P107: =IF($M107="x","incl",VLOOKUP($B107,'Cost prices'!$B$6:$H$538,7,FALSE)*$M107) -> 0 | R107: =IF($Q107="x","incl",VLOOKUP($B107,'Cost prices'!$B$6:$H$538,7,FALSE)*$Q107) -> 0 | U107: 0 | V107: =IF($U107="x","incl",VLOOKUP($B107,'Cost prices'!$B$6:$H$538,7,FALSE)*$U107) -> 0 | W107: 0 | X107: =IF($W107="x","incl",VLOOKUP($B107,'Cost prices'!$B$6:$H$538,7,FALSE)*$W107) -> 0 | Y107: 0 | Z107: =IF($Y107="x","incl",VLOOKUP($B107,'Cost prices'!$B$6:$H$538,7,FALSE)*$Y107) -> 0 | AA107: 0 | AB107: =IF($AA107="x","incl",VLOOKUP($B107,'Cost prices'!$B$6:$H$538,7,FALSE)*$AA107) -> 0 | AC107: 0 | AD107: =IF($AC107="x","incl",VLOOKUP($B107,'Cost prices'!$B$6:$H$538,7,FALSE)*$AC107) -> 0 | AE107: =IF($AC107="x","incl",VLOOKUP($B107,'Cost prices'!$B$6:$H$538,7,FALSE)*$AC107) -> 0 | AF107: =IF($AC107="x","incl",VLOOKUP($B107,'Cost prices'!$B$6:$H$538,7,FALSE)*$AC107) -> 0 | AG107: 0 | AH107: =IF($AG107="x","incl",VLOOKUP($B107,'Cost prices'!$B$6:$H$538,7,FALSE)*$AG107) -> 0 | AI107: =IF($AG107="x","incl",VLOOKUP($B107,'Cost prices'!$B$6:$H$538,7,FALSE)*$AG107) -> 0 | AJ107: 0 | AK107: =IF($AJ107="x","incl",VLOOKUP($B107,'Cost prices'!$B$6:$H$538,7,FALSE)*$AJ107) -> 0 | AL107: =IF($AJ107="x","incl",VLOOKUP($B107,'Cost prices'!$B$6:$H$538,7,FALSE)*$AJ107) -> 0 | AM107: =IF($AJ107="x","incl",VLOOKUP($B107,'Cost prices'!$B$6:$H$538,7,FALSE)*$AJ107) -> 0 | AN107: 0 | AO107: =IF($AN107="x","incl",VLOOKUP($B107,'Cost prices'!$B$6:$H$538,7,FALSE)*$AN107) -> 0 | AP107: =IF($AN107="x","incl",VLOOKUP($B107,'Cost prices'!$B$6:$H$538,7,FALSE)*$AN107) -> 0 | AQ107: =IF($AN107="x","incl",VLOOKUP($B107,'Cost prices'!$B$6:$H$538,7,FALSE)*$AN107) -> 0
B108: Internal DK shipment Fredensborg to Hardrodt | D108: 0 | E108: =IF(D108="x","incl",VLOOKUP($B108,'Cost prices'!$B$6:$H$538,7,FALSE)*D108) -> 0 | F108: =IF(D108="x","incl",VLOOKUP($B108,'Cost prices'!$B$6:$H$538,7,FALSE)*D108) -> 0 | G108: 0 | H108: =IF($G108="x","incl",VLOOKUP($B108,'Cost prices'!$B$6:$H$538,7,FALSE)*$G108) -> 0 | I108: 0 | J108: =IF($I108="x","incl",VLOOKUP($B108,'Cost prices'!$B$6:$H$538,7,FALSE)*$I108) -> 0 | K108: 0 | L108: =IF(K108="x","incl",VLOOKUP($B108,'Cost prices'!$B$6:$H$538,7,FALSE)*K108) -> 0 | M108: 1 | N108: =IF($M108="x","incl",VLOOKUP($B108,'Cost prices'!$B$6:$H$538,7,FALSE)*$M108) -> 913 | O108: 1 | P108: =IF($M108="x","incl",VLOOKUP($B108,'Cost prices'!$B$6:$H$538,7,FALSE)*$M108) -> 913 | Q108: 1 | R108: =IF($Q108="x","incl",VLOOKUP($B108,'Cost prices'!$B$6:$H$538,7,FALSE)*$Q108) -> 913 | U108: 1 | V108: =IF($U108="x","incl",VLOOKUP($B108,'Cost prices'!$B$6:$H$538,7,FALSE)*$U108) -> 913 | W108: 1 | X108: =IF($W108="x","incl",VLOOKUP($B108,'Cost prices'!$B$6:$H$538,7,FALSE)*$W108) -> 913 | Y108: 1 | Z108: =IF($Y108="x","incl",VLOOKUP($B108,'Cost prices'!$B$6:$H$538,7,FALSE)*$Y108) -> 913 | AA108: 1 | AB108: =IF($AA108="x","incl",VLOOKUP($B108,'Cost prices'!$B$6:$H$538,7,FALSE)*$AA108) -> 913 | AC108: 1 | AD108: =IF($AC108="x","incl",VLOOKUP($B108,'Cost prices'!$B$6:$H$538,7,FALSE)*$AC108) -> 913 | AE108: =IF($AC108="x","incl",VLOOKUP($B108,'Cost prices'!$B$6:$H$538,7,FALSE)*$AC108) -> 913 | AF108: =IF($AC108="x","incl",VLOOKUP($B108,'Cost prices'!$B$6:$H$538,7,FALSE)*$AC108) -> 913 | AG108: 1 | AH108: =IF($AG108="x","incl",VLOOKUP($B108,'Cost prices'!$B$6:$H$538,7,FALSE)*$AG108) -> 913 | AI108: =IF($AG108="x","incl",VLOOKUP($B108,'Cost prices'!$B$6:$H$538,7,FALSE)*$AG108) -> 913 | AJ108: 1 | AK108: =IF($AJ108="x","incl",VLOOKUP($B108,'Cost prices'!$B$6:$H$538,7,FALSE)*$AJ108) -> 913 | AL108: =IF($AJ108="x","incl",VLOOKUP($B108,'Cost prices'!$B$6:$H$538,7,FALSE)*$AJ108) -> 913 | AM108: =IF($AJ108="x","incl",VLOOKUP($B108,'Cost prices'!$B$6:$H$538,7,FALSE)*$AJ108) -> 913 | AN108: 1 | AO108: =IF($AN108="x","incl",VLOOKUP($B108,'Cost prices'!$B$6:$H$538,7,FALSE)*$AN108) -> 913 | AP108: =IF($AN108="x","incl",VLOOKUP($B108,'Cost prices'!$B$6:$H$538,7,FALSE)*$AN108) -> 913 | AQ108: =IF($AN108="x","incl",VLOOKUP($B108,'Cost prices'!$B$6:$H$538,7,FALSE)*$AN108) -> 913
B109: Hartrodt handling | D109: 1 | E109: =IF(D109="x","incl",VLOOKUP($B109,'Cost prices'!$B$6:$H$538,7,FALSE)*D109) -> 950 | F109: =IF(D109="x","incl",VLOOKUP($B109,'Cost prices'!$B$6:$H$538,7,FALSE)*D109) -> 950 | G109: 1 | H109: =IF($G109="x","incl",VLOOKUP($B109,'Cost prices'!$B$6:$H$538,7,FALSE)*$G109) -> 950 | I109: 1 | J109: =IF($I109="x","incl",VLOOKUP($B109,'Cost prices'!$B$6:$H$538,7,FALSE)*$I109) -> 950 | K109: 1 | L109: =IF(K109="x","incl",VLOOKUP($B109,'Cost prices'!$B$6:$H$538,7,FALSE)*K109) -> 950 | M109: 1 | N109: =IF($M109="x","incl",VLOOKUP($B109,'Cost prices'!$B$6:$H$538,7,FALSE)*$M109) -> 950 | O109: 1 | P109: =IF($M109="x","incl",VLOOKUP($B109,'Cost prices'!$B$6:$H$538,7,FALSE)*$M109) -> 950 | Q109: 1 | R109: =IF($Q109="x","incl",VLOOKUP($B109,'Cost prices'!$B$6:$H$538,7,FALSE)*$Q109) -> 950 | U109: 1 | V109: =IF($U109="x","incl",VLOOKUP($B109,'Cost prices'!$B$6:$H$538,7,FALSE)*$U109) -> 950 | W109: 1 | X109: =IF($W109="x","incl",VLOOKUP($B109,'Cost prices'!$B$6:$H$538,7,FALSE)*$W109) -> 950 | Y109: 1 | Z109: =IF($Y109="x","incl",VLOOKUP($B109,'Cost prices'!$B$6:$H$538,7,FALSE)*$Y109) -> 950 | AA109: 1 | AB109: =IF($AA109="x","incl",VLOOKUP($B109,'Cost prices'!$B$6:$H$538,7,FALSE)*$AA109) -> 950 | AC109: 1 | AD109: =IF($AC109="x","incl",VLOOKUP($B109,'Cost prices'!$B$6:$H$538,7,FALSE)*$AC109) -> 950 | AE109: =IF($AC109="x","incl",VLOOKUP($B109,'Cost prices'!$B$6:$H$538,7,FALSE)*$AC109) -> 950 | AF109: =IF($AC109="x","incl",VLOOKUP($B109,'Cost prices'!$B$6:$H$538,7,FALSE)*$AC109) -> 950 | AG109: 1 | AH109: =IF($AG109="x","incl",VLOOKUP($B109,'Cost prices'!$B$6:$H$538,7,FALSE)*$AG109) -> 950 | AI109: =IF($AG109="x","incl",VLOOKUP($B109,'Cost prices'!$B$6:$H$538,7,FALSE)*$AG109) -> 950 | AJ109: 1 | AK109: =IF($AJ109="x","incl",VLOOKUP($B109,'Cost prices'!$B$6:$H$538,7,FALSE)*$AJ109) -> 950 | AL109: =IF($AJ109="x","incl",VLOOKUP($B109,'Cost prices'!$B$6:$H$538,7,FALSE)*$AJ109) -> 950 | AM109: =IF($AJ109="x","incl",VLOOKUP($B109,'Cost prices'!$B$6:$H$538,7,FALSE)*$AJ109) -> 950 | AN109: 1 | AO109: =IF($AN109="x","incl",VLOOKUP($B109,'Cost prices'!$B$6:$H$538,7,FALSE)*$AN109) -> 950 | AP109: =IF($AN109="x","incl",VLOOKUP($B109,'Cost prices'!$B$6:$H$538,7,FALSE)*$AN109) -> 950 | AQ109: =IF($AN109="x","incl",VLOOKUP($B109,'Cost prices'!$B$6:$H$538,7,FALSE)*$AN109) -> 950
...

Sheet Rules
AL3: 1 | AM3: 2 | AN3: 3 | AO3: 4 | AP3: 5 | AQ3: 6 | AR3: 7 | AS3: 8 | AT3: 9 | AU3: 10 | AV3: 11 | AW3: 12 | AX3: 13 | AY3: 14 | AZ3: 15 | BA3: 16 | BB3: 17
A5: Country | B5: Negotiation | C5: Agent | D5: Country | F5: Months | H5: Selection | I5: Direct client | J5: Factor | K5: Design level | L5: Factor | M5: Competition | N5: Factor | O5: Power | P5: Overruling | Q5: Fcountry | R5: Fagent | S5: Fnegotiation | T5: Forderwhen | U5: Fcompetition | V5: Fclient | W5: Fdesignlevel | X5: Pump | Z5: Overruling | AA5: Fcountry | AB5: Fagent | AC5: Fnegotiation | AD5: Forderwhen | AE5: Fcompetition | AF5: Fclient | AG5: Fdesignlevel | AH5: Tank | AM5: Margin | AQ5: Hours | AV5: Quality Control
A6: Afghanistan | B6: 0.05 | C6: 0.1 | D6: 0.02 | F6: 2025 | G6: 0.01 | H6: Yes | I6: Any w. Agent | J6: 0.02 | K6: Standard | L6: 0 | M6: Standard | N6: 0 | O6: 11 kW | P6: None | Z6: None | AM6: DK | AN6: SG | AO6: VN | AP6: Eng | AQ6: D&E | AR6: Eng | AS6: Manual | AT6: Project M | AU6: Total | AV6: Hoang Lam FAT - Chinh | AW6: Hoang Lam FAT short - Kannan | AX6: Hoang Lam FAT - Kannan | AY6: Hoang Lam FAT - PM | AZ6: Hoang Lam FAT - HL staff | BA6: U3S FAT - DK | BB6: Training materials
A7: Albania | B7: 0.05 | C7: 0.1 | D7: 0.02 | F7: 2026 | G7: 0.05 | H7: No | I7: Agent | J7: 0.02 | K7: Advanced | L7: 0.05 | M7: Advanced | N7: 0.075 | O7: 15 kW | P7: Walk away | Q7: 0.001 | R7: 0 | S7: 0 | T7: 0 | U7: 0 | V7: 0 | W7: 0 | X7: =SUM(Q7:W7) -> 0.001 | Z7: Walk away | AA7: 0.001 | AB7: 0 | AC7: 0 | AD7: 0 | AE7: 0 | AF7: 0 | AG7: 0 | AH7: =SUM(AA7:AG7) -> 0.001 | AL7: Shear | AM7: 0.15 | AN7: 0.15 | AO7: 0.15 | AP7: 0.15 | AQ7: 4 | AR7: 4 | AS7: 4 | AT7: 12 | AU7: =SUM(AQ7:AT7) -> 24 | AV7: 0 | AW7: 0 | AX7: 0 | AY7: 0 | AZ7: 0 | BA7: 1 | BB7: 0
A8: Algeria | B8: 0.05 | C8: 0.1 | D8: 0.02 | I8: End client w/o Agent | J8: 0.075 | O8: 18.5 kW | P8: -- Tier 1 -- | Z8: -- Tier 1 -- | AL8: Shear L | AM8: 0.15 | AN8: 0.15 | AO8: 0.15 | AP8: 0.15 | AQ8: 4 | AR8: 4 | AS8: 4 | AT8: 12 | AU8: =SUM(AQ8:AT8) -> 24 | AV8: 0 | AW8: 0 | AX8: 0 | AY8: 0 | AZ8: 0 | BA8: 1 | BB8: 0
A9: Andorra | B9: 0.05 | C9: 0.1 | D9: 0.02 | I9: Engineering Corp w/o Agent | J9: 0.05 | O9: 22 kW | P9: Kesmo | Q9: 0.01 | R9: 0 | S9: 0.02 | T9: 0.02 | U9: 0 | V9: 0 | W9: 0 | X9: =SUM(Q9:W9) -> 0.05 | Z9: Kesmo | AA9: 0.01 | AB9: 0 | AC9: 0.02 | AD9: 0.02 | AE9: 0.05 | AF9: 0 | AG9: 0 | AH9: =SUM(AA9:AG9) -> 0.1 | AL9: Injector | AM9: 0.15 | AN9: 0.18 | AO9: 0.18 | AP9: 0.18 | AQ9: 4 | AR9: 4 | AS9: 4 | AT9: 12 | AU9: =SUM(AQ9:AT9) -> 24 | AV9: 0 | AW9: 0 | AX9: 0 | AY9: 0 | AZ9: 0 | BA9: 1 | BB9: 0
A10: Angola | B10: 0.05 | C10: 0.1 | D10: 0.02 | I10: MNC w/o Agent | J10: 0.05 | O10: 30 kW | P10: RRPE | Q10: 0.01 | R10: 0 | S10: 0.02 | T10: 0.02 | U10: 0 | V10: 0 | W10: 0 | X10: =SUM(Q10:W10) -> 0.05 | Z10: RRPE | AA10: 0.01 | AB10: 0 | AC10: 0.02 | AD10: 0.02 | AE10: 0.05 | AF10: 0 | AG10: 0 | AH10: =SUM(AA10:AG10) -> 0.1 | AL10: Vortex | AM10: 0.2 | AN10: 0.25 | AO10: 0.25 | AP10: 0.3 | AQ10: 4 | AR10: 4 | AS10: 4 | AT10: 12 | AU10: =SUM(AQ10:AT10) -> 24 | AV10: 0 | AW10: 0 | AX10: 0 | AY10: 0 | AZ10: 0 | BA10: 1 | BB10: 0
AL11: Injector site assemble | AM11: 0.15 | AN11: 0.15 | AO11: 0.15 | AP11: 0.15 | AQ11: 4 | AR11: 4 | AS11: 4 | AT11: 12 | AU11: =SUM(AQ11:AT11) -> 24 | AV11: 0 | AW11: 0 | AX11: 0 | AY11: 0 | AZ11: 0 | BA11: 0 | BB11: 0
A12: Antigua and Barbuda | B12: 0.05 | C12: 0.1 | D12: 0.02 | O12: 45 kW | P12: CSP | Q12: 0.01 | R12: 0 | S12: 0.02 | T12: 0.02 | U12: 0 | V12: 0 | W12: 0 | X12: =SUM(Q12:W12) -> 0.05 | Z12: CSP | AA12: 0.01 | AB12: 0 | AC12: 0.02 | AD12: 0.02 | AE12: 0.05 | AF12: 0 | AG12: 0 | AH12: =SUM(AA12:AG12) -> 0.1 | AL12: Shear VN | AM12: 0.15 | AN12: 0.15 | AO12: 0.15 | AP12: 0.15 | AQ12: 4 | AR12: 4 | AS12: 4 | AT12: 12 | AU12: =SUM(AQ12:AT12) -> 24 | AV12: 0 | AW12: 1 | AX12: 0 | AY12: 0 | AZ12: 0.5 | BA12: 0 | BB12: 0
A13: Argentina | B13: 0.05 | C13: 0.1 | D13: 0.02 | O13: 55 kW | P13: GDProcessDesign | Q13: 0.01 | R13: 0 | S13: 0.02 | T13: 0.02 | U13: 0 | V13: 0 | W13: 0 | X13: =SUM(Q13:W13) -> 0.05 | Z13: GDProcessDesign | AA13: 0.01 | AB13: 0 | AC13: 0.02 | AD13: 0.02 | AE13: 0.05 | AF13: 0 | AG13: 0 | AH13: =SUM(AA13:AG13) -> 0.1 | AL13: Loop VN | AM13: 0.15 | AN13: 0.15 | AO13: 0.15 | AP13: 0.15 | AQ13: 4 | AR13: 4 | AS13: 4 | AT13: 12 | AU13: =SUM(AQ13:AT13) -> 24 | AV13: 0 | AW13: 1 | AX13: 0 | AY13: 0 | AZ13: 0.5 | BA13: 0 | BB13: 0
A14: Armenia | B14: 0.05 | C14: 0.1 | D14: 0.02 | H14: Selection | O14: 75 kW | P14: PDP | Q14: 0.01 | R14: 0 | S14: 0.02 | T14: 0.02 | U14: 0 | V14: 0 | W14: 0 | X14: =SUM(Q14:W14) -> 0.05 | Z14: PDP | AA14: 0.01 | AB14: 0 | AC14: 0.02 | AD14: 0.02 | AE14: 0.05 | AF14: 0 | AG14: 0 | AH14: =SUM(AA14:AG14) -> 0.1 | AL14: Injector VN | AM14: 0.15 | AN14: 0.15 | AO14: 0.15 | AP14: 0.15 | AQ14: 4 | AR14: 4 | AS14: 4 | AT14: 12 | AU14: =SUM(AQ14:AT14) -> 24 | AV14: 0 | AW14: 1 | AX14: 0 | AY14: 0 | AZ14: 0.5 | BA14: 0 | BB14: 0
A15: Australia | B15: 0.05 | C15: 0.1 | D15: 0.02 | H15: 0 | O15: 90 kW | P15: Hyprosys | Q15: 0.01 | R15: 0 | S15: 0.02 | T15: 0.02 | U15: 0 | V15: 0 | W15: 0 | X15: =SUM(Q15:W15) -> 0.05 | Z15: Hyprosys | AA15: 0.01 | AB15: 0 | AC15: 0.02 | AD15: 0.02 | AE15: 0.05 | AF15: 0 | AG15: 0 | AH15: =SUM(AA15:AG15) -> 0.1 | AL15: Vortex VN | AM15: 0.15 | AN15: 0.15 | AO15: 0.15 | AP15: 0.15 | AQ15: 8 | AR15: 8 | AS15: 8 | AT15: 24 | AU15: =SUM(AQ15:AT15) -> 48 | AV15: 0 | AW15: 1 | AX15: 0 | AY15: 0 | AZ15: 0.5 | BA15: 0 | BB15: 0
A16: Austria | B16: 0.05 | C16: 0.1 | D16: 0.02 | H16: 1 | O16: 110 kW | P16: -- Tier 2 -- | Z16: -- Tier 2 -- | AL16: Vortex VN 800 | AM16: 0.25 | AN16: 0.25 | AO16: 0.3 | AP16: 0.3 | AQ16: 40 | AR16: 16 | AS16: 16 | AT16: 24 | AU16: =SUM(AQ16:AT16) -> 96 | AV16: 0 | AW16: 1 | AX16: 0 | AY16: 0 | AZ16: 0.5 | BA16: 0 | BB16: 0
A17: Azerbaijan | B17: 0.05 | C17: 0.1 | D17: 0.02 | H17: 2 | P17: Stig T | Q17: 0 | R17: 0.06 | S17: 0.025 | T17: 0 | U17: 0 | V17: 0 | W17: 0 | X17: =SUM(Q17:W17) -> 0.085 | Z17: Stig T | AA17: 0 | AB17: 0.1 | AC17: 0.025 | AD17: 0.01 | AE17: 0 | AF17: 0.01 | AG17: 0.01 | AH17: =SUM(AA17:AG17) -> 0.155 | AL17: Vortex Vacuum 2000 | AM17: 0.25 | AN17: 0.25 | AO17: 0.3 | AP17: 0.3 | AQ17: 80 | AR17: 40 | AS17: 40 | AT17: 80 | AU17: =SUM(AQ17:AT17) -> 240 | AV17: 0 | AW17: 0 | AX17: 1 | AY17: 1 | AZ17: 2 | BA17: 0 | BB17: 0
A18: Bahamas | B18: 0.05 | C18: 0.1 | D18: 0.02 | H18: 3 | P18: Scanimix | Q18: 0.01 | R18: 0.1 | S18: 0.025 | T18: 0.02 | U18: 0 | V18: 0 | W18: 0 | X18: =SUM(Q18:W18) -> 0.155 | Z18: Scanimix | AA18: 0.01 | AB18: 0.1 | AC18: 0.025 | AD18: 0.02 | AE18: 0.02 | AF18: 0.02 | AG18: 0.01 | AH18: =SUM(AA18:AG18) -> 0.205 | AL18: Bottom Shear | AM18: 0.3 | AN18: 0.3 | AO18: 0.3 | AP18: 0.3 | AQ18: 0 | AR18: 0 | AS18: 0 | AT18: 20 | AU18: =SUM(AQ18:AT18) -> 20 | AV18: 0 | AW18: 0 | AX18: 0 | AY18: 0 | AZ18: 0 | BA18: 0 | BB18: 0
A19: Bahrain | B19: 0.05 | C19: 0.1 | D19: 0.02 | H19: 4 | P19: mp-process | Q19: 0.01 | R19: 0.1 | S19: 0.025 | T19: 0.02 | U19: 0 | V19: 0 | W19: 0 | X19: =SUM(Q19:W19) -> 0.155 | Z19: mp-process | AA19: 0.01 | AB19: 0.1 | AC19: 0.025 | AD19: 0.02 | AE19: 0.02 | AF19: 0.02 | AG19: 0.01 | AH19: =SUM(AA19:AG19) -> 0.205 | AL19: Injector VN - TABLE ASSEMBLY | AM19: 0.15 | AN19: 0.15 | AO19: 0.15 | AP19: 0.15
A20: Bangladesh | B20: 0.05 | C20: 0.1 | D20: 0.02 | P20: Gabriel Urso | Q20: 0.01 | R20: 0.1 | S20: 0.025 | T20: 0.02 | U20: 0 | V20: 0 | W20: 0 | X20: =SUM(Q20:W20) -> 0.155 | Z20: Gabriel Urso | AA20: 0.01 | AB20: 0.1 | AC20: 0.025 | AD20: 0.02 | AE20: 0.02 | AF20: 0.02 | AG20: 0.01 | AH20: =SUM(AA20:AG20) -> 0.205 | AL20: LC 500 | AM20: 0.21 | AN20: 0.21 | AO20: 0.23 | AP20: 0.3 | AQ20: 16 | AR20: 16 | AS20: 16 | AT20: 24 | AU20: =SUM(AQ20:AT20) -> 72 | AV20: 0 | AW20: 1 | AX20: 0 | AY20: 0 | AZ20: 0.5 | BA20: 0 | BB20: 0
A21: Barbados | B21: 0.05 | C21: 0.1 | D21: 0.02 | P21: spa-alimentos | Q21: 0.01 | R21: 0.1 | S21: 0.025 | T21: 0.02 | U21: 0 | V21: 0 | W21: 0 | X21: =SUM(Q21:W21) -> 0.155 | Z21: spa-alimentos | AA21: 0.01 | AB21: 0.1 | AC21: 0.025 | AD21: 0.02 | AE21: 0.02 | AF21: 0.02 | AG21: 0.01 | AH21: =SUM(AA21:AG21) -> 0.205 | AL21: LC 1000 | AM21: 0.21 | AN21: 0.21 | AO21: 0.23 | AP21: 0.3 | AQ21: 16 | AR21: 16 | AS21: 16 | AT21: 24 | AU21: =SUM(AQ21:AT21) -> 72 | AV21: 0 | AW21: 1 | AX21: 0 | AY21: 0 | AZ21: 0.5 | BA21: 0 | BB21: 0
A22: Belarus | B22: 0.05 | C22: 0.1 | D22: 0.02 | I22: Mark-up additionals | P22: Morten Nielsen | Q22: 0.01 | R22: 0.1 | S22: 0.01 | T22: 0.02 | U22: 0 | V22: 0 | W22: 0 | X22: =SUM(Q22:W22) -> 0.14 | Z22: Morten Nielsen | AA22: 0.01 | AB22: 0.1 | AC22: 0.01 | AD22: 0.02 | AE22: 0 | AF22: 0 | AG22: 0 | AH22: =SUM(AA22:AG22) -> 0.14 | AL22: LC 3000 | AM22: 0.21 | AN22: 0.21 | AO22: 0.23 | AP22: 0.3 | AQ22: 24 | AR22: 16 | AS22: 16 | AT22: 24 | AU22: =SUM(AQ22:AT22) -> 80 | AV22: 0 | AX22: 1 | AY22: 0 | AZ22: 1 | BA22: 0 | BB22: 0
A23: Belgium | B23: 0.05 | C23: 0.1 | D23: 0.02 | I23: Minimum | J23: 0.85 | P23: Svend Erik | Q23: 0 | R23: 0.1 | S23: 0 | T23: 0 | U23: 0 | V23: 0 | W23: 0 | X23: =SUM(Q23:W23) -> 0.1 | Z23: Svend Erik | AA23: 0.01 | AB23: 0.1 | AC23: 0.025 | AD23: 0.02 | AE23: 0.01 | AF23: 0.01 | AG23: 0.01 | AH23: =SUM(AA23:AG23) -> 0.185 | AL23: Standard 500 | AM23: 0.21 | AN23: 0.21 | AO23: 0.26 | AP23: 0.3 | AQ23: 24 | AR23: 16 | AS23: 24 | AT23: 40 | AU23: =SUM(AQ23:AT23) -> 104 | AV23: 0 | AW23: 1 | AY23: 0 | AZ23: 1 | BA23: 0 | BB23: 0
A24: Belize | B24: 0.05 | C24: 0.1 | D24: 0.02 | I24: Standard | J24: 0.7 | AL24: Standard 1000 | AM24: 0.21 | AN24: 0.21 | AO24: 0.26 | AP24: 0.3 | AQ24: 24 | AR24: 16 | AS24: 24 | AT24: 40 | AU24: =SUM(AQ24:AT24) -> 104 | AV24: 0 | AW24: 1 | AY24: 0 | AZ24: 1 | BA24: 0 | BB24: 0
A25: Benin | B25: 0.05 | C25: 0.1 | D25: 0.02 | I25: Extra | J25: 0.55 | P25: -- Tier 3 -- | Z25: -- Tier 3 -- | AL25: Vacuum 500 | AM25: 0.29 | AN25: 0.26 | AO25: 0.4 | AP25: 0.3 | AQ25: 24 | AR25: 16 | AS25: 24 | AT25: 40 | AU25: =SUM(AQ25:AT25) -> 104 | AV25: 0 | AX25: 1 | AY25: 1 | AZ25: 1 | BA25: 0 | BB25: 0
A26: Bhutan | B26: 0.05 | C26: 0.1 | D26: 0.02 | I26: Extra++ | J26: 0.4 | P26: Scandinavia | Q26: 0.02 | R26: 0.05 | S26: 0.02 | T26: 0.02 | U26: 0.02 | V26: 0.03 | W26: 0 | X26: =SUM(Q26:W26) -> 0.16 | Z26: Scandinavia | AA26: 0.01 | AB26: 0.1 | AC26: 0.025 | AD26: 0.02 | AE26: 0.02 | AF26: 0.02 | AG26: 0.02 | AH26: =SUM(AA26:AG26) -> 0.215 | AL26: Vacuum 1000 | AM26: 0.29 | AN26: 0.26 | AO26: 0.4 | AP26: 0.3 | AQ26: 24 | AR26: 16 | AS26: 24 | AT26: 40 | AU26: =SUM(AQ26:AT26) -> 104 | AV26: 0 | AX26: 1 | AY26: 1 | AZ26: 1 | BA26: 0 | BB26: 0
A27: Bolivia | B27: 0.05 | C27: 0.1 | D27: 0.02 | I27: Spare parts | J27: 0.2 | P27: Middle East | Q27: 0.02 | R27: 0.05 | S27: 0.02 | T27: 0.02 | U27: 0.02 | V27: 0.03 | W27: 0 | X27: =SUM(Q27:W27) -> 0.16 | Z27: Middle East | AA27: 0.01 | AB27: 0.1 | AC27: 0.05 | AD27: 0.02 | AE27: 0.02 | AF27: 0.02 | AG27: 0.02 | AH27: =SUM(AA27:AG27) -> 0.24 | AL27: Vacuum 3000 | AM27: 0.3 | AN27: 0.3 | AO27: 0.4 | AP27: 0.3 | AQ27: 80 | AR27: 40 | AS27: 40 | AT27: 60 | AU27: =SUM(AQ27:AT27) -> 220 | AV27: 0 | AX27: 1 | AY27: 1 | AZ27: 2 | BA27: 0 | BB27: 0
A28: Bosnia and Herzegovina | B28: 0.05 | C28: 0.1 | D28: 0.02 | P28: North America | Q28: 0.02 | R28: 0.05 | S28: 0.02 | T28: 0.02 | U28: 0.02 | V28: 0.03 | W28: 0 | X28: =SUM(Q28:W28) -> 0.16 | Z28: North America | AA28: 0.01 | AB28: 0.1 | AC28: 0.025 | AD28: 0.02 | AE28: 0.05 | AF28: 0.05 | AG28: 0.02 | AH28: =SUM(AA28:AG28) -> 0.275 | AL28: Process 500 | AM28: 0.26 | AN28: 0.26 | AO28: 0.35 | AP28: 0.3 | AQ28: 80 | AR28: 24 | AS28: 40 | AT28: 80 | AU28: =SUM(AQ28:AT28) -> 224 | AV28: 0 | AX28: 1 | AY28: 1 | AZ28: 2 | BA28: 0 | BB28: 0
A29: Botswana | B29: 0.05 | C29: 0.1 | D29: 0.02 | P29: Africa | Q29: 0.02 | R29: 0.05 | S29: 0.02 | T29: 0.02 | U29: 0.02 | V29: 0.03 | W29: 0 | X29: =SUM(Q29:W29) -> 0.16 | Z29: Africa | AA29: 0.01 | AB29: 0.1 | AC29: 0.025 | AD29: 0.02 | AE29: 0.02 | AF29: 0.02 | AG29: 0.02 | AH29: =SUM(AA29:AG29) -> 0.215 | AL29: Process 1000 | AM29: 0.3 | AN29: 0.26 | AO29: 0.35 | AP29: 0.3 | AQ29: 80 | AR29: 24 | AS29: 40 | AT29: 80 | AU29: =SUM(AQ29:AT29) -> 224 | AV29: 0 | AX29: 1 | AY29: 1 | AZ29: 2 | BA29: 0 | BB29: 0
A30: Brazil | B30: 0.05 | C30: 0.1 | D30: 0.02 | I30: Contingency | J30: 0.05 | P30: Germany | Q30: 0.02 | R30: 0.05 | S30: 0.02 | T30: 0.02 | U30: 0.02 | V30: 0.03 | W30: 0 | X30: =SUM(Q30:W30) -> 0.16 | Z30: Germany | AA30: 0.01 | AB30: 0.1 | AC30: 0.025 | AD30: 0.02 | AE30: 0.02 | AF30: 0.02 | AG30: 0.02 | AH30: =SUM(AA30:AG30) -> 0.215 | AL30: Process 3000 | AM30: 0.26 | AN30: 0.26 | AO30: 0.35 | AP30: 0.3 | AQ30: 160 | AR30: 40 | AS30: 40 | AT30: 80 | AU30: =SUM(AQ30:AT30) -> 320 | AV30: 0 | AX30: 1 | AY30: 1 | AZ30: 2 | BA30: 0 | BB30: 0
A31: Brunei | B31: 0.05 | C31: 0.1 | D31: 0.02 | I31: Cost savings markup | J31: 0.05 | AL31: EU Documentation | AQ31: 0 | AR31: 0 | AS31: 40 | AT31: 0 | AU31: =SUM(AQ31:AT31) -> 40 | AV31: 0 | AX31: 0 | AY31: 0 | AZ31: 0 | BA31: 0 | BB31: 0
A32: Bulgaria | B32: 0.05 | C32: 0.1 | D32: 0.02 | I32: Financial cost markup | J32: 0.01 | P32: -- Tier 4 -- | Z32: -- Tier 4 -- | AL32: Coxial | AM32: 0.25 | AN32: 0.25 | AO32: 0.35 | AP32: 0.3 | AQ32: 40 | AR32: 20 | AS32: 16 | AT32: 16 | AU32: =SUM(AQ32:AT32) -> 92 | AV32: 0 | AX32: 0.5 | AY32: 0.5 | AZ32: 0.5 | BA32: 0 | BB32: 0
A33: Burkina Faso | B33: 0.05 | C33: 0.1 | D33: 0.02 | I33: Warranty cost | J33: 0.02 | P33: JBT | Q33: 0.01 | R33: 0 | S33: 0.02 | T33: 0.02 | U33: 0.02 | V33: 0.02 | W33: 0 | X33: =SUM(Q33:W33) -> 0.09 | Z33: JBT | AA33: 0.01 | AB33: 0 | AC33: 0.03 | AD33: 0.02 | AE33: 0.02 | AF33: 0.02 | AG33: 0.02 | AH33: =SUM(AA33:AG33) -> 0.12 | AL33: Steam Injection nozzles | AM33: As mixer | AQ33: 40 | AR33: 5 | AS33: 5 | AT33: 5 | AU33: =SUM(AQ33:AT33) -> 55 | AV33: 0 | AX33: 0 | AY33: 0 | AZ33: 0 | BA33: 0 | BB33: 0
A34: Burundi | B34: 0.05 | C34: 0.1 | D34: 0.02 | P34: Krones | Q34: 0.01 | R34: 0 | S34: 0.01 | T34: 0.01 | U34: 0.01 | V34: 0.01 | W34: 0 | X34: =SUM(Q34:W34) -> 0.05 | Z34: Krones | AA34: 0.01 | AB34: 0 | AC34: 0.01 | AD34: 0.01 | AE34: 0.01 | AF34: 0.01 | AG34: 0.02 | AH34: =SUM(AA34:AG34) -> 0.07 | AL34: Culinary steam unit | AQ34: 40 | AR34: 5 | AS34: 5 | AT34: 5 | AU34: =SUM(AQ34:AT34) -> 55 | AX34: 0.25 | AY34: 0.25 | AZ34: 0.25 | BA34: 0 | BB34: 0
A35: Cabo Verde | B35: 0.05 | C35: 0.1 | D35: 0.02 | I35: Vacuum pummp | J35: No | P35: Dterm | Q35: 0.01 | R35: 0 | S35: 0.02 | T35: 0.02 | U35: 0.02 | V35: 0.02 | W35: 0 | X35: =SUM(Q35:W35) -> 0.09 | Z35: Dterm | AA35: 0.01 | AB35: 0 | AC35: 0.03 | AD35: 0.02 | AE35: 0.02 | AF35: 0.02 | AG35: 0.02 | AH35: =SUM(AA35:AG35) -> 0.12 | AL35: Control Panel & VSD, 11 kW | AM35: 0.15 | AN35: 0.15 | AO35: 0.15 | AP35: 0.3 | AQ35: 1 | AR35: 1 | AS35: 2 | AT35: 2 | AU35: =SUM(AQ35:AT35) -> 6 | AV35: 0 | AX35: 0 | AY35: 0 | AZ35: 0 | BA35: 0 | BB35: 0
A36: Cambodia | B36: 0.05 | C36: 0.1 | D36: 0.02 | I36: Mild steel 2.2 kW | J36: 2.2 MS | P36: Ecodata Engineering Enterprise | Q36: 0.01 | R36: 0 | S36: 0.02 | T36: 0.02 | U36: 0.02 | V36: 0.02 | W36: 0 | X36: =SUM(Q36:W36) -> 0.09 | Z36: Ecodata Engineering Enterprise | AA36: 0.01 | AB36: 0 | AC36: 0.03 | AD36: 0.02 | AE36: 0.02 | AF36: 0.02 | AG36: 0.02 | AH36: =SUM(AA36:AG36) -> 0.12 | AI36: Friend with Raymond BOS Homogenisers | AL36: Control Panel & VSD, 15 kW | AM36: 0.15 | AN36: 0.15 | AO36: 0.15 | AP36: 0.3 | AQ36: 1 | AR36: 1 | AS36: 2 | AT36: 2 | AU36: =SUM(AQ36:AT36) -> 6 | AV36: 0 | AX36: 0 | AY36: 0 | AZ36: 0 | BA36: 0 | BB36: 0
I37: Mild steel 3.0 kW | J37: 3.0 MS | P37: Ener Tech Solutions S/B | Q37: 0.01 | R37: 0 | S37: 0.02 | T37: 0.02 | U37: 0.02 | V37: 0.02 | W37: 0 | X37: =SUM(Q37:W37) -> 0.09 | Z37: Ener Tech Solutions S/B | AA37: 0.01 | AB37: 0 | AC37: 0.03 | AD37: 0.02 | AE37: 0.02 | AF37: 0.02 | AG37: 0.02 | AH37: =SUM(AA37:AG37) -> 0.12 | AI37: Friends with JBT Michael Yong | AL37: Control Panel & VSD, 18.5 kW | AM37: 0.15 | AN37: 0.15 | AO37: 0.15 | AP37: 0.3 | AQ37: 1 | AR37: 1 | AS37: 2 | AT37: 2 | AU37: =SUM(AQ37:AT37) -> 6 | AV37: 0 | AX37: 0 | AY37: 0 | AZ37: 0 | BA37: 0 | BB37: 0
A38: Cameroon | B38: 0.05 | C38: 0.1 | D38: 0.02 | I38: Mild steel 4.0 kW | J38: 4.0 MS | P38: Taiwan Benefit Company | Q38: 0.01 | R38: 0 | S38: 0.02 | T38: 0.02 | U38: 0.02 | V38: 0.02 | W38: 0 | X38: =SUM(Q38:W38) -> 0.09 | Z38: Taiwan Benefit Company | AA38: 0.01 | AB38: 0 | AC38: 0.03 | AD38: 0.02 | AE38: 0.02 | AF38: 0.02 | AG38: 0.02 | AH38: =SUM(AA38:AG38) -> 0.12 | AI38: Friends with JBT Michael Yong | AL38: Control Panel & VSD, 22 kW | AM38: 0.15 | AN38: 0.15 | AO38: 0.15 | AP38: 0.3 | AQ38: 1 | AR38: 1 | AS38: 2 | AT38: 2 | AU38: =SUM(AQ38:AT38) -> 6 | AV38: 0 | AX38: 0 | AY38: 0 | AZ38: 0 | BA38: 0 | BB38: 0
A39: Canada | B39: 0.05 | C39: 0.1 | D39: 0.02 | I39: Mild steel 5.5 kW | J39: 5.5 MS | P39: 3xmtechnology | Q39: 0.01 | R39: 0 | S39: 0.02 | T39: 0.02 | U39: 0.02 | V39: 0.02 | W39: 0 | X39: =SUM(Q39:W39) -> 0.09 | Z39: 3xmtechnology | AA39: 0.01 | AB39: 0 | AC39: 0.03 | AD39: 0.02 | AE39: 0.02 | AF39: 0.02 | AG39: 0.02 | AH39: =SUM(AA39:AG39) -> 0.12 | AL39: Control Panel & VSD, 30 kW | AM39: 0.15 | AN39: 0.15 | AO39: 0.15 | AP39: 0.3 | AQ39: 1 | AR39: 1 | AS39: 2 | AT39: 2 | AU39: =SUM(AQ39:AT39) -> 6 | AV39: 0 | AX39: 0 | AY39: 0 | AZ39: 0 | BA39: 0 | BB39: 0
A40: Central African Republic | B40: 0.05 | C40: 0.1 | D40: 0.02 | I40: Mild steel 7.5 kW | J40: 7.5 MS | P40: KannanFoodTech | Q40: 0.01 | R40: 0.05 | S40: 0.02 | T40: 0.02 | U40: 0 | V40: 0 | W40: 0 | X40: =SUM(Q40:W40) -> 0.1 | Z40: KannanFoodTech | AA40: 0.01 | AB40: 0.05 | AC40: 0.02 | AD40: 0 | AE40: 0.02 | AF40: 0.02 | AG40: 0.02 | AH40: =SUM(AA40:AG40) -> 0.14 | AL40: Frequency Converter 11 kW | AM40: 0.15 | AN40: 0.15 | AO40: 0.15 | AP40: 0.3 | AQ40: 1 | AR40: 1 | AS40: 2 | AT40: 2 | AU40: =SUM(AQ40:AT40) -> 6 | AV40: 0 | AX40: 0 | AY40: 0 | AZ40: 0 | BA40: 0 | BB40: 0
A41: Chad | B41: 0.05 | C41: 0.1 | D41: 0.02 | P41: Nikos | Q41: 0.01 | R41: 0 | S41: 0.02 | T41: 0.02 | U41: 0 | V41: 0 | W41: 0 | X41: =SUM(Q41:W41) -> 0.05 | Z41: Nikos | AA41: 0.01 | AB41: 0.05 | AC41: 0.02 | AD41: 0 | AE41: 0.02 | AF41: 0.02 | AG41: 0.02 | AH41: =SUM(AA41:AG41) -> 0.14 | AK41: MIAC, Complete | AL41: Frequency Converter 15 kW | AM41: 0.15 | AN41: 0.15 | AO41: 0.15 | AP41: 0.3 | AQ41: 1 | AR41: 1 | AS41: 2 | AT41: 2 | AU41: =SUM(AQ41:AT41) -> 6 | AV41: 0 | AX41: 0 | AY41: 0 | AZ41: 0 | BA41: 0 | BB41: 0
A42: Chile | B42: 0.05 | C42: 0.1 | D42: 0.02 | I42: Stainless steel 2.2 kW | J42: 2.2 SS | P42: Stanfford Eng | Q42: 0.01 | R42: 0.05 | S42: 0.02 | T42: 0.02 | U42: 0 | V42: 0 | W42: 0 | X42: =SUM(Q42:W42) -> 0.1 | Z42: Stanfford Eng | AA42: 0.01 | AB42: 0.05 | AC42: 0.02 | AD42: 0 | AE42: 0.02 | AF42: 0.02 | AG42: 0.02 | AH42: =SUM(AA42:AG42) -> 0.14 | AL42: Frequency Converter 18.5 kW | AM42: 0.15 | AN42: 0.15 | AO42: 0.15 | AP42: 0.3 | AQ42: 1 | AR42: 1 | AS42: 2 | AT42: 2 | AU42: =SUM(AQ42:AT42) -> 6 | AV42: 0 | AX42: 0 | AY42: 0 | AZ42: 0 | BA42: 0 | BB42: 0
A43: China | B43: 0.05 | C43: 0.1 | D43: 0.02 | I43: Stainless steel 3.0 kW | J43: 3.0 SS | P43: OME Michael Cai | Q43: 0.01 | R43: 0.01 | S43: 0.01 | T43: 0.01 | U43: 0 | V43: 0 | W43: 0 | X43: =SUM(Q43:W43) -> 0.04 | Z43: OME Michael Cai | AA43: 0.01 | AB43: 0.05 | AC43: 0.02 | AD43: 0 | AE43: 0.02 | AF43: 0.02 | AG43: 0.02 | AH43: =SUM(AA43:AG43) -> 0.14 | AL43: Frequency Converter 22 kW | AM43: 0.15 | AN43: 0.15 | AO43: 0.15 | AP43: 0.3 | AQ43: 1 | AR43: 1 | AS43: 2 | AT43: 2 | AU43: =SUM(AQ43:AT43) -> 6 | AV43: 0 | AX43: 0 | AY43: 0 | AZ43: 0 | BA43: 0 | BB43: 0
A44: Colombia | B44: 0.05 | C44: 0.1 | D44: 0.02 | I44: Stainless steel 4.0 kW | J44: 4.0 SS | P44: Gemak | Q44: 0.01 | R44: 0 | S44: 0.02 | T44: 0.02 | U44: 0.02 | V44: 0.02 | W44: 0 | X44: =SUM(Q44:W44) -> 0.09 | Z44: Gemak | AA44: 0.01 | AB44: 0.05 | AC44: 0.02 | AD44: 0 | AE44: 0.02 | AF44: 0.02 | AG44: 0.02 | AH44: =SUM(AA44:AG44) -> 0.14 | AL44: MixSing Standard control 22 kW | AM44: 0.15 | AN44: 0.15 | AO44: 0.15 | AP44: 0.3 | AQ44: 1 | AR44: 1 | AS44: 2 | AT44: 2 | AU44: =SUM(AQ44:AT44) -> 6 | AV44: 0 | AX44: 0 | AY44: 0 | AZ44: 0 | BA44: 0 | BB44: 0
A45: Comoros | B45: 0.05 | C45: 0.1 | D45: 0.02 | I45: Stainless steel 5.5 kW | J45: 5.5 SS | P45: Essiential Engineering SG | Q45: 0.01 | R45: 0 | S45: 0.02 | T45: 0.02 | U45: 0.02 | V45: 0.02 | W45: 0 | X45: =SUM(Q45:W45) -> 0.09 | Z45: Essiential Engineering SG | AA45: 0.01 | AB45: 0.05 | AC45: 0.02 | AD45: 0 | AE45: 0.02 | AF45: 0.02 | AG45: 0.02 | AH45: =SUM(AA45:AG45) -> 0.14
A46: Congo, Democratic Republic of the | B46: 0.05 | C46: 0.1 | D46: 0.02 | I46: Stainless steel 7.5 kW | J46: 7.5 SS | P46: No-name engineering company | Q46: 0.01 | R46: 0.05 | S46: 0.02 | T46: 0.02 | U46: 0 | V46: 0 | W46: 0 | X46: =SUM(Q46:W46) -> 0.1 | Z46: No-name engineering company | AA46: 0.01 | AB46: 0.05 | AC46: 0.02 | AD46: 0 | AE46: 0.02 | AF46: 0.02 | AG46: 0.02 | AH46: =SUM(AA46:AG46) -> 0.14 | AL46: MixSing Vacuum control 22 kW | AM46: 0.15 | AN46: 0.15 | AO46: 0.15 | AP46: 0.3 | AQ46: 8 | AR46: 8 | AS46: 16 | AT46: 16 | AU46: =SUM(AQ46:AT46) -> 48 | AV46: 0 | AX46: 0 | AY46: 0 | AZ46: 0 | BA46: 0 | BB46: 0
A47: Congo, Republic of the | B47: 0.05 | C47: 0.1 | D47: 0.02 | AL47: MixSing Process control 22 kW | AM47: 0.15 | AN47: 0.15 | AO47: 0.15 | AP47: 0.3 | AQ47: 1 | AR47: 1 | AS47: 2 | AT47: 2 | AU47: =SUM(AQ47:AT47) -> 6 | AV47: 0 | AX47: 0 | AY47: 0 | AZ47: 0 | BA47: 0 | BB47: 0
A48: Costa Rica | B48: 0.05 | C48: 0.1 | D48: 0.02 | I48: FOOT BRAND | P48: -- Tier 5 -- | Z48: -- Tier 5 -- | AL48: Table | AM48: 0.15 | AN48: 0.15 | AO48: 0.2 | AP48: 0.3 | AQ48: 0.5 | AR48: 0.25 | AS48: 0.25 | AT48: 1 | AU48: =SUM(AQ48:AT48) -> 2 | AV48: 0 | AX48: 0 | AY48: 0 | AZ48: 0 | BA48: 0 | BB48: 0
A49: Croatia | B49: 0.05 | C49: 0.1 | D49: 0.02 | I49: MARTIN | P49: Nestle | Q49: 0.01 | R49: 0 | S49: 0.03 | T49: 0.02 | U49: 0.02 | V49: 0.02 | W49: 0.02 | X49: =SUM(Q49:W49) -> 0.12 | Z49: Nestle | AA49: 0.01 | AB49: 0 | AC49: 0.03 | AD49: 0.02 | AE49: 0.05 | AF49: 0.08 | AG49: 0.03 | AH49: =SUM(AA49:AG49) -> 0.22 | AL49: Table VN | AM49: 0.3 | AN49: 0.3 | AO49: 0.3 | AP49: 0.3 | AQ49: 0.5 | AR49: 0.25 | AS49: 0.25 | AT49: 1 | AU49: =SUM(AQ49:AT49) -> 2 | AV49: 0 | AX49: 0 | AY49: 0 | AZ49: 0 | BA49: 0 | BB49: 0
A50: Cuba | B50: 0.05 | C50: 0.1 | D50: 0.02 | I50: MARTIN 3A | P50: Lactalis | Q50: 0.01 | R50: 0 | S50: 0.03 | T50: 0.02 | U50: 0.02 | V50: 0.02 | W50: 0.02 | X50: =SUM(Q50:W50) -> 0.12 | Z50: Lactalis | AA50: 0.01 | AB50: 0 | AC50: 0.03 | AD50: 0.02 | AE50: 0.05 | AF50: 0.03 | AG50: 0.03 | AH50: =SUM(AA50:AG50) -> 0.17 | AL50: Mesh | AM50: 0.15 | AN50: 0.15 | AO50: 0.15 | AP50: 0.3 | AQ50: 0.5 | AR50: 0.25 | AS50: 0.25 | AT50: 1 | AU50: =SUM(AQ50:AT50) -> 2 | AV50: 0 | AX50: 0 | AY50: 0 | AZ50: 0 | BA50: 0 | BB50: 0
A51: Cyprus | B51: 0.05 | C51: 0.1 | D51: 0.02 | I51: NGI | P51: AAK | Q51: 0.01 | R51: 0 | S51: 0.03 | T51: 0.02 | U51: 0.02 | V51: 0.02 | W51: 0.02 | X51: =SUM(Q51:W51) -> 0.12 | Z51: AAK | AA51: 0.01 | AB51: 0 | AC51: 0.03 | AD51: 0.02 | AE51: 0.05 | AF51: 0.08 | AG51: 0.03 | AH51: =SUM(AA51:AG51) -> 0.22 | AL51: Seal flush | AM51: 0.15 | AN51: 0.15 | AO51: 0.15 | AP51: 0.3 | AQ51: 0.5 | AR51: 0.25 | AS51: 0.25 | AT51: 1 | AU51: =SUM(AQ51:AT51) -> 2 | AV51: 0 | AX51: 0 | AY51: 0 | AZ51: 0 | BA51: 0 | BB51: 0
A52: Czech Republic (Czechia) | B52: 0.05 | C52: 0.1 | D52: 0.02 | AL52: Connection to Client | AM52: 0.15 | AN52: 0.15 | AO52: 0.15 | AP52: 0.3 | AQ52: 0.5 | AR52: 0.25 | AS52: 0.25 | AT52: 0.25 | AU52: =SUM(AQ52:AT52) -> 1.25 | AV52: 0 | AX52: 0 | AY52: 0 | AZ52: 0 | BA52: 0 | BB52: 0
A53: Denmark | B53: 0.05 | C53: 0.1 | D53: 0.02 | I53: SITE GLASS | P53: -- Tier 6 -- | Z53: -- Tier 6 -- | AL53: Packaging | AM53: 0.15 | AN53: 0.15 | AO53: 0.15 | AP53: 0.3 | AQ53: 0.5 | AR53: 0.25 | AS53: 0.25 | AT53: 1 | AU53: =SUM(AQ53:AT53) -> 2 | AV53: 0 | AX53: 0 | AY53: 0 | AZ53: 0 | BA53: 0 | BB53: 0
A54: Djibouti | B54: 0.05 | C54: 0.1 | D54: 0.02 | I54: NONE | P54: Competition | Q54: 0.02 | R54: 0.05 | S54: 0.03 | T54: 0.05 | U54: 0.05 | V54: 0.05 | W54: 0.05 | X54: =SUM(Q54:W54) -> 0.3 | Z54: Competition | AA54: 0.02 | AB54: 0.05 | AC54: 0.03 | AD54: 0.05 | AE54: 0.05 | AF54: 0.05 | AG54: 0.05 | AH54: =SUM(AA54:AG54) -> 0.3 | AL54: Suction lance | AM54: 0.15 | AN54: 0.15 | AO54: 0.15 | AP54: 0.3 | AQ54: 8 | AR54: 8 | AS54: 8 | AT54: 24 | AU54: =SUM(AQ54:AT54) -> 48 | AV54: 0 | AX54: 0 | AY54: 0 | AZ54: 0 | BA54: 0 | BB54: 0
A55: Dominica | B55: 0.05 | C55: 0.1 | D55: 0.02 | I55: NO NAME CN | P55: Budget (Unknown) | Q55: 0.02 | R55: 0.1 | S55: 0.03 | T55: 0.05 | U55: 0.05 | V55: 0.075 | W55: 0.05 | X55: =SUM(Q55:W55) -> 0.375 | Z55: Budget (Unknown) | AA55: 0.02 | AB55: 0.1 | AC55: 0.05 | AD55: 0.05 | AE55: 0.05 | AF55: 0.075 | AG55: 0.05 | AH55: =SUM(AA55:AG55) -> 0.395
A56: Dominican Republic | B56: 0.05 | C56: 0.1 | D56: 0.02 | I56: EBORA EU | P56: Exhibition | Q56: 0.01 | R56: 0.05 | S56: 0.01 | T56: 0.01 | U56: 0.01 | V56: 0.01 | W56: 0.01 | X56: =SUM(Q56:W56) -> 0.11 | Z56: Exhibition | AA56: 0.01 | AB56: 0.1 | AC56: 0.025 | AD56: 0.02 | AE56: 0.01 | AF56: 0.01 | AG56: 0.01 | AH56: =SUM(AA56:AG56) -> 0.185
A57: East Timor (Timor-Leste) | B57: 0.05 | C57: 0.1 | D57: 0.02
A58: Ecuador | B58: 0.05 | C58: 0.1 | D58: 0.02
A59: Egypt | B59: 0.05 | C59: 0.1 | D59: 0.02
A60: El Salvador | B60: 0.05 | C60: 0.1 | D60: 0.02
A61: Equatorial Guinea | B61: 0.05 | C61: 0.1 | D61: 0.02
A62: Eritrea | B62: 0.05 | C62: 0.1 | D62: 0.02
A63: Estonia | B63: 0.05 | C63: 0.1 | D63: 0.02
A64: Eswatini (Swaziland) | B64: 0.05 | C64: 0.1 | D64: 0.02
A65: Ethiopia | B65: 0.05 | C65: 0.1 | D65: 0.02
A66: Fiji | B66: 0.05 | C66: 0.1 | D66: 0.02
A67: Finland | B67: 0.05 | C67: 0.1 | D67: 0.02
A68: France | B68: 0.05 | C68: 0.1 | D68: 0.02
... A201: Zimbabwe | B201: 0.05 | C201: 0.1 | D201: 0.02

Sheet Cost prices
A2: Exchange rate DKK to USD | B2: 7.17
A3: Exchange rate DKK to EUR | B3: 7.46
A4: Exchange rate DKK to SGD | B4: 5.34
D5: Equipment | E5: Polish / Tax | F5: Fees | G5: Freight | H5: Total DKK
A6: TPS essiential package | B6: xx Mixer, diameter 160mm | D6: DKK | E6: DKK | G6: DKK | H6: DKK
B7: Motor consol | D7: 4441 | G7: 640 | H7: =SUM(D7:G7) -> 5081 | I7: Updated Nov 2024
B8: Stator | D8: 4080 | G8: 640 | H8: =SUM(D8:G8) -> 4720 | I8: Updated Nov 2024
B9: Impeller | D9: 1180 | E9: 2487 | G9: 640 | H9: =SUM(D9:G9) -> 4307 | I9: Updated Nov 2024
B10: Pump house | D10: 3346 | E10: 4605 | G10: 640 | H10: =SUM(D10:G10) -> 8591 | I10: Updated Nov 2024
B11: Bottom | D11: 5200 | G11: 640 | H11: =SUM(D11:G11) -> 5840
B12: Shaft seal | D12: 990 | G12: 15 | H12: =SUM(D12:G12) -> 1005
B13: Shaft | D13: Incl Seneberg | H13: Incl Seneberg
B14: Dan Seneberg, Pump house fabrication | D14: =665.9*7.45 -> 4960.955 | H14: =SUM(D14:G14) -> 4960.955 | I14: Used the lower 5 pcs price from john 15october 2025 email
B15: Dan Seneberg, assemble and test | D15: =1103.86*7.45 -> 8223.757 | H15: =SUM(D15:G15) -> 8223.757 | I15: Used the lower 1 pcs price from john 15 october 2025 email
B16: Dan Seneberg workshop, 35 holes | D16: =1948.87*7.45 -> 14519.082 | H16: =SUM(D16:G16) -> 14519.082 | I16: Used the lower 10 pcs price from john 15 october 2025 email
B17: Dan Seneberg workshop, 105 holes | D17: =2148.87*7.45 -> 16009.082 | H17: =SUM(D17:G17) -> 16009.082 | I17: Used the lower 10 pcs price from john 15 october 2025 email
A19: RS components
A20: 4992694 | B20: *Y-strainer | D20: =423.67 -> 423.67 | G20: 50 | H20: =SUM(D20:G20) -> 473.67 | I20: 4992694 RS PRO Y-trækaflastning 1/4" BSP Rustfrit stål
A21: 8298987 | B21: *fan | D21: 491.88 | G21: 50 | H21: =SUM(D21:G21) -> 541.88 | I21: 8298987 Sanyo Denki Aksial blæser, 119 x 119 x 38mm, 168.3m³/h, Kugleleje, 5.28W, 24 V dc, San Ace 9WP
A22: Bürkert
A23: 295767 | B23: *2/2-waY-solenoId valve, servo assisted 6213-EV-A10,0AAVAGM82-6-024/DC-10 *NA38 | C23: =261 -> 261 | D23: =C23*$B$4 -> 1393.74 | F23: =82.27*$B$4/2 -> 219.6609 | G23: =88*$B$4 -> 469.92 | H23: =SUM(D23:G23) -> 2083.3209
A24: 314802 | B24: *Kabelstik 2518 28mm Form A UL approva 2518-A-BCS/UC-00-3-N50-00-0-00000 JLO4 | C24: 8.61 | D24: =C24*$B$4 -> 45.9774 | F24: =27.17*$B$4/2 -> 72.5439 | H24: =SUM(D24:G24) -> 118.5213 | I24: valve connector typ A 2518-A-BCS/UC-00-3-N50-00-0-00000 *JL04
A25: Armatech (DVC)
A26: E0226372553 | B26: Needel valve | D26: 229 | F26: 95 | G26: 269 | H26: =SUM(D26:G26) -> 593 | I26: E0226372553 1/4" PN420 Nåleventil Fig. 3710/Fig. 226 Materialer: Rustfrit stål 1.4401 Tilslut./Betjening: BSPP Gevind/Håndhjul
A27: 1101000016 | B27: 1/2" - PN68 kuglehane | D27: 141 | F27: 50 | G27: 100 | H27: =SUM(D27:G27) -> 291 | I27: 1/2" - PN68 kuglehane type 1101 m/lås CF8M/PTFE/fuld bore/BSPP gevind/håndtag
A28: 1351510050 | B28: Ball Valve (full bore) | D28: 1794 | F28: 95 | G28: 100 | H28: =SUM(D28:G28) -> 1989 | I28: 1351510050 DN50 - PN100 3-delt kuglehane 1351FB Materialer: CF8M/AISI316/PTFE +KF
A29: Hoyer
B30: 11 kW | D30: =6804+580 -> 7384 | F30: 562.95 | G30: =757.97+540+57 -> 1354.97 | H30: =SUM(D30:G30) -> 9301.92 | J30: Added DKK 580 for improved bearing, email from Frederik 19 Feb 2025
B31: 15 kW | D31: =7103+580 -> 7683 | F31: 562.95 | G31: =757.97+540+57 -> 1354.97 | H31: =SUM(D31:G31) -> 9600.92 | J31: Added DKK 580 for improved bearing, email from Frederik 19 Feb 2026
B32: 18.5 kW | D32: =7605+580 -> 8185 | F32: 562.95 | G32: =757.97+540+57 -> 1354.97 | H32: =SUM(D32:G32) -> 10102.92 | J32: Added DKK 580 for improved bearing, email from Frederik 19 Feb 2027
B33: 22 kW | D33: =10052.6 -> 10052.6 | F33: 563 | G33: =757.97+540+57 -> 1354.97 | H33: =SUM(D33:G33) -> 11970.57 | I33: 45809 | J33: 3102160-22.0-040201-M-058484
B34: 30 kW | D34: =16066 -> 16066 | F34: 562.95 | G34: =757.97+540+57 -> 1354.97 | H34: =SUM(D34:G34) -> 17983.92 | I34: 45809 | J34: 3102180-30.0-040201-M-063186
B35: 45 kW | D35: =12000+580 -> 12580 | F35: 562.95 | G35: =757.97+540+57 -> 1354.97 | H35: =SUM(D35:G35) -> 14497.92 | I35: Old 2022 pricing | J35: Added DKK 580 for improved bearing, email from Frederik 19 Feb 2030
B36: 55 kW | D36: =14000+580 -> 14580 | F36: 562.95 | G36: =757.97+540+57 -> 1354.97 | H36: =SUM(D36:G36) -> 16497.92 | I36: Old 2022 pricing | J36: Added DKK 580 for improved bearing, email from Frederik 19 Feb 2031
B37: 75 kW | D37: =21000+580 -> 21580 | F37: 562.95 | G37: =757.97+540+57 -> 1354.97 | H37: =SUM(D37:G37) -> 23497.92 | I37: Old 2022 pricing | J37: Added DKK 580 for improved bearing, email from Frederik 19 Feb 2032
B38: 90 kW | D38: =23000+580 -> 23580 | F38: 562.95 | G38: =757.97+540+57 -> 1354.97 | H38: =SUM(D38:G38) -> 25497.92 | I38: Old 2022 pricing | J38: Added DKK 580 for improved bearing, email from Frederik 19 Feb 2033
B39: 110 kW | D39: =36000+580 -> 36580 | F39: 562.95 | G39: =757.97+540+57 -> 1354.97 | H39: =SUM(D39:G39) -> 38497.92 | I39: Old 2022 pricing | J39: Added DKK 580 for improved bearing, email from Frederik 19 Feb 2034
B42: 11 kW US | D42: 10449.39 | E42: =D42/0.6-D42 -> 6966.26 | F42: 562.95 | G42: =757.97+540+57 -> 1354.97 | H42: =SUM(D42:G42) -> 19333.57
B43: 15 kW US | D43: 10910 | E43: =D43/0.6-D43 -> 7273.3333 | F43: 562.95 | G43: =757.97+540+57 -> 1354.97 | H43: =SUM(D43:G43) -> 20101.253
B44: 18.5 kW US | D44: 11525.75 | E44: =D44/0.6-D44 -> 7683.8333 | F44: 562.95 | G44: =757.97+540+57 -> 1354.97 | H44: =SUM(D44:G44) -> 21127.503
B45: 22 kW US | D45: 12494.1 | E45: =D45/0.6-D45 -> 8329.4 | F45: 562.95 | G45: =757.97+540+57 -> 1354.97 | H45: =SUM(D45:G45) -> 22741.42
B47: Control Panel & VSD, 11 kW | C47: 19665 | D47: =C47-D30 -> 12281 | F47: 233 | G47: 540 | H47: =SUM(D47:G47) -> 13054 | I47: Only extra price for the built in VSD. I deducted the motor
B48: Control Panel & VSD, 15 kW | C48: 20926 | D48: =C48-D31 -> 13243 | F48: 233 | G48: 540 | H48: =SUM(D48:G48) -> 14016 | I48: Only extra price for the built in VSD. I deducted the motor
B49: Control Panel & VSD, 18.5 kW | C49: 22390 | D49: =C49-D32 -> 14205 | F49: 233 | G49: 540 | H49: =SUM(D49:G49) -> 14978 | I49: Only extra price for the built in VSD. I deducted the motor
B50: Control Panel & VSD, 22 kW | D50: 16890 | F50: 233 | G50: 540 | H50: =SUM(D50:G50) -> 17663 | I50: Only extra price for the built in VSD. Quote 15 Oct 2025
B51: Control Panel & VSD, 30 kW | C51: 27283 | D51: =C51-D34 -> 11217 | F51: 233 | G51: 540 | H51: =SUM(D51:G51) -> 11990 | I51: Only extra price for the built in VSD. I deducted the motor
A53: Invertek | B53: Frequency Converter 11 kW | D53: 9308.25 | G53: 375 | H53: =SUM(D53:G53) -> 9683.25 | I53: Quote 34556 10 Dec 2025
B54: Frequency Converter 15 kW | D54: 11544.75 | G54: 375 | H54: =SUM(D54:G54) -> 11919.75 | I54: Quote 34556 10 Dec 2026
B55: Frequency Converter 18.5 kW | D55: 13340.25 | G55: 375 | H55: =SUM(D55:G55) -> 13715.25 | I55: Quote 34556 10 Dec 2027
B56: Frequency Converter 22 kW | D56: 15135.75 | G56: 375 | H56: =SUM(D56:G56) -> 15510.75 | I56: Quote 34556 10 Dec 2028
A58: Norland | B58: Control cabinet (DK version) | D58: 15500 | H58: =SUM(D58:G58) -> 15500
A59: HTEN | B59: Control cabinet (VN version) | C59: 1759 | D59: =C59*$B$2 -> 12612.03 | H59: =SUM(D59:G59) -> 12612.03 | I59: Incl. cables
A60: Eletrician | B60: Cables inst (part of Brian cost) | D60: 0
B61: SMS, Clamp, Flange | D61: 1000 | H61: =SUM(D61:G61) -> 1000
A63: Brian | B63: Shear | D63: =13550*1.1 -> 14905 | H63: =SUM(D63:G63) -> 14905 | I63: Feb 2025, added 10% as I have had no price update from Brian
B64: Shear L | D64: =23900*1.1 -> 26290 | H64: =SUM(D64:G64) -> 26290 | I64: Feb 2025, added 10% as I have had no price update from Brian
B65: Injector | D65: =46900*1.1 -> 51590 | H65: =SUM(D65:G65) -> 51590 | I65: Feb 2025, added 10% as I have had no price update from Brian
B66: Vortex | D66: =82100*1.1 -> 90310 | H66: =SUM(D66:G66) -> 90310 | I66: Feb 2025, added 10% as I have had no price update from Brian
B67: Mesh | D67: =4360*1.1 -> 4796 | H67: =SUM(D67:G67) -> 4796 | I67: Feb 2025, added 10% as I have had no price update from Brian
B68: Table | D68: =11940*1.1 -> 13134 | H68: =SUM(D68:G68) -> 13134 | I68: Feb 2025, added 10% as I have had no price update from Brian
B69: Control system (fitting/conection of panel) | D69: =5200*1.1 -> 5720 | H69: =SUM(D69:G69) -> 5720 | I69: Feb 2025, added 10% as I have had no price update from Brian
B70: Seal water | D70: =655*1.1 -> 720.5 | H70: =SUM(D70:G70) -> 720.5 | I70: Feb 2025, added 10% as I have had no price update from Brian
C71: Foreign currency
A72: Hoang Lam | B72: Table VN | C72: 670 | D72: =C72*$B$2 -> 4803.9 | H72: =SUM(D72:G72) -> 4803.9
B73: Vortex VN - MOTOR BASE SUPPORT ASSY | D73: =C73*$B$2 -> 0 | H73: =SUM(D73:G73) -> 0
B74: Vortex VN - PUMP COVER | D74: =C74*$B$2 -> 0 | H74: =SUM(D74:G74) -> 0
B75: Vortex VN - TANK & PIPING | C75: 3460 | D75: =C75*$B$2 -> 24808.2 | H75: =SUM(D75:G75) -> 24808.2
B76: Vortex VN - Wooden Box | C76: 150 | D76: =C76*$B$2 -> 1075.5 | H76: =SUM(D76:G76) -> 1075.5
B77: Injector VN - MOTOR BASE SUPPORT ASSY | C77: 498 | D77: =C77*$B$2 -> 3570.66 | H77: =SUM(D77:G77) -> 3570.66
B78: Injector VN - PUMP COVER | C78: 346 | D78: =C78*$B$2 -> 2480.82 | H78: =SUM(D78:G78) -> 2480.82
B79: PIPING WO - INJECTOR BODY ASSY | C79: 771 | D79: =C79*$B$2 -> 5528.07 | H79: =SUM(D79:G79) -> 5528.07
B80: Injector VN - INJECTOR BODY ASSY | C80: 369 | D80: =C80*$B$2 -> 2645.73 | H80: =SUM(D80:G80) -> 2645.73
B81: Injector VN - FUNNEL ASSEMBLY | C81: 1100 | D81: =C81*$B$2 -> 7887 | H81: =SUM(D81:G81) -> 7887
B82: Injector VN - TABLE ASSEMBLY | C82: 796 | D82: =C82*$B$2 -> 5707.32 | H82: =SUM(D82:G82) -> 5707.32
B83: Injector VN - Wooden Box | C83: 150 | D83: =C83*$B$2 -> 1075.5 | H83: =SUM(D83:G83) -> 1075.5
B84: Shear Loop with VSD installed | H84: =SUM(D85:D88) -> 14089.05
B85: Automation support | C85: 186 | D85: =C85*$B$2 -> 1333.62
B86: Piping loop | C86: 906 | D86: =C86*$B$2 -> 6496.02
B87: Pump cover | C87: 353 | D87: =C87*$B$2 -> 2531.01
B88: Motor base support | C88: 520 | D88: =C88*$B$2 -> 3728.4
B90: Powder Hopper 100L | C90: 2240 | D90: =C90*$B$2 -> 16060.8 | H90: =SUM(D90:G90) -> 16060.8 | I90: Quote 104452 from 15 July 2024
B91: 200 L liquid tank, half manway | C91: 3065 | D91: =C91*$B$2 -> 21976.05 | H91: =SUM(D91:G91) -> 21976.05 | I91: Quote 104486 from 16 August
B92: LC 500 | C92: 6590 | D92: =C92*$B$2 -> 47250.3 | H92: =SUM(D92:G92) -> 47250.3 | I92: 104625 April 2025
B93: LC 1000 | C93: 7360 | D93: =C93*$B$2 -> 52771.2 | H93: =SUM(D93:G93) -> 52771.2 | I93: 104625 April 2025
B94: LC 3000 | C94: =1.6*C93 -> 11776 | D94: =C94*$B$2 -> 84433.92 | H94: =SUM(D94:G94) -> 84433.92 | I94: Guess 1.6 x 1000L
B95: Standard 500 | C95: =C96-770 -> 10390 | D95: =C95*$B$2 -> 74496.3 | H95: =SUM(D95:G95) -> 74496.3 | I95: Updated based on Vacuum 1000 price
B96: Standard 1000 | C96: =C99 -> 11160 | D96: =C96*$B$2 -> 80017.2 | H96: =SUM(D96:G96) -> 80017.2 | I96: Updated based on Vacuum 1000 price
B97: Standard 3000 | C97: 18100 | D97: =C97*$B$2 -> 129777 | H97: =SUM(D97:G97) -> 129777 | I97: 44682
B98: Vacuum 500 | C98: =C99-770 -> 10390 | D98: =C98*$B$2 -> 74496.3 | H98: =SUM(D98:G98) -> 74496.3 | I98: Updated based on Vacuum 1000 price
B99: Vacuum 1000 | C99: =11160 -> 11160 | D99: =C99*$B$2 -> 80017.2 | H99: =SUM(D99:G99) -> 80017.2 | I99: Aug'25 - Q104587_Rev10 - CIP VERSION
B100: Vacuum 3000 | C100: =0.83*C103 -> 23646.7 | D100: =C100*$B$4 -> 126273.38 | H100: =SUM(D100:G100) -> 126273.38
B101: Process 500 | C101: 10267 | D101: =C101*$B$2 -> 73614.39 | H101: =SUM(D101:G101) -> 73614.39 | I101: Quote 10414612 from December 2023
B102: Process 1000 | C102: =10638+3000 -> 13638 | D102: =C102*$B$2 -> 97784.46 | H102: =SUM(D102:G102) -> 97784.46 | I102: Quote 104321 from March 2024 | J102: I added 3000 to pay for mixing leg support, service tray, agitator motor console, and possible tank diameter increaes
B103: Process 3000 | C103: 28490 | D103: =C103*$B$4 -> 152136.6 | H103: =SUM(D103:G103) -> 152136.6 | I103: Quteo 103669 - 19 Oct 2022
B104: Mixer flange tooling | C104: =3*115.85 -> 347.55 | D104: =C104*$B$2 -> 2491.9335 | H104: =SUM(D104:G104) -> 2491.9335 | I104: 15 2024, upgrade from HL under CVO P2311-04
B105: Bottom Flange | C105: =224.57 -> 224.57 | D105: =C105*$B$2 -> 1610.1669 | H105: =SUM(D105:G105) -> 1610.1669 | I105: 15 2024, upgrade from HL under CVO P2311-04
B106: Non-foam inlet | D106: =C106*$B$2 -> 0 | H106: =SUM(D106:G106) -> 0
B107: 4 off leg support | D107: =C107*$B$2 -> 0 | H107: =SUM(D107:G107) -> 0
B108: Bottom tray | D108: =C108*$B$2 -> 0 | H108: =SUM(D108:G108) -> 0
B109: Instrument sockets | D109: =C109*$B$2 -> 0 | H109: =SUM(D109:G109) -> 0
...

Sheet Cost tables
B2: ='Cost prices'!A2 -> Exchange rate DKK to USD | C2: ='Cost prices'!B2 -> 7.17
B3: ='Cost prices'!A3 -> Exchange rate DKK to EUR | C3: ='Cost prices'!B3 -> 7.46
B4: ='Cost prices'!A4 -> Exchange rate DKK to SGD | C4: ='Cost prices'!B4 -> 5.34
A6: Alfa Laval | C6: Updated 16 Jan 2026 | G6: Hoang Lam
A7: Item number | B7: Description | C7: Line total (EUR) | G7: No. | H7: Part No. | I7: Description | J7: USD | K7: EUR
A8: 9612650206 | B8: VALVE LKB 25/1" ISO W/W HNBR 316L | C8: 76.41 | G8: 3.01 | H8: FLY-SPECIAL-01 | I8: Bracket for actuator 1.5'' valve (304) | J8: 38 | K8: =HLcost[[#This Row],[USD]]*$C$2/$C$3 -> 36.522788
A9: 9612650207 | B9: VALVE LKB 38/1½" ISO W/W HNBR 316L | C9: 78.03 | G9: 3.02 | H9: FLY-SPECIAL-02 | I9: Bracket for actuator 2.0'' valve (304) | J9: 44 | K9: =HLcost[[#This Row],[USD]]*$C$2/$C$3 -> 42.289544
A10: 9612650208 | B10: VALVE LKB 51/2" ISO W/W HNBR 316L | C10: 85.59 | G10: 3.03 | H10: FLY-SPECIAL-03 | I10: Bracket for actuator 2.5'' valve (304) | J10: 50 | K10: =HLcost[[#This Row],[USD]]*$C$2/$C$3 -> 48.0563
A11: 9612650209 | B11: VALVE LKB 63,5/2½" ISO W/W HNBR 316L | C11: 106.92 | G11: 3.04 | H11: FLY-SPECIAL-04 | I11: Bracket for actuator 3.0'' valve (304) | J11: 50 | K11: =HLcost[[#This Row],[USD]]*$C$2/$C$3 -> 48.0563
A12: 9612650210 | B12: VALVE LKB 76/3" ISO W/W HNBR 316L | C12: 137.7 | G12: 3.05 | H12: FLY-SPECIAL-05 | I12: Coupler axle 8mm sq (304) | J12: 16 | K12: =HLcost[[#This Row],[USD]]*$C$2/$C$3 -> 15.378016
A13: 9612628161 | B13: VALVE LKB 25/1" ISO W/W EPDM 316L KIT HANDLE 1.1 W/2 POS TYPE A | C13: 94.23 | G13: 3.06 | H13: FLY-SPECIAL-06 | I13: Coupler axle 10mm sq (304) | J13: 19 | K13: =HLcost[[#This Row],[USD]]*$C$2/$C$3 -> 18.261394
A14: 9618581826 | B14: VALVE LKB 38/1½" ISO W/W PFA 316L KIT HANDLE 1.1 W/2 POS TYPE A | C14: 186.84 | G14: 3.07 | H14: FLY-SPECIAL-07 | I14: Coupler lower 8mm sq (304) | J14: 25 | K14: =HLcost[[#This Row],[USD]]*$C$2/$C$3 -> 24.02815
A15: 9611416470 | B15: BRACKET.FOR Ø85 LKLA/LKLA-T . FOR LKB/LKB-2/LKB ULTRA PURE VALVES 25-63.5/DN25-50 | C15: 7.56 | G15: 3.08 | H15: FLY-SPECIAL-08 | I15: Coupler lower 10mm sq (304) | J15: 28 | K15: =HLcost[[#This Row],[USD]]*$C$2/$C$3 -> 26.911528
A16: 9612194002 | B16: AIR-ACTUATOR LKLA-T Ø85 25-63.5/DN25-50 NC | C16: 268.92 | G16: 3.09 | H16: FLY-SPECIAL-09 | I16: Linkrod weld asm 8mm sq (304) | J16: 16 | K16: =HLcost[[#This Row],[USD]]*$C$2/$C$3 -> 15.378016
A17: 9612194003 | B17: AIR-ACTUATOR LKLA-T Ø85 76/DN65-80 NC | C17: 268.92 | G17: 3.1 | H17: FLY-SPECIAL-10 | I17: Linkrod weld asm 10mm sq (304) | J17: 19 | K17: =HLcost[[#This Row],[USD]]*$C$2/$C$3 -> 18.261394
A18: 9612045001 | B18: HANDLE 1.1 FOR LKB POS.A 2-POSITIONS 25-63.5/DN25-50 | C18: 21.33 | G18: 3.11 | H18: FLY-SPECIAL-11 | I18: LKB 38mm 1.5'' halfpart valve weldin (316) | J18: 112 | K18: =HLcost[[#This Row],[USD]]*$C$2/$C$3 -> 107.64611
A19: 9613437052 | B19: INSPECTION PORT LKDC-454-100 -N-1.4404, SS HANDLE | C19: 467.45 | G19: 3.12 | H19: FLY-SPECIAL-12 | I19: LKB 51mm 2'' halfpart valve weldin (316) | J19: 149 | K19: =HLcost[[#This Row],[USD]]*$C$2/$C$3 -> 143.20777
... A27: 9615400416 | B27: TTV50 ASI3 62N M12 1SV 6MM THINKTOP V50 AS-INTERFACE V3.0 62NODE M12 1 SOLENOID 3/2 6MM | C27: 393.05 | G27: 3.2 | H27: 240032-405 | I27: Welding jig for flange; SS304; OD250*24thk; lower part | J27: 115.85 | K27: =HLcost[[#This Row],[USD]]*$C$2/$C$3 -> 111.34645
A28: 9615400216 | B28: TTV70 ASI3 62N M12 1SV 5/2 6MM THINKTOP V70 AS-INTERFACE V3.0 62NODE M12 1 SOLENOID 5/2 6MM | C28: 515.2 | G28: 9612650207 | H28: x | I28: =_xlfn.TEXTJOIN(", ", TRUE, I8, $I$12,$I$14,$I$16,$I18,$I$22) -> Bracket for actuator 1.5'' valve (304), Coupler axle 8mm sq (304), Coupler lower 8mm sq (304), Linkrod weld asm 8mm sq (304), LKB 38mm 1.5'' halfpart valve weldin (316), D5mm rod for 8mm sq coupler axle (316) | K28: =K8+$K$12+$K$14+$K$16+$K18+$K$22 -> 203.75871
A29: 9612644027 | B29: BALL VALVE SBV-ISO51-W/W-MAN BALL VALVE SBV-ISO51-W/W-MAN - NBR | C29: 586.26 | G29: 9612650208 | H29: x | I29: =_xlfn.TEXTJOIN(", ", TRUE, I9, $I$12,$I$14,$I$16,$I19,$I$22) -> Bracket for actuator 2.0'' valve (304), Coupler axle 8mm sq (304), Coupler lower 8mm sq (304), Linkrod weld asm 8mm sq (304), LKB 51mm 2'' halfpart valve weldin (316), D5mm rod for 8mm sq coupler axle (316) | K29: =K9+$K$12+$K$14+$K$16+$K19+$K$22 -> 245.08713
A30: 9611444501 | B30: VALVE LKB 25/1" ISO W/W EPDM 316L | C30: 72.63 | G30: 9612650209 | H30: x | I30: =_xlfn.TEXTJOIN(", ", TRUE, I10, $I$12,$I$14,$I$16,$I20,$I$22) -> Bracket for actuator 2.5'' valve (304), Coupler axle 8mm sq (304), Coupler lower 8mm sq (304), Linkrod weld asm 8mm sq (304), LKB 63.5mm 2.5'' halfpart valve weldin (316), D5mm rod for 8mm sq coupler axle (316) | K30: =K10+$K$12+$K$14+$K$16+$K20+$K$22 -> 274.88204
A31: 9612047401 | B31: HANDLE 1.1 FOR LKB POS.A REGULATING 90 25-63.5/DN25-50 | C31: 61.02 | G31: 9612650210 | H31: x | I31: =_xlfn.TEXTJOIN(", ", TRUE, I11, $I$13,$I$15,$I$17,$I21,$I$23) -> Bracket for actuator 3.0'' valve (304), Coupler axle 10mm sq (304), Coupler lower 10mm sq (304), Linkrod weld asm 10mm sq (304), LKB 76mm 3'' halfpart valve weldin (316), D5mm rod for 10mm sq coupler axle (316) | K31: =K11+$K$13+$K$15+$K$17+$K21+$K$23 -> 356.57775
A32: 9611444531 | B32: VALVE LKB 63,5/2½" ISO W/W EPDM 316L | C32: 102.06
A33: 9612047402 | B33: HANDLE 1.1 FOR LKB POS.A REGULATING 90 76.1/DN65-80 | C33: 66.96
A34: 9611444541 | B34: VALVE LKB 76/3" ISO W/W. EPDM 316L | C34: 130.95

Sheet Margins
B3: Sell price | D3: Internal | E3: Margin | J3: External | K3: Wallk-away | N3: Internal Cost w/o engineering, contigency | O3: External Margin | P3: Exteranal Percent | Q3: Walk away maring | R3: Walk-away Percent
B4: External | C4: Walk-away | D4: Cost | E4: Internal | F4: Mark-up | G4: Special | H4: Nego | I4: Total | J4: Percent | K4: Percent
A5: Shear | B5: ='External Prices'!J40 -> 20058 | C5: ='Internal Sales price'!N218 -> 20037.653 | D5: =SUM('Internal Sales price'!N202:N204)/'Cost prices'!$B$3 -> 17032.005 | E5: ='Internal Sales price'!N221 -> 3005.648 | F5: =B5-C5 -> 20.346976 | I5: =SUM(E5:H5) -> 3025.9949 | J5: =I5/B5 -> 0.15086225 | K5: =E5/C5 -> 0.15 | N5: =('Internal Sales price'!E$202-SUM('Internal Sales price'!E$187:E$190))/'Cost prices'!$B$3 -> 11542.676 | O5: =B5-N5 -> 8515.3239 | P5: =O5/N5 -> 0.73772528 | Q5: =C5-N5 -> 8494.977 | R5: =Q5/C5 -> 0.4239507
A6: Shear L | B6: ='External Prices'!K40 -> 21869 | C6: ='Internal Sales price'!P218 -> 21846.523 | D6: =SUM('Internal Sales price'!P202:P204)/'Cost prices'!$B$3 -> 18569.545 | E6: ='Internal Sales price'!P221 -> 3276.9785 | F6: =B6-C6 -> 22.476816 | I6: =SUM(E6:H6) -> 3299.4553 | J6: =I6/B6 -> 0.15087362 | K6: =E6/C6 -> 0.15
A7: Injector | B7: ='External Prices'!L40 -> 25050 | C7: ='Internal Sales price'!R218 -> 25024.162 | D7: =SUM('Internal Sales price'!R202:R204)/'Cost prices'!$B$3 -> 21270.538 | E7: ='Internal Sales price'!R221 -> 3753.6243 | F7: =B7-C7 -> 25.838169 | I7: =SUM(E7:H7) -> 3779.4624 | J7: =I7/B7 -> 0.15087674 | K7: =E7/C7 -> 0.15
A8: Vortex VN | B8: ='External Prices'!N40 -> 29811 | C8: ='Internal Sales price'!V218 -> 29780.701 | D8: =SUM('Internal Sales price'!V202:V204)/'Cost prices'!$B$3 -> 25313.596 | E8: ='Internal Sales price'!V221 -> 4467.1052 | F8: =B8-C8 -> 30.298936 | I8: =SUM(E8:H8) -> 4497.4041 | J8: =I8/B8 -> 0.15086391 | K8: =E8/C8 -> 0.15
A9: Vortex VN 800 | B9: ='External Prices'!O40 -> 52357 | C9: ='Internal Sales price'!X218 -> 52304.244 | D9: =SUM('Internal Sales price'!X202:X204)/'Cost prices'!$B$3 -> 38054.231 | E9: ='Internal Sales price'!X221 -> 14250.013 | F9: =B9-C9 -> 52.756295 | I9: =SUM(E9:H9) -> 14302.769 | J9: =I9/B9 -> 0.27317778 | K9: =E9/C9 -> 0.27244467
A10: Vortex Vacuum 2000 | B10: ='External Prices'!P40 -> 104435 | C10: ='Internal Sales price'!Z218 -> 104330.02 | D10: =SUM('Internal Sales price'!Z202:Z204)/'Cost prices'!$B$3 -> 71622.765 | E10: ='Internal Sales price'!Z221 -> 27250.287 | F10: =B10-C10 -> 104.97555 | I10: =SUM(E10:H10) -> 27355.262 | J10: =I10/B10 -> 0.26193577 | K10: =E10/C10 -> 0.26119314
A11: Bottom Shear | B11: ='External Prices'!$Q$40 -> 15447 | C11: ='Internal Sales price'!$AB$218 -> 15431.1 | D11: =SUM('Internal Sales price'!AB202:AB204)/'Cost prices'!$B$3 -> 10801.77 | E11: ='Internal Sales price'!AB221 -> 4629.3301 | F11: =B11-C11 -> 15.899718 | I11: =SUM(E11:H11) -> 4645.2298 | J11: =I11/B11 -> 0.30072052 | K11: =E11/C11 -> 0.3
A12: LC500 | B12: ='External Prices'!R40 -> 36809 | C12: ='Internal Sales price'!AD218 -> 36771.894 | D12: =SUM('Internal Sales price'!AD202:AD204)/'Cost prices'!$B$3 -> 28231.324 | E12: ='Internal Sales price'!AD221 -> 8540.5702 | F12: =B12-C12 -> 37.105613 | I12: =SUM(E12:H12) -> 8577.6759 | J12: =I12/B12 -> 0.23303203 | K12: =E12/C12 -> 0.2322581
A13: LC1000 | B13: ='External Prices'!S40 -> 37818 | C13: ='Internal Sales price'!AE218 -> 37779.86 | D13: =SUM('Internal Sales price'!AE202:AE204)/'Cost prices'!$B$3 -> 29008.395 | E13: ='Internal Sales price'!AE221 -> 8771.4656 | F13: =B13-C13 -> 38.139923 | I13: =SUM(E13:H13) -> 8809.6055 | J13: =I13/B13 -> 0.23294742 | K13: =E13/C13 -> 0.23217306
A14: LC3000 | B14: ='External Prices'!T40 -> 49680 | C14: ='Internal Sales price'!AF218 -> 49629.602 | D14: =SUM('Internal Sales price'!AF202:AF204)/'Cost prices'!$B$3 -> 35923.085 | E14: ='Internal Sales price'!AF221 -> 10969.52 | F14: =B14-C14 -> 50.398163 | I14: =SUM(E14:H14) -> 11019.918 | J14: =I14/B14 -> 0.221818 | K14: =E14/C14 -> 0.22102777
A15: Standard 500 | B15: ='External Prices'!U40 -> 56083 | C15: ='Internal Sales price'!AH218 -> 56026.712 | D15: =SUM('Internal Sales price'!AH202:AH204)/'Cost prices'!$B$3 -> 40155.097 | E15: ='Internal Sales price'!AH221 -> 12812.179 | F15: =B15-C15 -> 56.288329 | I15: =SUM(E15:H15) -> 12868.467 | J15: =I15/B15 -> 0.22945397 | K15: =E15/C15 -> 0.22867983
A16: Standard 1000 | B16: ='External Prices'!V40 -> 57191 | C16: ='Internal Sales price'!AI218 -> 57132.847 | D16: =SUM('Internal Sales price'!AI202:AI204)/'Cost prices'!$B$3 -> 40932.167 | E16: ='Internal Sales price'!AI221 -> 13082.039 | F16: =B16-C16 -> 58.152708 | I16: =SUM(E16:H16) -> 13140.191 | J16: =I16/B16 -> 0.22975978 | K16: =E16/C16 -> 0.22897579
A17: Vacuum 500 | B17: ='External Prices'!W40 -> 95206 | C17: ='Internal Sales price'!AK218 -> 95110.099 | D17: =SUM('Internal Sales price'!AK202:AK204)/'Cost prices'!$B$3 -> 61611.257 | E17: ='Internal Sales price'!AK221 -> 28804.651 | F17: =B17-C17 -> 95.901335 | I17: =SUM(E17:H17) -> 28900.552 | J17: =I17/B17 -> 0.3035581 | K17: =E17/C17 -> 0.30285586
A18: Vacuum 1000 | B18: ='External Prices'!X40 -> 117464 | C18: ='Internal Sales price'!AL218 -> 117345.93 | D18: =SUM('Internal Sales price'!AL202:AL204)/'Cost prices'!$B$3 -> 76135.071 | E18: ='Internal Sales price'!AL221 -> 35410.095 | F18: =B18-C18 -> 118.0662 | I18: =SUM(E18:H18) -> 35528.161 | J18: =I18/B18 -> 0.30246 | K18: =E18/C18 -> 0.30175818 | N18: =('Internal Sales price'!AL$202-SUM('Internal Sales price'!AL$187,ABR$142))/'Cost prices'!$B$3 -> 71713.318 | O18: =B18-N18 -> 45750.682 | P18: =O18/N18 -> 0.63796632 | Q18: =C18-N18 -> 45632.616 | R18: =Q18/C18 -> 0.38887258
A19: Vacuum 3000 | B19: ='External Prices'!Y40 -> 130198 | C19: ='Internal Sales price'!AM218 -> 130067.61 | D19: =SUM('Internal Sales price'!AM202:AM204)/'Cost prices'!$B$3 -> 83101.629 | E19: ='Internal Sales price'!AM221 -> 40634.43 | F19: =B19-C19 -> 130.38773 | I19: =SUM(E19:H19) -> 40764.818 | J19: =I19/B19 -> 0.31309865 | K19: =E19/C19 -> 0.31241006
A20: Process 500 | B20: ='External Prices'!Z40 -> 120644 | C20: ='Internal Sales price'!AO218 -> 120523.11 | D20: =SUM('Internal Sales price'!AO202:AO204)/'Cost prices'!$B$3 -> 80782.523 | E20: ='Internal Sales price'!AO221 -> 33585.729 | F20: =B20-C20 -> 120.88913 | I20: =SUM(E20:H20) -> 33706.619 | J20: =I20/B20 -> 0.2793891 | K20: =E20/C20 -> 0.2786663
A21: Process 1000 | B21: ='External Prices'!AA40 -> 148861 | C21: ='Internal Sales price'!AP218 -> 148712.06 | D21: =SUM('Internal Sales price'!AP202:AP204)/'Cost prices'!$B$3 -> 97152.775 | E21: ='Internal Sales price'!AP221 -> 44157.167 | F21: =B21-C21 -> 148.94259 | I21: =SUM(E21:H21) -> 44306.109 | J21: =I21/B21 -> 0.2976341 | K21: =E21/C21 -> 0.29693064
A22: Process 3000 | B22: ='External Prices'!AB40 -> 170773 | C22: ='Internal Sales price'!AQ218 -> 170601.77 | D22: =SUM('Internal Sales price'!AQ202:AQ204)/'Cost prices'!$B$3 -> 113610.28 | E22: ='Internal Sales price'!AQ221 -> 48335.463 | F22: =B22-C22 -> 171.23092 | I22: =SUM(E22:H22) -> 48506.694 | J22: =I22/B22 -> 0.28404194 | K22: =E22/C22 -> 0.28332334
A23: Control Panel & VSD, 11 kW | B23: ='External Prices'!E41 -> 5606.6659 | C23: ='Internal Sales price'!AS218 -> 5601.0593 | D23: =SUM('Internal Sales price'!AS202:AS204)/'Cost prices'!$B$3 -> 4760.9004 | E23: ='Internal Sales price'!AS221 -> 840.15889 | F23: =B23-C23 -> 5.6066659 | I23: =SUM(E23:H23) -> 845.76556 | J23: =I23/B23 -> 0.15085 | K23: =E23/C23 -> 0.15
A24: Control Panel & VSD, 15 kW | B24: ='External Prices'!E42 -> 5766.122 | C24: ='Internal Sales price'!AT218 -> 5760.3559 | D24: =SUM('Internal Sales price'!AT202:AT204)/'Cost prices'!$B$3 -> 4896.3025 | E24: ='Internal Sales price'!AT221 -> 864.05339 | F24: =B24-C24 -> 5.766122 | I24: =SUM(E24:H24) -> 869.81951 | J24: =I24/B24 -> 0.15085 | K24: =E24/C24 -> 0.15
A25: Control Panel & VSD, 18.5 kW | B25: ='External Prices'!E43 -> 5925.5781 | C25: ='Internal Sales price'!AU218 -> 5919.6525 | D25: =SUM('Internal Sales price'!AU202:AU204)/'Cost prices'!$B$3 -> 5031.7047 | E25: ='Internal Sales price'!AU221 -> 887.94788 | F25: =B25-C25 -> 5.9255781 | I25: =SUM(E25:H25) -> 893.87346 | J25: =I25/B25 -> 0.15085 | K25: =E25/C25 -> 0.15
A26: Control Panel & VSD, 22 kW | B26: ='External Prices'!E44 -> 6786.5913 | C26: ='Internal Sales price'!AV218 -> 6779.8047 | D26: =SUM('Internal Sales price'!AV202:AV204)/'Cost prices'!$B$3 -> 5762.834 | E26: ='Internal Sales price'!AV221 -> 1016.9707 | F26: =B26-C26 -> 6.7865913 | I26: =SUM(E26:H26) -> 1023.7573 | J26: =I26/B26 -> 0.15085 | K26: =E26/C26 -> 0.15
A27: Control Panel & VSD, 30 kW | B27: ='External Prices'!E45 -> 5430.3028 | C27: ='Internal Sales price'!AW218 -> 5424.8725 | D27: =SUM('Internal Sales price'!AW202:AW204)/'Cost prices'!$B$3 -> 4611.1417 | E27: ='Internal Sales price'!AW221 -> 813.73088 | F27: =B27-C27 -> 5.4303028 | I27: =SUM(E27:H27) -> 819.16118 | J27: =I27/B27 -> 0.15085 | K27: =E27/C27 -> 0.15
A28: Frequency Converter 11 kW | B28: ='External Prices'!E46 -> 2957.4438 | C28: ='Internal Sales price'!AX218 -> 2954.4863 | D28: =SUM('Internal Sales price'!AX202:AX204)/'Cost prices'!$B$3 -> 2511.3134 | E28: ='Internal Sales price'!AX221 -> 443.17295 | F28: =B28-C28 -> 2.9574438 | I28: =SUM(E28:H28) -> 446.13039 | J28: =I28/B28 -> 0.15085 | K28: =E28/C28 -> 0.15
A29: Frequency Converter 15 kW | B29: ='External Prices'!E47 -> 3328.1543 | C29: ='Internal Sales price'!AY218 -> 3324.8262 | D29: =SUM('Internal Sales price'!AY202:AY204)/'Cost prices'!$B$3 -> 2826.1022 | E29: ='Internal Sales price'!AY221 -> 498.72393 | F29: =B29-C29 -> 3.3281543 | I29: =SUM(E29:H29) -> 502.05208 | J29: =I29/B29 -> 0.15085 | K29: =E29/C29 -> 0.15
A30: Frequency Converter 18.5 kW | B30: ='External Prices'!E48 -> 3625.767 | C30: ='Internal Sales price'!AZ218 -> 3622.1413 | D30: =SUM('Internal Sales price'!AZ202:AZ204)/'Cost prices'!$B$3 -> 3078.8201 | E30: ='Internal Sales price'!AZ221 -> 543.32119 | F30: =B30-C30 -> 3.625767 | I30: =SUM(E30:H30) -> 546.94696 | J30: =I30/B30 -> 0.15085 | K30: =E30/C30 -> 0.15
A31: Frequency Converter 22 kW | B31: ='External Prices'!E49 -> 3923.3797 | C31: ='Internal Sales price'!BA218 -> 3919.4564 | D31: =SUM('Internal Sales price'!BA202:BA204)/'Cost prices'!$B$3 -> 3331.5379 | E31: ='Internal Sales price'!BA221 -> 587.91845 | F31: =B31-C31 -> 3.9233797 | I31: =SUM(E31:H31) -> 591.84183 | J31: =I31/B31 -> 0.15085 | K31: =E31/C31 -> 0.15
A32: Table | B32: ='External Prices'!G65 -> 2432.5286 | C32: ='Internal Sales price'!BE218 -> 2430.0961 | D32: =SUM('Internal Sales price'!BE202:BE204)/'Cost prices'!$B$3 -> 2060.0569 | E32: ='Internal Sales price'!BE221 -> 370.03917 | F32: =B32-C32 -> 2.4325286 | I32: =SUM(E32:H32) -> 372.4717 | J32: =I32/B32 -> 0.1531212 | K32: =E32/C32 -> 0.15227347
A33: Table VN | B33: ='External Prices'!N65 -> 1085.7101 | C33: ='Internal Sales price'!BF218 -> 0 | D33: =SUM('Internal Sales price'!BF202:BF204)/'Cost prices'!$B$3 -> 0 | E33: ='Internal Sales price'!BF221 -> 0 | F33: =B33-C33 -> 1085.7101 | I33: =SUM(E33:H33) -> 1085.7101 | J33: =I33/B33 -> 1 | K33: =E33/C33 -> #DIV/0!
A34: Mesh | B34: ='External Prices'!G64 -> 904.2645 | C34: ='Internal Sales price'!BG218 -> 903.36024 | D34: =SUM('Internal Sales price'!BG202:BG204)/'Cost prices'!$B$3 -> 767.8562 | E34: ='Internal Sales price'!BG221 -> 135.50404 | F34: =B34-C34 -> 0.9042645 | I34: =SUM(E34:H34) -> 136.4083 | J34: =I34/B34 -> 0.15085 | K34: =E34/C34 -> 0.15
A35: Seal flush | B35: ='External Prices'!E62 -> 770.50242 | C35: ='Internal Sales price'!BH218 -> 769.73192 | D35: =SUM('Internal Sales price'!BH202:BH204)/'Cost prices'!$B$3 -> 654.27213 | E35: ='Internal Sales price'!BH221 -> 115.45979 | F35: =B35-C35 -> 0.77050242 | I35: =SUM(E35:H35) -> 116.23029 | J35: =I35/B35 -> 0.15085 | K35: =E35/C35 -> 0.15
A36: Connection to Client | B36: ='External Prices'!E63 -> 225.33293 | C36: ='Internal Sales price'!BI218 -> 225.1076 | D36: =SUM('Internal Sales price'!BI202:BI204)/'Cost prices'!$B$3 -> 191.34146 | E36: ='Internal Sales price'!BI221 -> 33.76614 | F36: =B36-C36 -> 0.22533293 | I36: =SUM(E36:H36) -> 33.991473 | J36: =I36/B36 -> 0.15085 | K36: =E36/C36 -> 0.15
A37: Packaging | B37: ='External Prices'!E60 -> 709.33688 | C37: ='Internal Sales price'!BJ218 -> 708.62755 | D37: =SUM('Internal Sales price'!BJ202:BJ204)/'Cost prices'!$B$3 -> 602.33341 | E37: ='Internal Sales price'!BJ221 -> 106.29413 | F37: =B37-C37 -> 0.70933688 | I37: =SUM(E37:H37) -> 107.00347 | J37: =I37/B37 -> 0.15085 | K37: =E37/C37 -> 0.15
A38: Suction lance | B38: ='External Prices'!G72 -> 5092.2966 | C38: ='Internal Sales price'!BK218 -> 5087.2043 | D38: =SUM('Internal Sales price'!BK202:BK204)/'Cost prices'!$B$3 -> 4324.1236 | E38: ='Internal Sales price'!BK221 -> 763.08064 | F38: =B38-C38 -> 5.0922966 | I38: =SUM(E38:H38) -> 768.17294 | J38: =I38/B38 -> 0.15085 | K38: =E38/C38 -> 0.15

Sheet Unit parts
A5: Unit price | D5: Shear | E5: Loop | F5: Injector | G5: Vortex
A6: Basis | B6: Mixer unit (motor, VSD, mixer unit w. impeller,stator, pump house) | D6: Mixer unit leveret af TPS
A7: Inlet/Outlet | B7: Cone down to 2.5" - allow for SMS, Clamp or flange connection | C7: Pcs | D7: 2 | E7: 2 | F7: 2 | G7: 2
A8: Feet | B8: NGI Varenummer 1017651 - Maskinsko XH065-XH16150-RHOX1650 Blå gummi | C8: Pcs | D8: 4 | E8: 4 | F8: 7 | G8: 7
A9: Drain | B9: Alfa Laval 1" manual - 9612628161 | C9: Pcs | D9: 0 | E9: 1 | F9: 1 | G9: 1
A10: Full Bore | B10: DVC Full bore valve Varenummer 1351510050 DN50 - PN100 3-delt kuglehane 1351FB Materialer: CF8M/AISI316/PTFE +KF | C10: Pcs | D10: 0 | E10: 0 | F10: 1 | G10: 0
A11: Manway | B11: Alfa Laval 9613437173 PERSONNEL ACCESS LKDC-518-200 -F-1.4404, SS HANDLE | C11: Pcs | D11: 0 | E11: 0 | F11: 0 | G11: 1
A12: Regulating valve | B12: Alfa Laval 9618582904 VALVE LKB 63,5/2½" ISO W/W PFA 316L KIT HANDLE 1.1 W/REGULATION | C12: Pcs | D12: 0 | E12: 0 | F12: 0 | G12: 3
A13: CIP ball | B13: Alfa Laval TE14B23001 SaniMicro 360° 3/4" WELD | C13: Pcs | D13: 0 | E13: 0 | F13: 0 | G13: 1
A14: CIP valve | B14: Alfa Laval 9618581826 VALVE LKB 38/1½" ISO W/W PFA 316L KIT HANDLE 1.1 W/2 POS TYPE | C14: PCS | D14: 0 | E14: 0 | F14: 0 | G14: 1
A15: CIP pneumatic | B15: Alfa Laval 9612194002 LUFTMOTOR LKLA-T Ö85 25-63,5/ 25-63.5/DN25-50 NC | C15: PCS | D15: 0 | E15: 0 | F15: 0 | G15: 1
A16: Air Vent | B16: Alfa Laval 9612945853 RELIEF VALVE, TWOWAY 316 MAX. FLOW 600hl/h, OIL WORKING | C16: Pcs | D16: 0 | E16: 0 | F16: 0 | G16: 1
A17: Safety switch | B17: IFM MN501S - MN44008-AKOG/6m/-H Safety switch | C17: Pcs | D17: 0 | E17: 0 | F17: 0 | G17: 1
A18: Level transmitter | B18: IFM LMT102 LMCCE-A12E-QSKG-2/US Level transmitter IFM E43309 ADAPT G1/2-WELD SLEEVE 3A | C18: Pcs | D18: 0 | E18: 0 | F18: 0 | G18: 1
A20: Options
A21: Seal Water
A22: RS components | B22: ST/ST Y STRAINER 1/4" - Varenummer: 4992694 | D22: 1 | E22: 1 | F22: 1 | G22: 1
A23: Bürkert | B23: *2/2-waY-solenoId valve, servo assisted 6213-EV-A10,0AAVAGM82-6-024/DC-10 *NA38 | D23: 1 | E23: 1 | F23: 1 | G23: 1
A24: Bürkert | B24: *Kabelstik 2518 28mm Form A UL approva 2518-A-BCS/UC-00-3-N50-00-0-00000 JLO4 | D24: 1 | E24: 1 | F24: 1 | G24: 1
A25: DVC | B25: Varenummer E0226372553 1/4" PN420 Nåleventil Fig. 3710/Fig. 226 3 Materialer: Rustfrit stål 1.4401 Tilslut./Betjening: BSPP Gevind/Håndhjul | D25: 1 | E25: 1 | F25: 1 | G25: 1
A26: Control system
A27: Norland | B27: Contorl panel, TPS koeber kontrol systemet fra Nordland | D27: U3S & extern elektrikker kost
A29: Table | B29: Table as desigend for Thailand plus additional 4 NGI feet | C29: Pcs | D29: 0 | E29: 0 | F29: 1 | G29: 0

Sheet Logistics
B2: EURO pallets | C2: Weight (kg) | D2: Type | E2: Incoterms | F2: Distination | G2: DKK | H2: Sell price EUR
A3: Injctor | B3: 2 | D3: air | E3: CIF | F3: Bangkok | G3: 10500 | H3: =G3/0.7/7.44 -> 2016.129
A4: Injctor | B4: 2 | D4: truck | E4: DAP | F4: Gernamy | G4: 2750 | H4: =G4/0.7/7.44 -> 528.03379
A5: Loop | B5: 1 | C5: 440 | D5: air | E5: CIF | F5: CPT | G5: =1800*7.45 -> 13410 | H5: =G5/0.7/7.44 -> 2574.8848
A6: Vortex | B6: 1 | C6: 440 | D6: air | E6: DDP | F6: Chile | G6: =3500*7.45 -> 26075 | H6: =G6/0.7/7.44 -> 5006.7204 | I6: Cost is without the DDP taxes, so likely a CIF price.
A7: Vacuum 1000` | D7: SEA | E7: CIF | F7: Gernamy | G7: 30000 | H7: =G7/0.7/7.44 -> 5760.3687 | I7: Estimate for 20ft from Hoang Lam to Hamburg sea port
A8: Container 20 ft | E8: DAP | F8: Kuwait | G8: =4000*7 -> 28000 | H8: =G8/0.7/7.44 -> 5376.3441 | I8: Vietnam to Kuwait
A9: Vacuum 1000` | B9: 2 | C9: 528 | D9: air | E9: DAP | F9: Vietnam | G9: 25152 | H9: =G9/0.7/7.44 -> 4829.4931 | I9: ??

Sheet Price Split Quote
A7: Vacuum 500 | D7: Main Scope: | F7: MixSing Vacuum XXX | I7: Vacuum 1000 | L7: Vacuum 3000
D8: Plant | F8: Included
D9: Engineering
D10: Control: Functional Description
D11: Remote Project Management
D12: Weld checks X-ray of 10% for tank body and 100% T-joint
D13: Price, EXW w/o packaging, Vietnam, 1 unit | E13: EUR | F13: ='External Prices'!W40 -> 95206 | G13: Included | I13: ='External Prices'!X40 -> 117464 | J13: Included | L13: ='External Prices'!Y40 -> 130198 | M13: Included
D15: Additional Services Frequently Bought by Customers
D16: Polish Vacuum 1000 top - bottom - shell internal 0.6 µm | E16: EUR | F16: ='External Prices'!W54 -> 437.89977 | G16: Exluded | I16: ='External Prices'!X54 -> 437.89977 | J16: Exluded
D17: Polish Vacuum 1000 top - bottom - shell external 0.6 µm | E17: EUR | F17: ='External Prices'!W55 -> 437.89977 | G17: Exluded | I17: ='External Prices'!X55 -> 437.89977 | J17: Exluded
D18: Polish Vacuum 1000 top - bottom - shell internal 0.3 µm | E18: EUR | F18: ='External Prices'!W56 -> 903.16827 | G18: Exluded | I18: ='External Prices'!X56 -> 903.16827 | J18: Exluded
D19: Polish Vacuum 1000 top - bottom - shell external 0.3 µm | E19: EUR | F19: ='External Prices'!W57 -> 903.16827 | G19: Exluded | I19: ='External Prices'!X57 -> 903.16827 | J19: Exluded
D20: Polish Vacuum 1000 leg support external 0.6 µm - 4 pcs | E20: EUR | F20: ='External Prices'!W58 -> 272.01303 | G20: Exluded | I20: ='External Prices'!X58 -> 272.01303 | J20: Exluded
D21: Polish Vacuum 1000 leg support external 0.3 µm - 4 pcs | E21: EUR | F21: ='External Prices'!W59 -> 867.04154 | G21: Exluded | I21: ='External Prices'!X59 -> 867.04154 | J21: Exluded
D22: Packaging for freight | E22: EUR | F22: ='External Prices'!W60 -> Included | G22: Included | I22: ='External Prices'!X60 -> Included | J22: Included | L22: ='External Prices'!Y60 -> Included | M22: Included
D23: EWX upgraded to FCA at workshop Vietnam. | E23: EUR | F23: ='External Prices'!W61 -> 642.71174 | G23: Included | I23: ='External Prices'!X61 -> 642.71174 | J23: Included | L23: ='External Prices'!Y61 -> 642.71174 | M23: Included
D24: Seal Flush on high-shear rotor-stator unit | E24: EUR | F24: ='External Prices'!W62 -> Included | G24: Included | I24: ='External Prices'!X62 -> Included | J24: Included | L24: ='External Prices'!Y62 -> Included | M24: Included
D25: Seal Flush on vacuum pump | E25: EUR | F25: ='External Prices'!W62 -> Included | G25: Included | I25: ='External Prices'!X62 -> Included | J25: Included | L25: ='External Prices'!Y62 -> Included | M25: Included
D26: Process connection: SMS, Clamp, or Flange | E26: EUR | F26: ='External Prices'!W63 -> 225.33293 | G26: Included | I26: ='External Prices'!X63 -> 225.33293 | J26: Included | L26: ='External Prices'!Y63 -> 225.33293 | M26: Included
D27: Tangential tank inlet incl. actuated BV, 1 pcs | E27: EUR | F27: ='External Prices'!W84 -> 796.08452 | G27: Included | I27: ='External Prices'!X84 -> 796.08452 | J27: Included | L27: ='External Prices'!Y84 -> 796.08452 | M27: Included
D28: Minor ingredients funnel, 25 litre | E28: EUR | F28: ='External Prices'!W86 -> 946.54848 | G28: Included | I28: ='External Prices'!X86 -> 946.54848 | J28: Included | L28: ='External Prices'!Y86 -> 946.54848 | M28: Included
